Workbook

Sheet dataset_overview
A1: dataset | B1: original_length | C1: sampled_length | D1: yfirferð
A2: arc_is_random_sample.csv | B2: 1116 | C2: 112 | D2: 3 | E2: alexandrainst/m_arc
A3: scala_is_random_sample.csv | B3: 1024 | C3: 102 | D3: 3
A4: iceEC_random_sample.csv | B4: 58239 | C4: 250 | D4: 3 | F4: yfirfarið | G4: =SUMIFS(C2:C13,D2:D13,">0") -> 1736 | H4: =G4/sum(C2:C13) -> 1 | J4: Yfirferðarkóðar
A5: nqii_random_sample.csv | B5: 2132 | C5: 213 | D5: 3 | F5: eftir | G5: =SUMIFS(C2:C13,D2:D13,"") -> 0 | H5: =G5/sum(C2:C13) -> 0 | J5: IC | K5: incomprehensible | L5: Skilgreining á IC: one of the following (anywhere in the example): severely flawed example, clearly/poorly machine-translated, incomprehensible
A6: icelandic_qa_random_sample.csv | B6: 2000 | C6: 200 | D6: 3 | J6: F | K6: flawed | L6: Skilgreining á F: one of the following: flawed example, contains spelling or grammatical errors, is wrong (e.g. wrong answer to a question)
A7: belebele_is_random_sample.csv | B7: 900 | C7: 90 | D7: 3 | F7: tvíyfirfarið | G7: =SUMIFS(C2:C13,D2:D13,">=2") -> 1736 | H7: =G7/sum(C2:C13) -> 1 | J7: OK | K7: okay
A8: multiwikiqa_is_random_sample.csv | B8: 5004 | C8: 250 | D8: 3 | F8: eftir | G8: =sum(C2:C13)-G7 -> 0 | H8: =G8/sum(C2:C13) -> 0
A9: arc_challenge_is_random_sample.csv | B9: 1119 | C9: 112 | D9: 3 | E9: Miðeind | J9: rater_1 | K9: Finnur
A10: mmlu_is_random_sample.csv | B10: 277 | C10: 28 | D10: 3 | F10: þríyfirfarið | G10: =SUMIFS(C2:C13,D2:D13,"3") -> 1736 | H10: =G10/sum(C2:C13) -> 1 | J10: rater_2 | K10: Steinunn
A11: winogrande_is_random_sample.csv | B11: 1088 | C11: 109 | D11: 3 | F11: eftir | G11: =SUM(C2:C13)-G10 -> 0 | H11: =G11/sum(C2:C13) -> 0 | J11: rater_3 | K11: Steinþór
A12: hellaswag_is_random_sample.csv | B12: 9368 | C12: 250 | D12: 3
A13: ged_is_random_sample.csv | B13: 200 | C13: 20 | D13: 3
A14: inflection_is_random_sample.csv | B14: 2400 | C14: 240
A15: iceling_random_sample.csv | B15: 1160 | C15: 116
A18: Dataset | B18: IC | C18: F | D18: OK | E18: Samanlagt | G18: Almennar aths.
A19: arc_is_random_sample.csv | B19: =countif(arc_is_random_sample!M2:M113,"IC") -> 44 | C19: =countif(arc_is_random_sample!M2:M113,"F") -> 50 | D19: =countif(arc_is_random_sample!M2:M113,"OK") -> 18 | E19: =SUM(B19:D19) -> 112 | F19: =if(E19=C2,"stemmir","stemmir ekki") -> stemmir | G19: Iðulega rangt fall í svörum m.v. spurningu, hvort í stað hvaða/hvert o.s.frv., skrýtin "íslensk" orð (handlinsa). Kynjamisræmi (Nemandi ... hún, Einstaklingur veiðir og mælir stóran fisk sem kallast lúða. Hún heldur ... þetta er ekki endilega óeðlilegt á íslensku, en samt ekki alveg eins og í ensku!), ákveðinn greinir í ensku sem á ekki endilega við í íslensku, í svörum eru stundum allar þrjár útgáfur af they á íslensku. "long hair" varð "hár" í íslenskri þýðingu og það skipti sköpum!
A20: scala_is_random_sample.csv | B20: =countif(scala_is_random_sample!D2:D114,"IC") -> 6 | C20: =countif(scala_is_random_sample!D2:D114,"F") -> 10 | D20: =countif(scala_is_random_sample!D2:D114,"OK") -> 86 | E20: =SUM(B20:D20) -> 102 | F20: =if(E20=C3,"stemmir","stemmir ekki") -> stemmir | G20: Aðallega Alþingisræður, i.e. talmál, </percent>, Gripið fram í, Forseti hringir, og setningar stundum réttar þrátt fyrir breytingar.
A21: iceEC_random_sample.csv | B21: =countif(iceEC_random_sample!F1:F251,"IC") -> 42 | C21: =countif(iceEC_random_sample!F1:F251,"F") -> 4 | D21: =countif(iceEC_random_sample!F1:F251,"OK") -> 204 | E21: =SUM(B21:D21) -> 250 | F21: =if(E21=C4,"stemmir","stemmir ekki") -> stemmir | G21: Ath. EuroEval pælir ekki í leiðréttum setningum, en stundum eru enn villur í leiðréttum setningum, réttar setningar eru stundum rangar og iceEC hefur nokkra villuflokka, style á t.d. illa við í svona prófi og hefur lítið með "grammatically correct" að gera.
A22: nqii_random_sample.csv | B22: =countif(nqii_random_sample!F1:F251,"IC") -> 41 | C22: =countif(nqii_random_sample!F1:F251,"F") -> 46 | D22: =countif(nqii_random_sample!F1:F251,"OK") -> 126 | E22: =SUM(B22:D22) -> 213 | F22: =if(E22=C5,"stemmir","stemmir ekki") -> stemmir | G22: stundum ekkert samhengi milli hins eiginlega samhengis og spurningar, og oft eru villur í spurningum (stafsetningar- og málfræðivillur) -- (STEINÞÓR): Spurningar um "hver er núverandi..." "Hvar spilar X í dag" o.s.frv. eru handónýtar í svona próf, nema textinn sé bara bull og það sé verið að spyrja úr honum. Annars getur rétt svar innan textans
A23: icelandic_qa_random_sample.csv | B23: =countif(icelandic_qa_random_sample!F2:F251,"IC") -> 8 | C23: =countif(icelandic_qa_random_sample!F1:F251,"F") -> 20 | D23: =countif(icelandic_qa_random_sample!F1:F251,"OK") -> 172 | E23: =SUM(B23:D23) -> 200 | F23: =if(E23=C6,"stemmir","stemmir ekki") -> stemmir
A24: belebele_is_random_sample.csv | B24: =countif(belebele_is_random_sample!L2:L91,"IC") -> 14 | C24: =countif(belebele_is_random_sample!L2:L91,"F") -> 51 | D24: =countif(belebele_is_random_sample!L2:L91,"OK") -> 25 | E24: =SUM(B24:D24) -> 90 | F24: =if(E24=C7,"stemmir","stemmir ekki") -> stemmir | G24: gögnin eiga að hafa verið þýdd af fagmönnum en bera þess yfirleitt ekki merki (vélþýðingarvillur/óeðlilegar villur koma fyrir...)
A25: multiwikiqa_is_random_sample.csv | B25: =countif(multiwikiqa_is_random_sample!F2:F251,"IC") -> 48 | C25: =countif(multiwikiqa_is_random_sample!F2:F251,"F") -> 84 | D25: =countif(multiwikiqa_is_random_sample!F2:F251,"OK") -> 118 | E25: =SUM(B25:D25) -> 250 | F25: =if(E25=C8,"stemmir","stemmir ekki") -> stemmir | G25: Fyrsta persóna í spurningum (Hvernig get ég orðið múslimi?), bullspurningar, villur í spurningum, spurningar samræmast ekki alltaf svari (t.d. út frá íslensku fallakerfi, svo sem "Hver var pabbi Fáfnis og Regins? Hreiðmars bónda" en kannski er ósanngjarnt að gagnrýna það (?), orðið 'pabbi' nær alltaf notað um föður einhvers
A26: arc_challenge_is_random_sample.csv | B26: =countif(arc_challenge_is_random_sample!E2:E251,"IC") -> 8 | C26: =countif(arc_challenge_is_random_sample!E2:E251,"F") -> 50 | D26: =countif(arc_challenge_is_random_sample!E2:E251,"OK") -> 54 | E26: =SUM(B26:D26) -> 112 | F26: =if(E26=C9,"stemmir","stemmir ekki") -> stemmir
A27: mmlu_is_random_sample.csv | B27: =countif(mmlu_is_random_sample!H2:H29,"IC") -> 17 | C27: =countif(mmlu_is_random_sample!H2:H29,"F") -> 9 | D27: =countif(mmlu_is_random_sample!H2:H29,"OK") -> 2 | E27: =SUM(B27:D27) -> 28 | F27: =if(E27=C10,"stemmir","stemmir ekki") -> stemmir
A28: winogrande_is_random_sample.csv | B28: =countif(winogrande_is_random_sample!F2:F110,"IC") -> 0 | C28: =countif(winogrande_is_random_sample!F2:F110,"F") -> 12 | D28: =countif(winogrande_is_random_sample!F2:F110,"OK") -> 97 | E28: =SUM(B28:D28) -> 109 | F28: =if(E28=C11,"stemmir","stemmir ekki") -> stemmir
A29: hellaswag_is_random_sample.csv | B29: =countif(hellaswag_is_random_sample!L2:L252,"IC") -> 247 | C29: =countif(hellaswag_is_random_sample!L2:L252,"F") -> 3 | D29: =countif(hellaswag_is_random_sample!L2:L252,"OK") -> 0 | E29: =SUM(B29:D29) -> 250 | F29: =if(E29=C12,"stemmir","stemmir ekki") -> stemmir
A30: ged_is_random_sample.csv | B30: =countif(ged_is_random_sample!C2:C21,"IC") -> 0 | C30: =countif(ged_is_random_sample!C2:C21,"F") -> 1 | D30: =countif(ged_is_random_sample!C2:C21,"OK") -> 19 | E30: =SUM(B30:D30) -> 20 | F30: =if(E30=C13,"stemmir","stemmir ekki") -> stemmir
A31: inflection_is_random_sample.csv
A32: iceling_random_sample.csv
A35: rater_2
A36: Dataset | B36: IC | C36: F | D36: OK | E36: Samanlagt
A37: arc_is_random_sample.csv | B37: =countif(arc_is_random_sample!L2:L131,"IC") -> 35 | C37: =countif(arc_is_random_sample!L2:L131,"F") -> 59 | D37: =countif(arc_is_random_sample!L2:L131,"OK") -> 18 | E37: =SUM(B37:D37) -> 112 | F37: =if(E37=C2,"stemmir","stemmir ekki") -> stemmir
A38: scala_is_random_sample.csv | B38: =countif(scala_is_random_sample!E2:E132,"IC") -> 0 | C38: =countif(scala_is_random_sample!E2:E132,"F") -> 12 | D38: =countif(scala_is_random_sample!E2:E132,"OK") -> 90 | E38: =SUM(B38:D38) -> 102 | F38: =if(E38=C3,"stemmir","stemmir ekki") -> stemmir
A39: iceEC_random_sample.csv | B39: =countif(iceEC_random_sample!H2:H269,"IC") -> 23 | C39: =countif(iceEC_random_sample!H2:H269,"F") -> 50 | D39: =countif(iceEC_random_sample!H2:H269,"OK") -> 177 | E39: =SUM(B39:D39) -> 250 | F39: =if(E39=C4,"stemmir","stemmir ekki") -> stemmir
A40: nqii_random_sample.csv | B40: =countif(nqii_random_sample!G2:G269,"IC") -> 37 | C40: =countif(nqii_random_sample!G2:G269,"F") -> 41 | D40: =countif(nqii_random_sample!G2:G269,"OK") -> 135 | E40: =SUM(B40:D40) -> 213 | F40: =if(E40=C5,"stemmir","stemmir ekki") -> stemmir
A41: icelandic_qa_random_sample.csv | B41: =countif(icelandic_qa_random_sample!G2:G269,"IC") -> 3 | C41: =countif(icelandic_qa_random_sample!G2:G269,"F") -> 26 | D41: =countif(icelandic_qa_random_sample!G2:G269,"OK") -> 171 | E41: =SUM(B41:D41) -> 200 | F41: =if(E41=C6,"stemmir","stemmir ekki") -> stemmir
A42: belebele_is_random_sample.csv | B42: =countif(belebele_is_random_sample!M2:M109,"IC") -> 8 | C42: =countif(belebele_is_random_sample!M2:M109,"F") -> 38 | D42: =countif(belebele_is_random_sample!M2:M109,"OK") -> 44 | E42: =SUM(B42:D42) -> 90 | F42: =if(E42=C7,"stemmir","stemmir ekki") -> stemmir
A43: multiwikiqa_is_random_sample.csv | B43: =countif(multiwikiqa_is_random_sample!G2:G269,"IC") -> 47 | C43: =countif(multiwikiqa_is_random_sample!G2:G269,"F") -> 86 | D43: =countif(multiwikiqa_is_random_sample!G2:G269,"OK") -> 117 | E43: =SUM(B43:D43) -> 250 | F43: =if(E43=C8,"stemmir","stemmir ekki") -> stemmir
A44: arc_challenge_is_random_sample.csv | B44: =countif(arc_challenge_is_random_sample!F2:F269,"IC") -> 7 | C44: =countif(arc_challenge_is_random_sample!F2:F269,"F") -> 51 | D44: =countif(arc_challenge_is_random_sample!F2:F269,"OK") -> 54 | E44: =SUM(B44:D44) -> 112 | F44: =if(E44=C9,"stemmir","stemmir ekki") -> stemmir
A45: mmlu_is_random_sample.csv | B45: =countif(mmlu_is_random_sample!I2:I47,"IC") -> 5 | C45: =countif(mmlu_is_random_sample!I2:I47,"F") -> 20 | D45: =countif(mmlu_is_random_sample!I2:I47,"OK") -> 3 | E45: =SUM(B45:D45) -> 28 | F45: =if(E45=C10,"stemmir","stemmir ekki") -> stemmir
A46: winogrande_is_random_sample.csv | B46: =countif(winogrande_is_random_sample!G2:G128,"IC") -> 0 | C46: =countif(winogrande_is_random_sample!G2:G128,"F") -> 17 | D46: =countif(winogrande_is_random_sample!G2:G128,"OK") -> 92 | E46: =SUM(B46:D46) -> 109 | F46: =if(E46=C11,"stemmir","stemmir ekki") -> stemmir
A47: hellaswag_is_random_sample.csv | B47: =countif(hellaswag_is_random_sample!M2:M270,"IC") -> 194 | C47: =countif(hellaswag_is_random_sample!M2:M270,"F") -> 56 | D47: =countif(hellaswag_is_random_sample!M2:M270,"OK") -> 0 | E47: =SUM(B47:D47) -> 250 | F47: =if(E47=C12,"stemmir","stemmir ekki") -> stemmir
A48: ged_is_random_sample.csv | B48: =countif(ged_is_random_sample!D2:D270,"IC") -> 0 | C48: =countif(ged_is_random_sample!D2:D270,"F") -> 2 | D48: =countif(ged_is_random_sample!D2:D270,"OK") -> 18 | E48: =SUM(B48:D48) -> 20 | F48: =if(E48=C13,"stemmir","stemmir ekki") -> stemmir
A50: rater_3
A51: Dataset | B51: IC | C51: F | D51: OK | E51: Samanlagt
A52: arc_is_random_sample.csv | B52: =countif(arc_is_random_sample!I2:I146,"IC") -> 46 | C52: =countif(arc_is_random_sample!I2:I146,"F") -> 36 | D52: =countif(arc_is_random_sample!I2:I146,"OK") -> 30 | E52: =SUM(B52:D52) -> 112 | F52: =if(E52=C2,"stemmir","stemmir ekki") -> stemmir
A53: scala_is_random_sample.csv | B53: =countif(scala_is_random_sample!F2:F132,"IC") -> 0 | C53: =countif(scala_is_random_sample!F2:F132,"F") -> 14 | D53: =countif(scala_is_random_sample!F2:F132,"OK") -> 88 | E53: =SUM(B53:D53) -> 102 | F53: =if(E53=C3,"stemmir","stemmir ekki") -> stemmir
A54: iceEC_random_sample.csv | B54: =countif(iceEC_random_sample!I2:I269,"IC") -> 38 | C54: =countif(iceEC_random_sample!I2:I269,"F") -> 44 | D54: =countif(iceEC_random_sample!I2:I269,"OK") -> 168 | E54: =SUM(B54:D54) -> 250 | F54: =if(E54=C4,"stemmir","stemmir ekki") -> stemmir
A55: nqii_random_sample.csv | B55: =countif(nqii_random_sample!H2:H214,"IC") -> 43 | C55: =countif(nqii_random_sample!H2:H214,"F") -> 49 | D55: =countif(nqii_random_sample!H2:H214,"OK") -> 121 | E55: =SUM(B55:D55) -> 213 | F55: =if(E55=C5,"stemmir","stemmir ekki") -> stemmir
A56: icelandic_qa_random_sample.csv | B56: =countif(icelandic_qa_random_sample!H2:H201,"IC") -> 8 | C56: =countif(icelandic_qa_random_sample!H2:H201,"F") -> 18 | D56: =countif(icelandic_qa_random_sample!H2:H201,"OK") -> 174 | E56: =SUM(B56:D56) -> 200 | F56: =if(E56=C6,"stemmir","stemmir ekki") -> stemmir
A57: belebele_is_random_sample.csv | B57: =countif(belebele_is_random_sample!N2:N91,"IC") -> 12 | C57: =countif(belebele_is_random_sample!N2:N91,"F") -> 42 | D57: =countif(belebele_is_random_sample!N2:N91,"OK") -> 36 | E57: =SUM(B57:D57) -> 90 | F57: =if(E57=C7,"stemmir","stemmir ekki") -> stemmir
A58: multiwikiqa_is_random_sample.csv | B58: =countif(multiwikiqa_is_random_sample!H2:H251,"IC") -> 38 | C58: =countif(multiwikiqa_is_random_sample!H2:H251,"F") -> 88 | D58: =countif(multiwikiqa_is_random_sample!H2:H251,"OK") -> 124 | E58: =SUM(B58:D58) -> 250 | F58: =if(E58=C8,"stemmir","stemmir ekki") -> stemmir
A59: arc_challenge_is_random_sample.csv | B59: =countif(arc_challenge_is_random_sample!G2:G113,"IC") -> 9 | C59: =countif(arc_challenge_is_random_sample!G2:G113,"F") -> 27 | D59: =countif(arc_challenge_is_random_sample!G2:G113,"OK") -> 76 | E59: =SUM(B59:D59) -> 112 | F59: =if(E59=C9,"stemmir","stemmir ekki") -> stemmir
A60: mmlu_is_random_sample.csv | B60: =countif(mmlu_is_random_sample!J2:J29,"IC") -> 12 | C60: =countif(mmlu_is_random_sample!J2:J29,"F") -> 11 | D60: =countif(mmlu_is_random_sample!J2:J29,"OK") -> 5 | E60: =SUM(B60:D60) -> 28 | F60: =if(E60=C10,"stemmir","stemmir ekki") -> stemmir
A61: winogrande_is_random_sample.csv | B61: =countif(winogrande_is_random_sample!H2:H128,"IC") -> 1 | C61: =countif(winogrande_is_random_sample!H2:H128,"F") -> 11 | D61: =countif(winogrande_is_random_sample!H2:H128,"OK") -> 97 | E61: =SUM(B61:D61) -> 109 | F61: =if(E61=C11,"stemmir","stemmir ekki") -> stemmir
A62: hellaswag_is_random_sample.csv | B62: =countif(hellaswag_is_random_sample!N2:N270,"IC") -> 214 | C62: =countif(hellaswag_is_random_sample!N2:N270,"F") -> 36 | D62: =countif(hellaswag_is_random_sample!N2:N270,"OK") -> 0 | E62: =SUM(B62:D62) -> 250 | F62: =if(E62=C12,"stemmir","stemmir ekki") -> stemmir
A63: ged_is_random_sample.csv | B63: =countif(ged_is_random_sample!E2:E270,"IC") -> 0 | C63: =countif(ged_is_random_sample!E2:E270,"F") -> 1 | D63: =countif(ged_is_random_sample!E2:E270,"OK") -> 19 | E63: =SUM(B63:D63) -> 20 | F63: =if(E63=C13,"stemmir","stemmir ekki") -> stemmir

Sheet arc_is_random_sample
A1: id | B1: answer | C1: instruction | D1: option_a | E1: option_b | F1: option_c | G1: option_d | H1: option_e | I1: rater_3 | J1: rater_3 athugasemd | K1: rater_3_not_pedantic | L1: rater_2 | M1: rater_1
A2: ARC-Challenge/train/Mercury_7016625 | B2: A | C2: Í berghringrásinni hefst veðrun og rof sem leiðir til myndunar | D2: setlögum. | E2: magma. | F2: jarðefni. | G2: kristalla. | I2: F | J2: vitlaus beyging, annars OK | K2: OK | L2: F | M2: F
A3: ARC-Challenge/train/Mercury_7041248 | B3: D | C3: Tveimur efnum er blandað saman í bikarglasi sem er í ísvatnsbaði. Ísinn í vatninu bráðnar þegar íðefnin hvarfast í eina mínútu. Hvers konar hvarf á sér stað? | D3: innvarma, þar sem orka er tekin upp | E3: innvarma, þar sem orka er losuð | F3: útvarma, þar sem orka er tekin upp | G3: útvarma, þar sem orka er leyst út | I3: F | J3: það heitir útvermið | K3: OK | L3: F | M3: OK
A4: ARC-Challenge/train/Mercury_SC_416456 | B4: A | C4: Einfruma lífvera getur gert allt sem fruma úr fjölfrumu lífveru getur gert nema | D4: sérhæfa sig. | E4: fjölga sér. | F4: nota orku. | G4: búa til prótein. | I4: F | J4: sérhæft sig | K4: OK | L4: F | M4: F
A5: ARC-Challenge/train/ACTAAP_2008_5_7 | B5: A | C5: Hvað brjóta frumur niður til að framleiða orku? | D5: matvæli | E5: vatn | F5: chlorophyll | G5: koltvísýringur | I5: F | J5: samt skrítið að tala um "matvæli" - eru ekki ensími sem brjóta þau niður og svo nýta frumur kolvetni, fitu eða prótín? | K5: OK | L5: F | M5: F
A6: ARC-Challenge/train/MCAS_2008_5_5633 | B6: B | C6: Nemendur vilja planta sítrónutré í skólann sinn en kuldatíð í Massachusetts myndi drepa tréð. Hver af eftirfarandi er besta lausnin á þessu vandamáli? | D6: að planta nokkrum sítrónutrjám saman í röð | E6: bygging gróðurhúss til að hýsa sítrónutréð | F6: að gefa sítrónutrénu auka áburð á veturna | G6: að binda staur við sítrónutréð til stuðnings yfir veturinn | I6: F | J6: "í skólann sinn"!! | K6: OK | L6: F | M6: F
A7: ARC-Challenge/train/MCAS_2005_8_4 | B7: B | C7: Hvert af eftirfarandi er dæmi um líkamlega breytingu? | D7: kveikja eldspýtu | E7: brjóta glas | F7: brennsla bensíns | G7: ryðfylling járns | I7: F | J7: "líkamlega" á ekki við hér | L7: IC | M7: F
A8: ARC-Challenge/train/ACTAAP_2008_7_3 | B8: C | C8: Hvaða spurningu er líklegast að hægt sé að svara með vísindalegri rannsókn? | D8: Hver verður sigurvegari næsta happdrættis? | E8: Hvaða knattspyrnulið vinnur næsta leik? | F8: Hvert er ljósmagnið sem þarf til að rækta tómata? | G8: Hvaða fjórar fuglafjaðrir eru fallegastar á litinn? | I8: OK | L8: OK | M8: OK
A9: ARC-Challenge/train/MEA_2011_8_3 | B9: D | C9: Á hvaða stað á jörðinni er sólbirtan minnst þann 22. desember? | D9: Miðja | E9: Flórída | F9: Maine | G9: Norðurpóllinn | I9: F | J9: við notum "sólarljós" en ekki "sólbirta" | K9: OK | L9: F | M9: F
A10: ARC-Challenge/train/MEA_2016_8_1 | B10: C | C10: Refur fæddi afkvæmi sem höfðu betri heyrn en flestir refir. Hvernig gæti þessi litla breyting líklegast leitt til afkomenda sem eru frábrugðnir upprunalega refnum? | D10: Ræsir sem hafa betra heyrnarskyn geta stökkbreyst oftar en aðrir refir. | E10: Það má veiða oftar refi sem hafa betra heyrnarskyn. | F10: Með tímanum gætu afkomendur þessa refs heyrt betur og veitt bráð en aðrir refir. | G10: Með tímanum geta afkomendur þessa refs orðið útdauðir. | I10: OK | J10: A-svarið er gallað og upphafið á C: "Með tímanum" er óþarfur og mögulega truflandi | L10: F | M10: IC
A11: ARC-Challenge/train/NYSEDREGENTS_2006_8_26 | B11: C | C11: Þó að breytingar á fjölfrumutegundum taki yfirleitt mörg þúsund ár, þá taka sumar bakteríutegundir miklum breytingum á örfáum árum. Ein ástæðan fyrir þessum mun er sú að þessar bakteríur | D11: eru smásæjar | E11: innihalda ekki DNA | F11: fjölga sér mjög fljótt | G11: valda smitsjúkdómum | I11: OK | J11: "fljótt" ætti að vera "ört" | L11: OK | M11: OK
A12: ARC-Challenge/train/Mercury_7206535 | B12: C | C12: Í fjölfrumulífverum gegna mismunandi byggingar mismunandi hlutverki. Hvaða hlutverki gegnir laufplanta? | D12: að taka til sín mat | E12: að framleiða blóm | F12: gleypir ljós | G12: fræsuðugerð | I12: IC | J12: Laufblöð vinna orku úr sólarljósi, koltvísýringi og vatni. Ég hef aldrei heyrt að hlutverk laufplantna sé að "gleypa ljós" | K12: F | L12: F | M12: IC
A13: ARC-Challenge/train/Mercury_SC_401591 | B13: D | C13: Sólarsellur taka til sín orku frá sólinni. Til þess að nýta þessa orku til að knýja heimilistæki þurfa sólarsellur að umbreyta upptekinni orku í | D13: hiti. | E13: ljós. | F13: geislun. | G13: rafmagn. | I13: OK | J13: beyging samt röng á valmöguleika A | L13: F | M13: F
A14: ARC-Challenge/train/Mercury_183750 | B14: A | C14: Í hvaða sviðsmynd hér á eftir er líklegast að náttúruval eigi sér stað? | D14: Loftslagsbreytingar hafa smám saman aukist í aldaraðir | E14: stórfelld eyðilegging búsvæða | F14: hröð og mikil loftslagsbreytingar | G14: tafarlaust tap á frumfæðugjöfum | I14: OK | J14: Svar C er gallað | L14: F | M14: F
A15: ARC-Challenge/train/Mercury_SC_400300 | B15: B | C15: Hvort þessara tækja væri best að nota þegar skordýr eru skoðuð á vettvangi? | D15: áttaviti | E15: handlinsa | F15: smásjá | G15: hitamælir | I15: F | J15: Er "handlinsa" það sama og stækkunargler? | K15: OK | L15: F | M15: F
A16: ARC-Challenge/train/Mercury_SC_LBS10271 | B16: B | C16: Hvað er það sem einkennir plöntur og dýr? | D16: Plöntur þurfa ekki á steinefnum að halda og dýrin líka. | E16: Plöntur framleiða sína eigin fæðu og dýr ekki. | F16: Plöntur framleiða ekki súrefni og það gera dýrin líka. | G16: Plöntur þurfa sólarljós og dýr ekki. | I16: F | J16: Öll svör eru einkennilega orðuð | K16: OK | L16: IC | M16: F
A17: ARC-Challenge/train/Mercury_SC_400119 | B17: A | C17: Hvaða breyting verður á vírum rafrásar sem virkar eðlilega? | D17: Vírinn hlýnar | E17: Vírinn mun missa hluta af massa sínum. | F17: Vírinn myndar rafsvið. | G17: Vírinn myndar nýja kristalbyggingu. | I17: F | J17: Vírinn "hlýnar" ekki. Hann hitnar. | K17: OK | L17: F | M17: OK
A18: ARC-Challenge/train/Mercury_7056613 | B18: D | C18: Þegar bílvél er gangsett er bensíni blandað saman við loft og brennt. Varmi, hljóð og efnaafurðir losna. Hvort þessara þátta helst stöðugt í gangi vélarinnar? | D18: massa efnasambanda sem finnast í vélinni | E18: hversu mikill hiti er í vélinni | F18: heildarmassi bensíns | G18: heildarorkumagnið | I18: F | J18: Klúðurslega orðað, en mögulega hægt að ramba á rétt svar. | K18: OK | L18: F | M18: F
A19: ARC-Challenge/train/Mercury_7181668 | B19: C | C19: Daffodils eru plöntur sem geta bæði framkvæmt kynlausa og kynlausa æxlun. Hvernig nýtist daffodil stofninn betur við að æxlast kynlaust en kynlaus? | D19: Hún getur fjölgað sér hraðar. | E19: Það getur aðlagast umhverfi sínu hraðar. | F19: Það getur aukið fjölbreytni arfgengra eiginleika. | G19: Það getur eytt óheppilegum eiginleikum úr genamengi. | I19: IC | J19: Daffodils er ekki íslenska | K19: F | L19: IC | M19: IC
A20: ARC-Challenge/train/AKDE&ED_2012_8_14 | B20: A | C20: Einstaklingur fellir lifandi eikartré. Einstaklingurinn brennir viðinn úr eikartrénu til að sjóða vatn. Hvaða röð raðar rétt þeim orkuumbreytingum sem áttu sér stað frá lifandi trénu til sjóðunar vatns? | D20: ljósorka - efnaorka - varmaorka | E20: varmaorka - efnaorka - ljósorka | F20: efnaorka - vélræn orka - rafmagnsorka | G20: rafmagns-vélræn-efnaorka | I20: F | J20: Skringilega orðað, en hægt að skilja | K20: OK | L20: IC | M20: F
A21: ARC-Challenge/train/Mercury_SC_LBS10907 | B21: B | C21: Á hvaða tímaskeiði tunglsins gæti sólmyrkvi átt sér stað? | D21: full | E21: ný | F21: ársfjórðung | G21: hálfmáni | I21: F | J21: Það er talað um kvartilaskipti á tunglinu. Ekkert af þeim heitir ársfjórðungur og raunar ekki hálfmáni heldur. Svarið er samt þannig að hægt er að ramba á það. En varla hægt að tala um fjóra valmöguleika, sem er gegnumgangandi galli í þessu prófi. | L21: F | M21: IC
A22: ARC-Challenge/train/MEA_2014_8_6 | B22: B | C22: Bolta er varpað úr mismunandi hæð. Þegar bolta er varpað úr hæstu hæð þá er mesti hávaðinn eða titringurinn þegar hann lendir á jörðinni. Hver er besta skýringin á því að boltinn er með mesta hávaðann? | D22: Loftið þrýstir meira niður og boltinn fer hraðar. | E22: Þyngdaraflið togar í lengri tíma og boltinn fer hraðar. | F22: Boltinn þyngist og fer hraðar. | G22: Boltinn er að hitna og fer hraðar. | I22: OK | J22: mætti samt orða betur | L22: F | M22: F
A23: ARC-Challenge/train/LEAP__5_10318 | B23: D | C23: Miguel var að gera tilraun. Hann skrifaði eftirfarandi setningar í stílabókina sína: Byrjunarhitastig vatnsins var 10 gráður á Celsíus. Hlutur sem var 5 grömm að þyngd var settur í vatnið. Hitastig vatnsins hækkaði í 15 gráður. Hluturinn þarf að hafa verið heitari en 10 gráður. Í hvaða setningu ályktaði Miguel? | D23: setning 1 | E23: 2. setning | F23: 3. setning | G23: setning 4 | I23: OK | J23: ósamræmi í orðalagi svara, en skiptir ekki máli hér | L23: F | M23: F
A24: ARC-Challenge/train/MCAS_2008_8_5608 | B24: C | C24: Ef ný lífvera fyndist, hvaða af eftirfarandi yrði þá líklegast notað til að flokka hana í viðeigandi ríki? | D24: litur lífverunnar | E24: náttúrulegt búsvæði lífverunnar | F24: uppbyggingu líffærakerfis lífverunnar | G24: staðsetningin þar sem lífveran fannst | I24: OK | J24: orðalag | L24: F | M24: F
A25: ARC-Challenge/train/CSZ20740 | B25: B | C25: Hversu langan tíma tekur reiðhjól að fara 100 m vegalengd á meðalhraðanum 2 m/s? | D25: 0.0 | E25: s B 50 s | F25: 100 sek | G25: 200 s | I25: F | J25: Svör ekki stöðluð og rétta svarið skrítið | K25: OK | L25: F | M25: F
A26: ARC-Challenge/train/Mercury_7185448 | B26: B | C26: Kveikja eldspýtu og baka köku eru tvær aðgerðir sem fela í sér efnabreytingar. Hvers vegna eru þessar aðgerðir taldar efnabreytingar? | D26: Þær breyta ástandi efnisins. | E26: Þau búa til ný efni. | F26: Þeir breyta um magn. | G26: Þau skapa orku. | I26: F | J26: Upphafið | L26: F | M26: IC
A27: ARC-Challenge/train/Mercury_7268293 | B27: D | C27: Hvernig rata fræsprotar sem grafnir eru í algjöru myrkri í jarðveginum upp á yfirborð jarðvegsins? | D27: Þeir vaxa í átt að ljósi. | E27: Þau vaxa í átt að yfirborðshita. | F27: Þau vaxa á móti berggrunninum. | G27: Þau vaxa í andstöðu við stefnu þyngdaraflsins. | I27: OK | J27: "Þeir" en ekki "Þau" í svarinu | L27: OK | M27: IC
A28: ARC-Challenge/train/Mercury_7166093 | B28: B | C28: Plöntur geta komið í veg fyrir rof eða stuðlað að rofi. Hvert er dæmið um hvernig plöntur gætu stuðlað að rofi? | D28: Plöntur hægja á afrennsli vatns og jarðvegs. | E28: Rótar plöntunnar vaxa í bergi og brjóta það. | F28: Rætur plantna halda jarðveginum á sínum stað gegn vindi. | G28: Plöntur brjóta niður áhrif regndropa áður en þeir lenda í jarðveginum. | I28: F | J28: Í rétta svarinu stendur "Rótar" en ekki "Rætur" | L28: F | M28: F
A29: ARC-Challenge/train/Mercury_SC_LBS10674 | B29: D | C29: Hvert af eftirfarandi er dæmi um efnabreytingu? | D29: ský myndast | E29: sykur sem leysist upp | F29: vatnsfrysting | G29: kerti brennur | I29: OK | J29: Fáir myndu samt tala um "vatnsfrystingu" | L29: OK | M29: F
A30: ARC-Challenge/train/NYSEDREGENTS_2009_8_20 | B30: D | C30: Einn mikilvægur munur á lifandi og ólifandi er sá að aðeins lifandi hlutir hafa | D30: Efnasambönd | E30: þættir | F30: sameindir | G30: frumur | I30: F | J30: "ólifandi"? | L30: IC | M30: F
A31: ARC-Challenge/train/Mercury_SC_405303 | B31: C | C31: Hvaða vatnsform er líklegast að komi fram þegar hitastig er undir frostmarki? | D31: þoka | E31: rigning | F31: snjór | G31: skýjað | I31: OK | J31: "vatnsform" er samt bara bull | L31: OK | M31: F
A32: ARC-Challenge/train/Mercury_7245070 | B32: B | C32: Hvaða matvörur er hægt að brjóta niður að mestu í amínósýrur? | D32: Spagettí-núðlur | E32: Hamborgarabrauð | F32: eplahneppi | G32: gúrkusneiðar | I32: IC | J32: Hvað er "eplahneppi"? Inniheldur brauð meira af amínósýrum en spagettí? Getur verið að hér eigi bara að vera hamborgari, en ekki hamborgarabrauð? | L32: F | M32: F
A33: ARC-Challenge/train/Mercury_7284060 | B33: B | C33: Vampírufinkur á Galapagos eyjum kroppa aðra fuglategund, bláfættan bauga, þar til finkurnar sárbæna. Síðan drekka finkurnar blóð bauga. Vísindamenn halda að fyrir mörgum kynslóðum hafi finkurnar kroppað pöddur af bauga og hegðunin þróast í það sem hún er í dag. Hvor staðhæfingin lýsir best sambandi fugla fyrir mörgum kynslóðum og sambandinu í dag? | D33: Gamla sambandið var sníkjudýralegt. Nýja sambandið er gagnkvæmt. | E33: Gamla sambandið var gagnkvæmt en nýja sambandið er sníkjudýr. | F33: Bæði samböndin eru sníkjudýr. | G33: Bæði samböndin eru gagnkvæm. | I33: IC | J33: illskiljanleg spurning | K33: F | L33: IC | M33: IC
A34: ARC-Challenge/train/Mercury_416673 | B34: A | C34: Margir þættir hafa áhrif á heilsu fólks. Hvaða hugtak lýsir best mataræði og hreyfingu hjá flestum fullorðnum? | D34: lífsstílsval | E34: umhverfisþáttur | F34: erfðafræðileg tilhneiging | G34: hegðun sem er ávísuð af lækni | I34: IC | J34: Bein þýðing úr ensku sem verður frekar torskilin á íslensku | L34: OK | M34: F
A35: ARC-Challenge/train/NYSEDREGENTS_2011_4_13 | B35: C | C35: Nemandi sem hjólar sér að hann fer hraðar yfir sléttan veg en torfæran. Það gerist vegna þess að slétti vegurinn hefur | D35: minni þyngdarafl | E35: meiri þyngdarafl | F35: minni núningur | G35: meiri núningur | I35: OK | J35: Slétti vegurinn "hefur" ekki minni núning. En það er kannski minni núningur á milli hjólsins og vegarins á slétta veginum. | K35: F | L35: F | M35: IC
A36: ARC-Challenge/train/MCAS_1998_8_5 | B36: A | C36: Hvor staðhæfingin um ljóstillífun og öndun er sönn? | D36: Ljóstillífun geymir orku og öndun losar orku. | E36: Öndunin geymir orku og ljóstillífun losar orku. | F36: Ljóstillífun og öndun eru sama ferlið. | G36: Ljóstillífun og öndun hafa ekkert með orku að gera. | I36: OK | L36: F | M36: OK
A37: ARC-Challenge/train/Mercury_7030083 | B37: B | C37: Daginn áður en bekkurinn fer í tilraunastofu minnir kennari þeirra á að fara ekki í opna skó í skólann daginn eftir. Hvaða rök útskýra beiðni kennarans best? | D37: til að koma í veg fyrir að spilliefni leki | E37: til að koma í veg fyrir áverka á tám eða fótum | F37: til að koma í veg fyrir að þeir verði þreyttir á fótum | G37: að halda þeim kyrrum ef áföll dynja yfir | I37: F | J37: orðalag skrítið | L37: F | M37: F
A38: ARC-Challenge/train/MEA_2010_8_7 | B38: B | C38: Hvert af eftirfarandi er lengst frá jörðinni? | D38: Halastjarna Halleys | E38: Andromeda vetrarbrautin | F38: Neptúnus | G38: Sólin | I38: OK | L38: OK | M38: F
A39: ARC-Challenge/train/Mercury_184345 | B39: C | C39: Hvert af eftirfarandi er besta sönnun þess að landsvæði hafi eitt sinn verið hulið jökli? | D39: kalksteinsskálar | E39: sjávarjarðefni | F39: slit á yfirborðsgrjóti | G39: flagnandi bergflekar | I39: OK | L39: OK | M39: F
A40: ARC-Challenge/train/Mercury_7071943 | B40: C | C40: Hvaða jarðvegsþáttur hefur minnsta getu til að halda vatni? | D40: silt | E40: leir | F40: sandi | G40: humus | I40: F | J40: jarðvegsgerð. Rétta svarið er vitlaust beygt. Valmöguleikar 1 og 4 eru óþýddir. | L40: F | M40: F
A41: ARC-Challenge/train/MCAS_1998_8_4 | B41: B | C41: Hvaða staðhæfing lýsir best sambandinu á milli heildarmagns vatnsgufu sem andrúmsloftið getur geymt og hitastigs andrúmsloftsins? | D41: Magn vatnsgufu er ekki í tengslum við hitastig andrúmsloftsins. | E41: Magn vatnsgufu eykst eftir því sem hitastig andrúmsloftsins hækkar. | F41: Magn vatnsgufu eykst eftir því sem hitastig andrúmsloftsins lækkar. | G41: Magn vatnsgufu minnkar eftir því sem hitastig lofthjúpsins hækkar. | I41: OK | L41: OK | M41: OK
A42: ARC-Challenge/train/Mercury_SC_401284 | B42: C | C42: Ákveðið dýr hefur sérhæfðar frumur sem geta valdið því að það breytir lit hratt. Þessi litabreyting hjálpar dýrinu líklegast | D42: hlaupið hratt. | E42: melta mat hratt. | F42: fela sig fyrir rándýrum. | G42: halda líkamshita. | I42: F | J42: Beyging skrítin í svörum. Vantar 'að' framan við svörin. | L42: F | M42: IC
A43: ARC-Challenge/train/Mercury_411450 | B43: D | C43: Stjörnufræðilegar einingar eru notaðar til að mæla fjarlægðir milli fyrirbæra í geimnum. Ein stjarnfræðileg eining (AU) er fjarlægðin milli jarðar og sólar. Miðað við þessar upplýsingar, hversu margar stjarnfræðilegar einingar er Mars frá sólinni? | D43: 0.4 | E43: 0.7 | F43: 1.0 | G43: 1.5 | I43: F | J43: Það er talað um "stjarnfræðieiningar" í íslensku. En ekki stjörnufræðilegar einingar eða stjarnfræðilegar einingar, eins og þarna er notað á víxl. Eins á að vera komma en ekki punktur í tölunum á íslensku. | L43: OK | M43: OK
A44: ARC-Challenge/train/MCAS_1999_4_2 | B44: D | C44: Af hverju er betra að vera í hvítum bol en dökkbláum bol á sumrin? | D44: Ljós á fötum hleypir meira lofti inn. | E44: Ljós föt koma í veg fyrir svitamyndun. | F44: Ljós á fötum eru ekki eins þung og dökk á fötum. | G44: Ljós á fötum endurspegla meira sólarljós en dökk á fötum. | I44: OK | L44: IC | M44: IC
A45: ARC-Challenge/train/Mercury_SC_LBS10046 | B45: B | C45: Íkorni sem safnar hnetum hjálpar trjánum | D45: vaxa. | E45: fjölga sér. | F45: að standast sjúkdóminn. | G45: verða sterkari. | I45: F | J45: óþarfa greinir í "trjánum" og vantar 'að' framan við nokkur svör | L45: F | M45: IC
A46: ARC-Challenge/train/MDSA_2010_4_28 | B46: A | C46: Sum matvæli sem menn borða, eins og maís og ertur, eru í raun fræ plantna. Hvað lýsir best hlutverki mannsins í fæðuvef sem inniheldur þessar plöntur? | D46: neytandi | E46: a decomposer | F46: framleiðandi | G46: a skötusel | I46: F | J46: "ertur" eru almennt kallaðar "baunir" á íslensku. valmöguleiki B er óþýddur. | L46: IC | M46: IC
A47: ARC-Challenge/train/Mercury_401376 | B47: B | C47: Hvert þeirra er ekki dæmi um líkamlega breytingu á ástandi? | D47: suða | E47: hræra | F47: frysting | G47: gufa upp | I47: IC | L47: IC | M47: IC
A48: ARC-Challenge/train/Mercury_SC_401153 | B48: C | C48: Hvaða plöntuhluti er líkur fuglseggjum? | D48: laufblað | E48: rótin | F48: fræ | G48: stofn | I48: OK | L48: F | M48: OK
A49: ARC-Challenge/train/TIMSS_2003_4_pg5 | B49: C | C49: Sterkur segulmagnari skilur að blöndu af | D49: glært gler og grænt gler. | E49: pappírsbollur og plastbollur. | F49: járnnaglar og álnaglar. | G49: sand og salt. | I49: IC | J49: beygingar í svörum skrítnar | L49: F | M49: IC
A50: ARC-Challenge/train/Mercury_7219083 | B50: D | C50: Geislavirkni ísótópa í berginu er hægt að nota til að greina hvaða eiginleika bergið hefur? | D50: heildarmassi bergsins | E50: hversu hratt bergið myndaðist | F50: þær tegundir steingervinga sem bergið inniheldur | G50: hversu langur tími hefur liðið frá því að bergið myndaðist | I50: F | J50: Ekki orðað eins og spurning | L50: IC | M50: IC
A51: ARC-Challenge/train/Mercury_SC_414081 | B51: D | C51: Nemandi blés lofti í fjörukúlu og lokaði hana inni. Hún ýtti svo á miðja fjörukúluna. Hvað varð um loftið inni í fjörukúlunni? | D51: Loftið í strandboltanum slapp. | E51: Loftið í strandboltanum varð að vökva. | F51: Lofttegund í strandbolta breyttist. | G51: Lögun loftsins í strandboltanum breyttist. | I51: F | J51: Hvað er fjörukúla? | L51: IC | M51: IC
A52: ARC-Challenge/train/Mercury_7116130 | B52: B | C52: Vaxtarhraði grastegundar var mældur í trjálausum garði og trjáskyggðum garði. Grasið óx tvöfalt hraðar í trjálausa garðinum. Hvaða þáttur er líklegastur til að hafa áhrif á vaxtarhraðamuninn? | D52: magn dýra | E52: ljósmagn | F52: magn jarðvegs | G52: magn regns | I52: IC | J52: svör skrítin | L52: F | M52: OK
A53: ARC-Challenge/train/AKDE&ED_2008_4_36 | B53: B | C53: Einstaklingur veiðir og mælir stóran fisk sem kallast lúða. Hún heldur að lúðan sé yfir meðallagi að stærð. Til að styðja við þessa hugsun hennar væri gagnlegast að mæla | D53: margar tegundir fiska. | E53: marga fiska af sömu tegund. | F53: fiskur frá sama stað. | G53: fiska á öðru árstímabili. | I53: IC | J53: einstaklingur - hún | L53: F | M53: F
A54: ARC-Challenge/train/Mercury_7029645 | B54: A | C54: Málmfrumeindir munu að öllum líkindum mynda jónir með | D54: rafeindatap. | E54: prótónutap. | F54: mögnun á rafeindum. | G54: gróða á prótónum. | I54: IC | J54: svörin tengjast skringilega | L54: F | M54: IC
A55: ARC-Challenge/train/NYSEDREGENTS_2006_4_19 | B55: D | C55: Skjaldbakur sem étur orma er dæmi um | D55: öndun | E55: fjölgun | F55: að útrýma úrgangi | G55: að taka inn næringarefni | I55: IC | J55: Hvað er skjaldbakur? | L55: IC | M55: IC
A56: ARC-Challenge/train/Mercury_SC_409238 | B56: A | C56: Ugla veiðir mýs sem lifa á túni bónda. Eftir að bóndinn safnar uppskerunni hafa mýsnar færri staði til að fela sig á. Hvað er líklegast að gerist eftir að uppskerunni er safnað? | D56: Uglan mun veiða fleiri mýs. | E56: Uglan veiðir á öðrum vettvangi. | F56: Uglan fær nýtt efni til að byggja hreiður sitt. | G56: Uglan á erfitt með að fóðra ungviðið. | I56: OK | L56: OK | M56: OK
A57: ARC-Challenge/train/MCAS_2013_5_29397 | B57: D | C57: Hvert af eftirfarandi er dæmi um orkuform? | D57: loftið í innsiglaðri krukku | E57: vírinn í málmhengi | F57: vatnið í litlum polla | G57: hljóðið í háværri kennslustofu | I57: IC | J57: svör skrítin | L57: F | M57: F
A58: ARC-Challenge/train/Mercury_7038203 | B58: B | C58: Þegar fingur er skorinn og blæðir, flytjast blóðflögur og plasmaprótein til skurðarins til að stöðva blæðinguna. Þegar þessir þættir flytjast til skurðarins, örvar það fleiri blóðflögur og prótein til að flytjast til skurðarins til að stöðva blæðinguna. Hvers konar ferli er verið að sýna fram á? | D58: neikvæð svörun | E58: jákvæð endurgjöf | F58: endurgjöf frá eftirlitsaðilum | G58: endurgjöf á örvun | I58: IC | J58: orðalag í svörum skrítið | L58: F | M58: F
A59: ARC-Challenge/train/Mercury_414091 | B59: B | C59: Hvert er algengasta frumefnið í efnasamböndum sem mynda hafsjó? | D59: köfnunarefni | E59: súrefni | F59: kolefni | G59: kísil | I59: F | J59: skil ekki spurninguna | L59: F | M59: IC
A60: ARC-Challenge/train/Mercury_7086118 | B60: C | C60: Nemandi leggur vatn og þvottaefni í bolla af mold. Blandan er hrist og látin setjast. Nemandi sér að sítrónuagnir haldast í sviflausn löngu eftir að hinar agnirnar mynda lög neðst í krukkunni. Líklegasta skýringin er að sítrónuagnirnar séu | D60: lífrænt. | E60: að leysast upp. | F60: ekki jafn þétt. | G60: hreyft hraðar. | I60: IC | J60: tvö svörin passa ekki málfræðilega við spurninguna. Gæti ruglað val á svari. | L60: IC | M60: IC
A61: ARC-Challenge/train/Mercury_SC_405455 | B61: D | C61: Ný vélatækni hefur hjálpað bílum að ná meiri kílómetrafjölda á bensínlítra. Þar sem bensín er framleitt úr olíu mun þessi tækni hafa áhrif á olíubirgðir í heiminum um | D61: að þörfin fyrir að leita að meiri olíu aukist. | E61: að stytta þann tíma sem það tekur olíu að endurnýja sig. | F61: minnka magn olíu sem er til neðanjarðar. | G61: lengri tíma sem olía verður tilbúin til notkunar. | I61: F | J61: Svörin mjög léleg og erfitt að láta passa við spurninguna | L61: F | M61: F
A62: ARC-Challenge/train/Mercury_7213115 | B62: C | C62: Hvaða vatnsgeymir inniheldur mest magn af ferskvatni? | D62: vötn | E62: ár | F62: ísblöð | G62: Veitendur | I62: F | J62: það er ekki talað um vatnsgeymi í þessu sambandi á íslensku | L62: IC | M62: IC
A63: ARC-Challenge/train/MCAS_2006_9_5-v1 | B63: C | C63: Í koparvír er hitaaukning afleiðing af hvoru af eftirfarandi? | D63: aukning á stærð koparsögnanna | E63: minnkun á massa koparsögnanna | F63: aukin hreyfing á koparögnunum | G63: minnkun á fjarlægð milli koparsögnanna | I63: IC | L63: F | M63: IC
A64: ARC-Challenge/train/NYSEDREGENTS_2004_4_12 | B64: D | C64: Hvaða matur er ávöxtur? | D64: kartöflu | E64: lauk | F64: gulrót | G64: grasker | I64: IC | L64: F | M64: F
A65: ARC-Challenge/train/Mercury_SC_401197 | B65: C | C65: Öruggar starfsaðferðir á rannsóknarstofu fela í sér allt þetta nema | D65: binda aftur sítt hár. | E65: í öryggisgleraugum. | F65: að framkvæma hvert skref hratt. | G65: þurrka strax upp leka. | I65: IC | L65: F | M65: F
A66: ARC-Challenge/train/Mercury_7211663 | B66: D | C66: Nú eru lífverur flokkaðar eftir DNA sönnunargögnum. Hvað af eftirfarandi er gagnlegast fyrir rannsakanda að flokka lífveru sem er nýlega uppgötvuð? | D66: jarðefnamet | E66: Genaspólun | F66: sérvalin kynbótastarfsemi | G66: rafdráttur á geli | I66: IC | L66: F | M66: IC
A67: ARC-Challenge/train/Mercury_7214463 | B67: A | C67: Rauð stjarna er líklegast með meiri stjörnuþyngd en sólin í samanburði við sólina | D67: magn. | E67: snúningshraða. | F67: yfirborðshita. | G67: fjölda reikistjarna á braut um jörðina. | I67: F | L67: IC | M67: IC
A68: ARC-Challenge/train/Mercury_SC_401364 | B68: C | C68: Dropa af rauðum matarlit er bætt út í skál af vatni. Nokkrum mínútum síðar er allt vatnið orðið rautt. Hver þessara aðferða lýsir breytingunni sem átti sér stað? | D68: rof | E68: osmósuþörf | F68: flæði | G68: blóðgjöf | I68: OK | L68: OK | M68: OK
A69: ARC-Challenge/train/MCAS_2005_9_20 | B69: A | C69: Hvert af eftirfarandi er líkt 20 milli röntgenbylgna og hljóðbylgna? | D69: Báðir flytja orku. | E69: Hvort tveggja krefst tómarúms. | F69: Báðir hafa sama hraða. | G69: Báðar hafa þær sömu tíðni. | I69: F | L69: IC | M69: IC
A70: ARC-Challenge/train/Mercury_7140035 | B70: C | C70: Ánamaðkar ferðast af handahófi um jarðvegsbotn. Hvaða áhrif hafa ánamaðkar líklegast á jarðvegsbotninn? | D70: með því að þjappa jarðveginum saman | E70: með því að draga úr frjósemi jarðvegs í efstu gróðurlendum | F70: með því að bæta næringarefnum í jarðvegsbotninn | G70: með því að fjarlægja steinefnin úr jarðveginum | I70: IC | L70: F | M70: F
A71: ARC-Challenge/train/NCEOGA_2013_5_10 | B71: A | C71: Hver er besta skýringin á því hvernig loftmassar flytjast yfir Bandaríkin? | D71: Hinir ríkjandi vesturveldar flytja loftmassa frá vestri til austurs um Bandaríkin en geta sveigt með straumi þotustreymis. | E71: Viðskiptavindar flytja loftmassa frá vestri til austurs um Bandaríkin. | F71: Þotustraumurinn flytur loftmassa frá Kyrrahafi yfir Bandaríkin. | G71: Hlýtt loft í Golfstraumnum veldur því að loftmassar flytjast frá Atlantshafi til Kyrrahafs. | I71: IC | L71: IC | M71: IC
A72: ARC-Challenge/train/Mercury_SC_LBS10343 | B72: B | C72: Þungi þungra vinnuvéla þjappar jarðvegi saman, sérstaklega þegar hann er blautur. Af hverju forðast bændur að keyra vinnuvélar sínar yfir blautan jarðveg? | D72: Þjappaður jarðvegur mun gleypa of mikið vatn. | E72: Plöntur geta ekki vaxið þegar jarðvegur er þjappaður. | F72: Jarðefni eyðast við þjöppun jarðvegs. | G72: Þjappaður jarðvegur eykur sýrustig jarðvegs. | I72: OK | L72: OK | M72: OK
A73: ARC-Challenge/train/Mercury_7212030 | B73: D | C73: Í samanburði við bíla sem knúnir eru bensíni og eru af svipaðri stærðargráðu eru rafmagns- og bensínblöndubílar aðallega hannaðir til að | D73: framleiða meira hestafl. | E73: útblástur gróðurhúsalofttegunda. | F73: starfa óháð jarðefnaeldsneyti. | G73: veita betri gaskílómetra. | I73: IC | L73: IC | M73: IC
A74: ARC-Challenge/train/Mercury_7017168 | B74: D | C74: Hvert er besta dæmið um að efnabreyting hafi átt sér stað? | D74: breyting á ríki | E74: losun orku | F74: hitastigsbreytingar | G74: myndun nýs efnis | I74: IC | L74: OK | M74: OK
... A113: ARC-Challenge/train/Mercury_7170433 | B113: D | C113: Emily er að hjóla. Hvort skýrir best hvers vegna aðeins hluti af orkunni sem fer í að pedala hjólið hennar fer í að hreyfa hjólið áfram? | D113: Orka hjóladekksins er sett á í hringhreyfingu. | E113: Orka hjólsins flyst aðeins á annað hjólið. | F113: Gír og keðja hjólsins eru þakin olíu. | G113: Gír og keðja hjólsins mynda núning. | I113: IC | L113: F | M113: IC

Sheet scala_is_random_sample
A1: text | B1: corruption_type | C1: label | D1: rater_1 | E1: rater_2 | F1: rater_3
A2: Núna þurfum við að fá meira að láni í nafni sanngirni. | C2: correct | D2: OK | E2: OK | F2: OK
A3: Hvers vegna erum við ekki með lögin þannig að hver sem opinberlega hæðist að, rógber, smánar og ógnar manni og svo framvegis án tillits Forseti hringir. til nokkurs skapaðar hlutar sæti refsingu? | C3: correct | D3: OK | E3: OK | F3: OK
A4: Alþingi gert getur hitt og þetta. | B4: flip_neighbours | C4: incorrect | D4: OK | E4: OK | F4: OK
A5: Hitt er miklu stærra mál sem við erum ekki búin að afgreiða og við eigum ekki að afgreiða með þessu, það er hvar línurnar eiga að liggja, af því að við setjum ekki bara venjulegan verðmiða á það. | C5: correct | D5: OK | E5: OK | F5: OK
A6: Að öðru leyti við ég þakka svör utanríkisráðherra í dag og hrósa honum aftur og hvetja hann áfram til að standa vörð um NATO. | C6: correct | D6: IC | E6: F | F6: F
A7: Niðurstaðan varð sú að hvetja ráðherra til að halda áfram og hefur hún móttekið þau skilaboð. | C7: correct | D7: OK | E7: OK | F7: OK
A8: Hann er látinn fylgja landslaginu eins mikið og mögulegt er til þess að sé hann sem minnst áberandi. | B8: flip_neighbours | C8: incorrect | D8: OK | E8: OK | F8: OK
A9: Virðulegi forseti. Hvað það varðar að markmiðið sé ljóst og tvíþætt ég hélt nú að ég væri að gera stuðningsmönnum frumvarpsins greiða með því að kalla það óljóst. | C9: correct | D9: F | E9: F | F9: OK
A10: Maður býr við verðbólgu, maður einhvern veginn venst því. | C10: correct | D10: OK | E10: OK | F10: OK
A11: og samgöngu nefnd lagði gríðarlega vinnu í málið. | B11: delete | C11: incorrect | D11: F | E11: F | F11: F
A12: Guðni Valur Guðnason kringlukastari úr ÍR náði sínum besta árangri á árinu þegar hann kastaði 60,72 m Vormóti á UFA á Þórsvelli á Akureyri í dag. | B12: flip_neighbours | C12: incorrect | D12: OK | E12: OK | F12: OK
A13: Virðulegi forseti. Það er svo sem ekki mikið eftir að ræða í sjálfu hvað viðkemur þessu tiltekna máli. | B13: delete | C13: incorrect | D13: OK | E13: OK | F13: F
A14: Varðandi það sem hv. þingmaður spurði um og ég nefndi sem dæmi um nokkra hluti sem eru mikið á skjön við annað og andann í þessu frumvarpi sem er ekki upplífgandi að stærstum hluta til nema í einstökum tilvikum. | C14: correct | D14: OK | E14: OK | F14: OK
A15: Það var að sjálfsögðu erfitt fyrir margra hluta sakir og auðvitað greindi menn á um það hvernig ætti að skipta takmarkaðri auðlind. | C15: correct | D15: OK | E15: OK | F15: OK
A16: Leikur Íslands og Danmerkur hefst klukkan 19:15 og verður sýndur á RÚV 2. | C16: correct | D16: OK | E16: OK | F16: OK
A17: Það þarf ekki alltaf greiningartæki til þess að sjá hvað er helsta vinnuafl ríkisins, til að mynda á landsbyggðinni eða innan eða menntakerfisins. | B17: delete | C17: incorrect | D17: OK | E17: OK | F17: OK
A18: Bryndísi Rún Hansen tókst ekki að sér tryggja sæti í undanúrslitum 100 m skriðsunds kvenna. | B18: flip_neighbours | C18: incorrect | D18: OK | E18: OK | F18: OK
A19: Svo er hitt, að það er kannski ekki þingmannsstarf að meta hversu mikið mál það væri. | C19: correct | D19: OK | E19: OK | F19: OK
A20: Hefði áætlunin, ef hún hefði verið samþykkt, komið í veg fyrir þær tillögur sem voru í fjárlagafrumvarpinu og ákveðin voru atlaga að konum? | B20: flip_neighbours | C20: incorrect | D20: OK | E20: OK | F20: OK
A21: Það er mun ódýrara að borga þá bara fyrir viðtalið á greiningunni. | C21: correct | D21: OK | E21: OK | F21: F
A22: Störfunum fjölgar jú og fleiri hendur vinna þau en arðbærnin og hagkvæmnin er ekki sama sú. | B22: flip_neighbours | C22: incorrect | D22: OK | E22: OK | F22: OK
A23: Lengra svarið er að þegar kemur að fjarskiptasjóði og nettengingu úti á landi þá finnst mér það óhjákvæmilega svolítið eins og að skilja fólk eftir símalaust eða ég ætla ekki að segja vatnslaust kannski en símalaust og jafnvel rafmagnslaust þegar það er netlaust eða með það lélega tengingu að geti ekki gert það sem það þarf að gera. | B23: delete | C23: incorrect | D23: OK | E23: OK | F23: F
A24: Mig langar til þess að minna hv. þm. Pál Jóhann Pálsson á þegar hann segir að hér sé aðeins deilt um útfærslu og hversu mikið útgerðin þoli að það er í raun og veru enginn sérstakur ágreiningur um það í þjóðfélaginu. | C24: correct | D24: OK | E24: OK | F24: OK
A25: hún í undanúrslit keppir hún í þeim á fimmtudag klukkan 16: 50. | B25: delete | C25: incorrect | D25: OK | E25: OK | F25: OK
A26: Gripið fram í: Svo er praxísinn Já, svo er það alls konar praxísinn og jafnvægið þar á milli, það fer eftir því hvað verið er að tala um o. s. frv. En mér finnst þetta einhvern veginn vera það versta úr báðum hugmyndum. | B26: delete | C26: incorrect | D26: IC | E26: F | F26: OK
A27: Ef þessi lög eiga að standast lög um tjáningarfrelsi vil ég því upp, virðulegi forseti, að það sé eitthvað mikið að því hvernig við lítum á tjáningarfrelsið. | B27: delete | C27: incorrect | D27: OK | E27: OK | F27: OK
A28: Núna skilst mér að það séu fleiri en 300 nemendur í skólanum en menn töluðu ávallt um í kringum 250. | C28: correct | D28: OK | E28: OK | F28: OK
A29: Þetta er besti tími sem Bryndís hefur nokkurn tímann synt á í greininni. | C29: correct | D29: OK | E29: OK | F29: OK
A30: Norska kvennalandsliðið í handbolta vann tíu marka sigur á Hvít-Rússum í Minsk í gær 32 22 og tryggði sér þannig sæti á EM sem haldið verður í Svíþjóð í desember. | C30: correct | D30: OK | E30: OK | F30: OK
A31: Þess vegna spyr ég, eðlilega: Hvað hafa menn verið að gera þessi tvö ár ef ekki er meira kjöt á beinunum en raun ber vitni? | C31: correct | D31: OK | E31: OK | F31: OK
A32: Alþingi getur gert hitt og þetta. | C32: correct | D32: OK | E32: OK | F32: OK
A33: Héldu menn virkilega að það yrði með öðrum hætti? | C33: correct | D33: OK | E33: OK | F33: OK
A34: Það efast enginn um mikilvægi þess að leggja fram kerfisáætlun en það er ekki sama hvernig það er gert og við þurfum að vanda okkur betur. | C34: correct | D34: OK | E34: OK | F34: OK
A35: Ég tek hins vegar undir með hv. þingmanni, við megum ekki tala um að þetta verkefni fari illa. | C35: correct | D35: OK | E35: OK | F35: OK
A36: Það er bara hluti af hinum föstu tekjusamskiptum ríkis og sveitarfélaga og hefur verið svo mjög lengi. | C36: correct | D36: OK | E36: OK | F36: OK
A37: En hvað er hér á dagskrá? | C37: correct | D37: OK | E37: OK | F37: OK
A38: Það er skýr munur á umhverfi nútímans, árið 2013, frá því sem var 1990, munurinn er svo yfirþyrmandi og skýr að það blasir við að endurskoða þarf náttúruverndarlög með hliðsjón af því. | C38: correct | D38: OK | E38: OK | F38: OK
A39: Gleymum því ekki að við komum úr sárustu fátækt Evrópu fyrir rúmum 100 árum. | C39: correct | D39: OK | E39: OK | F39: OK
A40: Gylfi Þór Sigurðsson og Ögmundur Kristinsson séu líklega þeir bestu í hópnum. | C40: correct | D40: OK | E40: OK | F40: F
A41: Þetta frumvarp gerir það miður ekki. | B41: delete | C41: incorrect | D41: OK | E41: OK | F41: F
A42: Maður er stressaður að fara meiddur út af ef einhver hefur keypt mann í Fantasy innsk:, “ segir Ásgerður Stefanía Baldursdóttir, fyrirliði Stjörnunnar. | B42: delete | C42: incorrect | D42: F | E42: F | F42: OK
A43: Það fara líka peningar í hæstu arðgreiðslur, einhverjar hæstu arðgreiðslur sem við höfum séð ganga ár eftir ár út úr einni atvinnugrein til eigenda sinna. | C43: correct | D43: OK | E43: OK | F43: OK
A44: Ef ég skil hann rétt, eða samkvæmt tilfinningunni sem ég fæ, að hann mundi ekki atkvæði með því, þá velti ég fyrir mér nákvæmlega hvers vegna. | B44: delete | C44: incorrect | D44: F | E44: OK | F44: OK
A45: Geta ráðherrar pantað eigin að geðþótta hvaða svigrúm þeir hafa í yfirfærslu fjárheimilda milli ára eftir því hvort það er þóknanlegt eða ekki? | B45: flip_neighbours | C45: incorrect | D45: OK | E45: OK | F45: OK
A46: Við höfum rifjað upp og söguna það er hægt að benda á ýmislegt. | B46: flip_neighbours | C46: incorrect | D46: OK | E46: OK | F46: OK
A47: Nú er búið að krukka í það a. m. k. þrisvar sinnum. | C47: correct | D47: OK | E47: OK | F47: OK
A48: Virðulegi forseti. Mig langaði að spyrja hv. þm. Pétur H. Blöndal tveggja spurninga, aðra mér til fróðleiks. | C48: correct | D48: OK | E48: OK | F48: OK
A49: Nú vitum við öll að þetta er viðurkenning á því að þjóðin eigi auðlindina. | C49: correct | D49: OK | E49: OK | F49: OK
A50: Þar af er þetta annar sigur hans í mótaröðinni 2016. | C50: correct | D50: OK | E50: OK | F50: OK
A51: Svo kemur og maturinn veitingaþjónustan með 7 <percent/> og svo kannski eitthvað annað með 25,5 <percent/>. | B51: flip_neighbours | C51: incorrect | D51: OK | E51: OK | F51: OK
A52: Ég hef sagt að við sjálfstæðismenn séum tilbúin til að auðlindaákvæðið setja inn í stjórnarskrá. | B52: flip_neighbours | C52: incorrect | D52: OK | E52: OK | F52: OK
A53: Að finna þessa miklu umfjöllun sem er í gangi og þetta gefur manni byr báða vængi að halda áfram, “ segir Ásgerður. | B53: delete | C53: incorrect | D53: OK | E53: OK | F53: OK
A54: Nýr listi var gefinn út í morgun. | C54: correct | D54: OK | E54: OK | F54: OK
A55: það hefur veruleg verðlags- og félagsleg áhrif tengingar sem þarf að huga að. | B55: delete | C55: incorrect | D55: OK | E55: OK | F55: OK
A56: Þá getum við kosið um nýja stjórnarskrá og þá verðum við kannski komin með nýja stjórnarskrá innan árs. | C56: correct | D56: OK | E56: OK | F56: OK
A57: Stuðlar þetta miklu frekar að því að allt verði eins og landbúnaðarkerfið er, þunglamalegt og svifaseint, í stað þess að vera núna með ákveðna reglufestu og markaðsdrifið eins og sjávarútvegurinn er rekinn í dag. | B57: flip_neighbours | C57: incorrect | D57: IC | E57: F | F57: F
A58: Það ekki nógu góð ástæða til að ráðast inn á friðhelgi einkalífsins. | B58: delete | C58: incorrect | D58: OK | E58: OK | F58: OK
A59: Geir Þorsteinsson sem verið hefur formaður Knattspyrnusambands Íslands frá 2007 ætlar ekki að gefa kost á sér til endurkjörs formanns á ársþingi sambandsins í. | B59: delete | C59: incorrect | D59: OK | E59: OK | F59: OK
A60: Besti tími Collins var áður 9,96 sek. frá því í júlí 2014 en bætti nú sitt besta og um leið landsmetið í Saint Kitts og Nevis um þrjá hundraðshluta úr. | B60: delete | C60: incorrect | D60: OK | E60: OK | F60: OK
A61: Ég tók eiginlega ekki eftir því hvort þingmaðurinn beindi einhverri sérstakri spurningu til mín. | C61: correct | D61: OK | E61: OK | F61: OK
A62: Ég veit ekki alveg hvernig ætti að vinna þetta tiltekna frumvarp frekar vegna þess að það er svo, nú vantar mig aftur íslenska orðið fyrir „ brutal “ frumvarpið tekur einfaldlega út gömlu lögin. | C62: correct | D62: F | E62: OK | F62: OK
A63: Virðulegi forseti. Ég þakka þm. hv. Brynjari Níelssyni fyrir fína ræðu. | B63: flip_neighbours | C63: incorrect | D63: F | E63: F | F63: F
A64: Samt er þetta einfaldasta nú greinin, hlaupa bara hratt. | B64: flip_neighbours | C64: incorrect | D64: OK | E64: OK | F64: OK
A65: Þau koma inn í málið þegar við förum að tala um skuldavanda og heimilanna þá neyð sem krefst þess að við söfnum umræddum upplýsingum. | B65: flip_neighbours | C65: incorrect | D65: OK | E65: OK | F65: OK
A66: Mig langar að biðja hana að útskýra aftur í stuttu máli hvað það er í tillögum minni hlutans, þessum aukningum hér frá minni hlutanum, af hverju það skiptir svona miklu máli og ef ekkert verður að gert, ekkert bætt í, hvað við sjáum þá fram undan. | B66: delete | C66: incorrect | D66: IC | E66: F | F66: F
A67: Ísland endaði í þriðja sæti og leikur um fimmta sæti á mótinu við en hvern kemur í ljós síðar í dag. | B67: flip_neighbours | C67: incorrect | D67: OK | E67: OK | F67: OK
A68: Það skilar ekki hagnaði til ríkisins per se þó þeir aðilar yrðu til dæmis að færa niður eign sína í íslensku bönkunum og láta hana fyrir afslátt, þá það þeir sem tapa en ekki við sem græðum. | B68: delete | C68: incorrect | D68: OK | E68: OK | F68: OK
A69: Við erum að ræða um fleiri þætti og fleiri úrbætur á þeim vegi sem mér fannst sveitarstjórnarfólkið rökstyðja mjög vel að hægt væri að fara í. | C69: correct | D69: OK | E69: OK | F69: OK
A70: Hér stoppar allt of margt og við erum ekkert ofboðslega enn klár sem komið er að tala saman. | B70: flip_neighbours | C70: incorrect | D70: OK | E70: OK | F70: OK
A71: Ég hef lært að það er miklu betra að við förum í gegnum þetta og það tók ekkert langan tíma í sjálfu sér. | C71: correct | D71: OK | E71: OK | F71: OK
A72: Getur hv. þingmaður upplýst um þær umræður sem hafa átt sér stað innan samgöngunefndar? | C72: correct | D72: OK | E72: OK | F72: OK
A73: Í grunninn aftengir hún eitt element sem þarf að vera til staðar upp að vissu marki, er það það að á vissum tímum þarf að rýra verðgildi peninganna. | B73: flip_neighbours | C73: incorrect | D73: OK | E73: OK | F73: F
A74: Það sem gerðist í nefndinni þá vænti ég þess fastlega að hv. þingmaður meini nefndarfundinn sem haldinn var eftir þingfund á fimmtudag var að við í minni hlutanum stungum upp á því málið yrði tekið upp á haustþingi og við mundum frekar ræða aðrar útfærslur, svo sem þær sem hv. þingmaður spyr út í. | B74: delete | C74: incorrect | D74: F | E74: F | F74: F
A75: Það skilar ekki hagnaði til ríkisins per se þó þeir aðilar yrðu til dæmis að færa niður eign sína í íslensku bönkunum og láta hana fyrir afslátt, þá eru það þeir sem tapa en ekki við sem græðum. | C75: correct | D75: OK | E75: OK | F75: OK
A76: Það er ekki af neinni meinbægni út í forsetaembættið að ég geri það sérstaklega að umtalsefni hér en það vill bara svo að ég man að það fékk tvo myndarlega liði til hækkunar afgreidda við afgreiðslu fjárlaga í sama mánuði síðasta árs upp á 16 milljónir og annan rúmlega. | B76: delete | C76: incorrect | D76: OK | E76: OK | F76: OK
A77: Svo smám heillaðist saman ég af íþróttinni. | B77: flip_neighbours | C77: incorrect | D77: OK | E77: OK | F77: OK
A78: Nú er búið að krukka í a. það m. k. þrisvar sinnum. | B78: flip_neighbours | C78: incorrect | D78: OK | E78: OK | F78: OK
A79: Jason Day, Dustin Johnson, Shane Lowry, Rory McIlroy, Graeme McDowell, Adam Scott, Louis Oosthuizen, Vijay Singh og Jordan Spieth eru allir í hópi þeirra sem hafa afboðið á leikana. | B79: delete | C79: incorrect | D79: F | E79: OK | F79: OK
A80: Eins og ég fór yfir ræðu í minni hv. þingmaður hefur kannski brugðið sér aðeins frá þá var þetta misræmi einmitt ein meginstoð þess sem ég fjallaði um. | B80: flip_neighbours | C80: incorrect | D80: OK | E80: F | F80: F
A81: Það er umræða sem ég bíð með þar til í síðara andsvari mínu. | C81: correct | D81: OK | E81: OK | F81: OK
A82: Hv. þingmaður ræddi niðurskurðinn til Vinnumálastofnunar og mér finnst það líka athyglisvert að starfsendurhæfingarsjóður dettur alveg út úr tryggingagjaldinu. | C82: correct | D82: OK | E82: OK | F82: OK
A83: Íbúðalánasjóð varðandi er staða hans vissulega alvarleg og er meiri hlutinn gagnrýninn á það hve lítið hafi gerst í sambandi við málefni sjóðsins. | B83: flip_neighbours | C83: incorrect | D83: F | E83: OK | F83: OK
A84: Ég gerði það samt þess að ég trúi á bjartsýni, ég trúi á von. | B84: delete | C84: incorrect | D84: OK | E84: OK | F84: OK
A85: Er það bara þetta hrun? | C85: correct | D85: OK | E85: OK | F85: OK
A86: Það er ekki verið að reyna að gera hana betri, þannig að já, því miður held ég að það megi túlka það þannig. | C86: correct | D86: OK | E86: OK | F86: OK
A87: Verður lögsókn sú þá ekki bara að koma fram? | B87: flip_neighbours | C87: incorrect | D87: IC | E87: F | F87: F
A88: Það er einn lokapunktur um gegnsæi sem mig langar að benda á sem er sá að gegnsæi kemur ekki sjálfkrafa. | C88: correct | D88: OK | E88: OK | F88: OK
A89: Þetta er hvimleitt vandamál sem hefur komið með tækniþróuninni. | C89: correct | D89: OK | E89: OK | F89: OK
A90: Hitt er miklu stærra mál sem við erum ekki búin að afgreiða og við eigum ekki að afgreiða þessu, það er hvar línurnar eiga að liggja, af því að við setjum ekki bara venjulegan verðmiða á það. | B90: delete | C90: incorrect | D90: OK | E90: OK | F90: OK
A91: Peningarnir eru í settir annað. | B91: flip_neighbours | C91: incorrect | D91: OK | E91: OK | F91: OK
A92: Það er erfitt að taka afstöðu til einhvers í fjárlagafrumvarpi sem maður veit ekki hvað er og mér heyrist enginn vita hvernig þessi komugjöld eiga að vera. | C92: correct | D92: OK | E92: OK | F92: OK
A93: Það væru ekki 70 <percent/> aðspurðra á móti því. | C93: correct | D93: F | E93: OK | F93: OK
A94: Því auk Hrafnhildar munu Eygló Ósk Gústafsdóttir og Anton Sveinn McKee keppa í úrslitum í 200 m baksundi og 100 m bringusundi. | C94: correct | D94: OK | E94: OK | F94: OK
A95: Eldra fólk býr líka á heimilum. | C95: correct | D95: OK | E95: OK | F95: OK
A96: Geir Þorsteinsson sem verið hefur formaður Knattspyrnusambands Íslands frá 2007 ætlar ekki að gefa kost á sér til endurkjörs formanns á ársþingi sambandsins í febrúar. | C96: correct | D96: OK | E96: OK | F96: OK
A97: Árangurinn er sérlega merkilegur í þess að Kim Collins varð 40 ára í apríl en sýnir það að aldurinn er ekkert annað en tala, fyrst hann er enn í framför. | B97: delete | C97: incorrect | D97: OK | E97: OK | F97: OK
A98: Já, en mörg gerðu það ekki, það er mikill breytileiki innan Evrópusambandsins. | C98: correct | D98: OK | E98: OK | F98: OK
A99: Ég hef ekki meiri tíma en held kannski áfram í seinna andsvari. | C99: correct | D99: OK | E99: OK | F99: OK
A100: Varðandi smábátahlutfallið í þessu verð ég að segja ég hef ekki skoðað skiptinguna á því mjög „ grundigt “. | B100: delete | C100: incorrect | D100: IC | E100: F | F100: OK
...

Sheet iceEC_random_sample
A1: idx | B1: sentence | C1: errors | D1: has_error | E1: corrected_sentence | F1: rater_1 | G1: leiðrétting | H1: rater_2 | I1: rater_3
A2: 54106 | B2: ['Kannski' 'er' 'þessi' 'fullyrðing' 'þröngsýn' 'en' 'ef' 'prestur' 'er' 'spurður' 'afhverju' 'samkynhneigt' 'fólk' 'má' 'ekki' 'giftast' 'þá' 'svarar' 'hann' '„' 'vegna' 'þess' 'að' 'hjónband' 'getur' 'ekki' 'átt' 'sér' 'stað' 'nema' 'á' 'milli' 'karls' 'og' 'konu' '“' '.'] | C2: [array([], dtype=object) array([], dtype=object) array([], dtype=object) array([], dtype=object) array([], dtype=object) array([], dtype=object) array([], dtype=object) array([], dtype=object) array([], dtype=object) array([], dtype=object) array(['orthography', 'orthography'], dtype=object) array([], dtype=object) array([], dtype=object) array([], dtype=object) array([], dtype=object) array([], dtype=object) array([], dtype=object) array([], dtype=object) array([], dtype=object) array([], dtype=object) array([], dtype=object) array([], dtype=object) array([], dtype=object) array([], dtype=object) array([], dtype=object) array([], dtype=object) array([], dtype=object) array([], dtype=object) array([], dtype=object) array([], dtype=object) array([], dtype=object) array([], dtype=object) array([], dtype=object) array([], dtype=object) array([], dtype=object) array([], dtype=object) array([], dtype=object)] | D2: True | E2: ['Kannski' 'er' 'þessi' 'fullyrðing' 'þröngsýn' 'en' 'ef' 'prestur' 'er' 'spurður' 'af hverju' 'samkynhneigt' 'fólk' 'má' 'ekki' 'giftast' 'þá' 'svarar' 'hann' '„' 'vegna' 'þess' 'að' 'hjónband' 'getur' 'ekki' 'átt' 'sér' 'stað' 'nema' 'á' 'milli' 'karls' 'og' 'konu' '“' '.'] | F2: IC | G2: hjónband enn rangt | H2: F | I2: IC
A3: 12695 | B3: ['Átján' 'prósent' 'fyrirtækja' 'hyggjast' 'fjölga' 'starfsfólki' 'næstu' 'þrjá' 'til' 'fjóra' 'mánuðina' 'en' 'tíu' 'prósent' 'hyggjast' 'fækka' 'því' '.'] | C3: [array([], dtype=object) array([], dtype=object) array([], dtype=object) array([], dtype=object) array([], dtype=object) array([], dtype=object) array([], dtype=object) array([], dtype=object) array([], dtype=object) array([], dtype=object) array([], dtype=object) array([], dtype=object) array([], dtype=object) array([], dtype=object) array([], dtype=object) array([], dtype=object) array([], dtype=object) array([], dtype=object)] | D3: False | E3: ['Átján' 'prósent' 'fyrirtækja' 'hyggjast' 'fjölga' 'starfsfólki' 'næstu' 'þrjá' 'til' 'fjóra' 'mánuðina' 'en' 'tíu' 'prósent' 'hyggjast' 'fækka' 'því' '.'] | F3: OK | H3: OK | I3: OK
A4: 36240 | B4: ['Klerkaveldi' 'er' 'stjórnarform' 'þar' 'sem' 'æðsti' 'valdhafi' 'er' 'sagður' 'fara' 'með' 'vald' 'Guðs' ',' 'öll' 'löggjöf' 'byggir' 'á' 'trúarbrögðum' 'og' 'á' 'að' 'tjá' 'vilja' 'Guðs' '.'] | C4: [array([], dtype=object) array([], dtype=object) array([], dtype=object) array([], dtype=object) array([], dtype=object) array([], dtype=object) array([], dtype=object) array([], dtype=object) array([], dtype=object) array([], dtype=object) array([], dtype=object) array([], dtype=object) array(['orthography', 'orthography'], dtype=object) array(['orthography', 'orthography'], dtype=object) array([], dtype=object) array([], dtype=object) array([], dtype=object) array([], dtype=object) array([], dtype=object) array([], dtype=object) array([], dtype=object) array([], dtype=object) array([], dtype=object) array([], dtype=object) array([], dtype=object) array([], dtype=object)] | D4: True | E4: ['Klerkaveldi' 'er' 'stjórnarform' 'þar' 'sem' 'æðsti' 'valdhafi' 'er' 'sagður' 'fara' 'með' 'vald' 'guðs og' 'öll' 'löggjöf' 'byggir' 'á' 'trúarbrögðum' 'og' 'á' 'að' 'tjá' 'vilja' 'Guðs' '.'] | F4: OK | G4: og bætt við | H4: OK | I4: F
A5: 36648 | B5: ['Það' 'á' 'upptök' 'sín' 'í' 'Sambíu' 'en' 'rennur' 'fyrst' 'í' 'vestur' 'til' 'Angóla' 'og' 'svo' 'aftur' 'til' 'Sambíu' 'áður' 'en' 'það' 'nær' 'Mósambík' 'þar' 'sem' 'það' 'fellur' 'í' 'Indlandshaf' '.'] | C5: [array([], dtype=object) array([], dtype=object) array([], dtype=object) array([], dtype=object) array([], dtype=object) array([], dtype=object) array([], dtype=object) array([], dtype=object) array([], dtype=object) array([], dtype=object) array([], dtype=object) array([], dtype=object) array([], dtype=object) array([], dtype=object) array([], dtype=object) array([], dtype=object) array([], dtype=object) array([], dtype=object) array([], dtype=object) array([], dtype=object) array([], dtype=object) array(['grammar'], dtype=object) array([], dtype=object) array([], dtype=object) array([], dtype=object) array([], dtype=object) array([], dtype=object) array([], dtype=object) array([], dtype=object) array([], dtype=object)] | D5: True | E5: ['Það' 'á' 'upptök' 'sín' 'í' 'Sambíu' 'en' 'rennur' 'fyrst' 'í' 'vestur' 'til' 'Angóla' 'og' 'svo' 'aftur' 'til' 'Sambíu' 'áður' 'en' 'það' 'nær' 'til' 'Mósambík' 'þar' 'sem' 'það' 'fellur' 'í' 'Indlandshaf' '.'] | F5: OK | G5: nær + til | H5: OK | I5: OK
A6: 53263 | B6: ['Sumir' 'geta' 'bara' 'alls' 'ekki' 'átt' 'peninga' 'heldur' 'verða' 'bara' 'að' 'eyða' 'þeim' '.'] | C6: [array([], dtype=object) array([], dtype=object) array([], dtype=object) array([], dtype=object) array([], dtype=object) array([], dtype=object) array([], dtype=object) array([], dtype=object) array([], dtype=object) array([], dtype=object) array([], dtype=object) array([], dtype=object) array([], dtype=object) array([], dtype=object)] | D6: False | E6: ['Sumir' 'geta' 'bara' 'alls' 'ekki' 'átt' 'peninga' 'heldur' 'verða' 'bara' 'að' 'eyða' 'þeim' '.'] | F6: OK | H6: OK | I6: OK
A7: 55379 | B7: ['Þau' 'þurftu' 'bæði' 'að' 'hafa' 'mikið' 'fyrir' 'því' 'að' 'geta' 'haldið' 'uppi' 'svo' 'stóru' 'heimili' '.'] | C7: [array([], dtype=object) array([], dtype=object) array([], dtype=object) array([], dtype=object) array([], dtype=object) array([], dtype=object) array([], dtype=object) array([], dtype=object) array([], dtype=object) array([], dtype=object) array([], dtype=object) array([], dtype=object) array([], dtype=object) array([], dtype=object) array([], dtype=object) array([], dtype=object)] | D7: False | E7: ['Þau' 'þurftu' 'bæði' 'að' 'hafa' 'mikið' 'fyrir' 'því' 'að' 'geta' 'haldið' 'uppi' 'svo' 'stóru' 'heimili' '.'] | F7: OK | H7: OK | I7: OK
A8: 30017 | B8: ['Tölvuleikjatónlist' 'er' 'yfirleitt' 'notað' 'sem' 'hugtak' 'yfir' 'bakgrunnstónlistina' 'sem' 'heyrist' 'í' 'tölvuleikjum' '.'] | C8: [array([], dtype=object) array([], dtype=object) array([], dtype=object) array([], dtype=object) array([], dtype=object) array([], dtype=object) array([], dtype=object) array(['grammar'], dtype=object) array([], dtype=object) array([], dtype=object) array([], dtype=object) array([], dtype=object) array([], dtype=object)] | D8: True | E8: ['Tölvuleikjatónlist' 'er' 'yfirleitt' 'notað' 'sem' 'hugtak' 'yfir' 'bakgrunnstónlist' 'sem' 'heyrist' 'í' 'tölvuleikjum' '.'] | F8: IC | G8: bakgrunnstónlistina -> bakgrunnstónlist | H8: F | I8: IC
A9: 2302 | B9: ['Hann' 'telur' 'að' 'um' 'fimmtán' 'manns' 'hafi' 'látið' 'af' 'störfum' 'hér' 'á' 'Íslandi' '.'] | C9: [array([], dtype=object) array([], dtype=object) array([], dtype=object) array([], dtype=object) array([], dtype=object) array([], dtype=object) array([], dtype=object) array([], dtype=object) array([], dtype=object) array([], dtype=object) array([], dtype=object) array([], dtype=object) array([], dtype=object) array([], dtype=object)] | D9: False | E9: ['Hann' 'telur' 'að' 'um' 'fimmtán' 'manns' 'hafi' 'látið' 'af' 'störfum' 'hér' 'á' 'Íslandi' '.'] | F9: OK | H9: OK | I9: OK
A10: 40825 | B10: ['Hljómsveitir' 'hafa' 'oft' 'plötusnúða' 'innan' 'raða' 'sinna' 'til' 'að' 'undirstrika' 'þessi' 'áhrif' '.'] | C10: [array([], dtype=object) array([], dtype=object) array([], dtype=object) array([], dtype=object) array([], dtype=object) array([], dtype=object) array([], dtype=object) array([], dtype=object) array([], dtype=object) array([], dtype=object) array([], dtype=object) array([], dtype=object) array([], dtype=object)] | D10: False | E10: ['Hljómsveitir' 'hafa' 'oft' 'plötusnúða' 'innan' 'raða' 'sinna' 'til' 'að' 'undirstrika' 'þessi' 'áhrif' '.'] | F10: OK | H10: OK | I10: OK
A11: 13899 | B11: ['Af' 'þessu' 'hlaust' 'talsvert' 'uppnám' 'í' 'þingsal' '.'] | C11: [array([], dtype=object) array([], dtype=object) array([], dtype=object) array([], dtype=object) array([], dtype=object) array([], dtype=object) array([], dtype=object) array([], dtype=object)] | D11: False | E11: ['Af' 'þessu' 'hlaust' 'talsvert' 'uppnám' 'í' 'þingsal' '.'] | F11: OK | H11: OK | I11: OK
A12: 34444 | B12: ['Útskýrt' 'var' 'að' 'engar' 'frekari' 'ákvarðanir' 'yrðu' 'teknar' 'um' 'viðræðurnar' 'án' 'frumkvæðis' 'þjóðarinnar' 'í' 'þjóðaratkvæðagreiðslu' '.'] | C12: [array([], dtype=object) array([], dtype=object) array([], dtype=object) array([], dtype=object) array([], dtype=object) array([], dtype=object) array([], dtype=object) array([], dtype=object) array([], dtype=object) array([], dtype=object) array([], dtype=object) array([], dtype=object) array([], dtype=object) array([], dtype=object) array([], dtype=object) array([], dtype=object)] | D12: False | E12: ['Útskýrt' 'var' 'að' 'engar' 'frekari' 'ákvarðanir' 'yrðu' 'teknar' 'um' 'viðræðurnar' 'án' 'frumkvæðis' 'þjóðarinnar' 'í' 'þjóðaratkvæðagreiðslu' '.'] | F12: OK | H12: OK | I12: OK
A13: 52229 | B13: ['Möguleikarnir' 'eru' 'endalaust' 'margir' 'sem' 'gerir' 'valið' 'enn' 'erfiðara' '.'] | C13: [array([], dtype=object) array([], dtype=object) array([], dtype=object) array([], dtype=object) array([], dtype=object) array([], dtype=object) array([], dtype=object) array([], dtype=object) array([], dtype=object) array([], dtype=object)] | D13: False | E13: ['Möguleikarnir' 'eru' 'endalaust' 'margir' 'sem' 'gerir' 'valið' 'enn' 'erfiðara' '.'] | F13: OK | H13: OK | I13: OK
A14: 35585 | B14: ['Það' 'er' 'talið' 'að' 'garðabrúða' 'sé' 'nokkuð' 'örugg' 'sé' 'hún' 'tekin' 'inn' 'í' 'litlum' 'skömmtum' 'í' 'stuttan' 'tíma' '.'] | C14: [array([], dtype=object) array([], dtype=object) array([], dtype=object) array([], dtype=object) array([], dtype=object) array([], dtype=object) array([], dtype=object) array([], dtype=object) array([], dtype=object) array([], dtype=object) array([], dtype=object) array([], dtype=object) array([], dtype=object) array([], dtype=object) array([], dtype=object) array([], dtype=object) array([], dtype=object) array([], dtype=object) array([], dtype=object)] | D14: False | E14: ['Það' 'er' 'talið' 'að' 'garðabrúða' 'sé' 'nokkuð' 'örugg' 'sé' 'hún' 'tekin' 'inn' 'í' 'litlum' 'skömmtum' 'í' 'stuttan' 'tíma' '.'] | F14: OK | H14: OK | I14: OK
A15: 32729 | B15: ['Fyrir' 'opnunarsenuna' 'á' 'hótelinu' 'þurfti' 'Sheen' 'ekkert' 'að' 'leika' 'mikið' 'þar' 'sem' 'hann' 'átti' 'afmæli' 'og' 'var' 'mjög' 'drukkinn' '.'] | C15: [array([], dtype=object) array([], dtype=object) array([], dtype=object) array([], dtype=object) array([], dtype=object) array([], dtype=object) array(['style'], dtype=object) array([], dtype=object) array([], dtype=object) array([], dtype=object) array([], dtype=object) array([], dtype=object) array([], dtype=object) array([], dtype=object) array([], dtype=object) array([], dtype=object) array([], dtype=object) array([], dtype=object) array([], dtype=object) array([], dtype=object)] | D15: True | E15: ['Fyrir' 'opnunarsenuna' 'á' 'hótelinu' 'þurfti' 'Sheen' 'ekki' 'að' 'leika' 'mikið' 'þar' 'sem' 'hann' 'átti' 'afmæli' 'og' 'var' 'mjög' 'drukkinn' '.'] | F15: OK | G15: ekkert -> ekki | H15: F | I15: F
A16: 20513 | B16: ['Kartöflur' 'á' 'norðurlandi' 'gætu' 'komið' 'eitthvað' 'síðar' 'vegna' 'veðurfars' 'þar' 'á' 'svæðinu' '.'] | C16: [array([], dtype=object) array(['style'], dtype=object) array(['style'], dtype=object) array([], dtype=object) array([], dtype=object) array([], dtype=object) array(['style'], dtype=object) array([], dtype=object) array([], dtype=object) array(['vocabulary'], dtype=object) array([], dtype=object) array(['style'], dtype=object) array([], dtype=object)] | D16: True | E16: ['Kartöflur' '' 'gætu' 'komið' 'eitthvað' 'síðar' 'á Norðurlandi' 'vegna' 'veðurfars' '' 'á' 'því svæði' '.'] | F16: IC | G16: norðurlandi er rangt í upphaflegu setningunni en annars er þetta skrýtin leiðrétting | H16: F | I16: OK
A17: 2614 | B17: ['Mats' 'Hummels' 'skoraði' 'eina' 'mark' 'leiksins' 'með' 'skalla' 'á' '13.' 'mínútu' 'en' 'hann' 'er' 'fyrsti' 'varnarmaður' 'keppninnar' 'sem' 'nær' 'að' 'skora' 'tvö' 'mörk' 'á' 'mótinu' '.'] | C17: [array([], dtype=object) array([], dtype=object) array([], dtype=object) array([], dtype=object) array([], dtype=object) array([], dtype=object) array([], dtype=object) array([], dtype=object) array([], dtype=object) array([], dtype=object) array([], dtype=object) array([], dtype=object) array([], dtype=object) array([], dtype=object) array([], dtype=object) array([], dtype=object) array([], dtype=object) array([], dtype=object) array([], dtype=object) array([], dtype=object) array([], dtype=object) array([], dtype=object) array([], dtype=object) array([], dtype=object) array([], dtype=object) array([], dtype=object)] | D17: False | E17: ['Mats' 'Hummels' 'skoraði' 'eina' 'mark' 'leiksins' 'með' 'skalla' 'á' '13.' 'mínútu' 'en' 'hann' 'er' 'fyrsti' 'varnarmaður' 'keppninnar' 'sem' 'nær' 'að' 'skora' 'tvö' 'mörk' 'á' 'mótinu' '.'] | F17: OK | H17: OK | I17: OK
A18: 36256 | B18: ['Þingið' 'getu' 'lýst' 'yfir' 'vantrausti' 'á' 'forsetan' 'og' 'leiðtoginn' 'síðan' 'svipt' 'hann' 'embætti' 'í' 'kjölfarið' '.'] | C18: [array([], dtype=object) array(['orthography'], dtype=object) array([], dtype=object) array([], dtype=object) array([], dtype=object) array([], dtype=object) array(['orthography', 'orthography'], dtype=object) array([], dtype=object) array([], dtype=object) array([], dtype=object) array([], dtype=object) array([], dtype=object) array([], dtype=object) array([], dtype=object) array([], dtype=object) array([], dtype=object)] | D18: True | E18: ['Þingið' 'getur' 'lýst' 'yfir' 'vantrausti' 'á' 'forsetann' 'og' 'leiðtoginn' 'síðan' 'svipt' 'hann' 'embætti' 'í' 'kjölfarið' '.'] | F18: OK | H18: OK | I18: OK
A19: 31454 | B19: ['Jórdanía' 'skiptist' 'í' 'tólf' 'héruð' '(' 'landstjóraumdæmi' ')' 'sem' 'aftur' 'skiptast' 'í' '54' 'umdæmi' '(' 'nawahi' ')' '.'] | C19: [array([], dtype=object) array([], dtype=object) array([], dtype=object) array([], dtype=object) array([], dtype=object) array([], dtype=object) array([], dtype=object) array([], dtype=object) array([], dtype=object) array([], dtype=object) array([], dtype=object) array([], dtype=object) array([], dtype=object) array([], dtype=object) array([], dtype=object) array([], dtype=object) array([], dtype=object) array([], dtype=object)] | D19: False | E19: ['Jórdanía' 'skiptist' 'í' 'tólf' 'héruð' '(' 'landstjóraumdæmi' ')' 'sem' 'aftur' 'skiptast' 'í' '54' 'umdæmi' '(' 'nawahi' ')' '.'] | F19: OK | H19: OK | I19: OK
A20: 685 | B20: ['Þannig' 'að' 'það' 'hefur' 'varla' 'verið' 'stórmál' '.'] | C20: [array([], dtype=object) array([], dtype=object) array([], dtype=object) array([], dtype=object) array([], dtype=object) array([], dtype=object) array([], dtype=object) array([], dtype=object)] | D20: False | E20: ['Þannig' 'að' 'það' 'hefur' 'varla' 'verið' 'stórmál' '.'] | F20: OK | H20: OK | I20: OK
A21: 3747 | B21: ['Hún' 'fékk' 'nafnið' 'Ingibjörg' 'Rósa' 'Haraldsdóttir' ',' '"' 'sagði' 'Eva' 'Laufey' 'í' 'samtali' 'við' 'Vísi' '.'] | C21: [array([], dtype=object) array([], dtype=object) array([], dtype=object) array([], dtype=object) array([], dtype=object) array([], dtype=object) array([], dtype=object) array(['orthography'], dtype=object) array([], dtype=object) array([], dtype=object) array([], dtype=object) array([], dtype=object) array([], dtype=object) array([], dtype=object) array([], dtype=object) array([], dtype=object)] | D21: True | E21: ['Hún' 'fékk' 'nafnið' 'Ingibjörg' 'Rósa' 'Haraldsdóttir' ',' '“' 'sagði' 'Eva' 'Laufey' 'í' 'samtali' 'við' 'Vísi' '.'] | F21: OK | G21: gæsalöppum breytt | H21: OK | I21: F
A22: 37045 | B22: ['Árið' '1701' '(' 'MDCCI' 'í' 'rómverskum' 'tölum' ')'] | C22: [array([], dtype=object) array([], dtype=object) array([], dtype=object) array([], dtype=object) array([], dtype=object) array([], dtype=object) array([], dtype=object) array([], dtype=object)] | D22: False | E22: ['Árið' '1701' '(' 'MDCCI' 'í' 'rómverskum' 'tölum' ')'] | F22: OK | H22: OK | I22: OK
A23: 20550 | B23: ['Hann' 'fór' 'úr' 'axlarlið' 'og' 'var' 'borinn' 'af' 'velli' '.'] | C23: [array([], dtype=object) array(['style'], dtype=object) array([], dtype=object) array([], dtype=object) array([], dtype=object) array([], dtype=object) array([], dtype=object) array([], dtype=object) array([], dtype=object) array([], dtype=object)] | D23: True | E23: ['Hann' 'hafði farið' 'úr' 'axlarlið' 'og' 'var' 'borinn' 'af' 'velli' '.'] | F23: IC | G23: fór -> hafði farið | H23: F | I23: IC
A24: 727 | B24: ['Hann' 'ætlar' 'að' 'opna' 'snemma' 'í' 'fyrramálið' 'og' 'hafa' 'opið' 'alla' 'helgina' '.'] | C24: [array([], dtype=object) array([], dtype=object) array([], dtype=object) array([], dtype=object) array([], dtype=object) array([], dtype=object) array([], dtype=object) array([], dtype=object) array([], dtype=object) array([], dtype=object) array([], dtype=object) array([], dtype=object) array([], dtype=object)] | D24: False | E24: ['Hann' 'ætlar' 'að' 'opna' 'snemma' 'í' 'fyrramálið' 'og' 'hafa' 'opið' 'alla' 'helgina' '.'] | F24: OK | H24: OK | I24: OK
A25: 42129 | B25: ['Einnig' 'tilnefndar' ':' 'Davíð' 'Logi' 'Sigurðsson' ',' 'Morgunblaðinu' ',' 'fyrir' 'skrif' 'um' 'alþjóðamál' ',' 'þar' 'á' 'meðal' 'skrif' 'um' 'Guantanamo-fangabúðirnar' 'á' 'Kúbu' 'og' 'Íslensku' 'friðargæsluna' '.'] | C25: [array([], dtype=object) array(['grammar'], dtype=object) array([], dtype=object) array([], dtype=object) array([], dtype=object) array([], dtype=object) array([], dtype=object) array([], dtype=object) array([], dtype=object) array([], dtype=object) array([], dtype=object) array([], dtype=object) array([], dtype=object) array([], dtype=object) array([], dtype=object) array([], dtype=object) array([], dtype=object) array([], dtype=object) array([], dtype=object) array([], dtype=object) array([], dtype=object) array([], dtype=object) array([], dtype=object) array([], dtype=object) array([], dtype=object) array([], dtype=object)] | D25: True | E25: ['Einnig' 'tilnefndur' ':' 'Davíð' 'Logi' 'Sigurðsson' ',' 'Morgunblaðinu' ',' 'fyrir' 'skrif' 'um' 'alþjóðamál' ',' 'þar' 'á' 'meðal' 'skrif' 'um' 'Guantanamo-fangabúðirnar' 'á' 'Kúbu' 'og' 'Íslensku' 'friðargæsluna' '.'] | F25: OK | H25: OK | I25: OK
A26: 35080 | B26: ['Var' 'mikill' 'fengur' 'að' 'því' 'að' 'fá' 'á' 'ný' 'notið' 'þessa' 'stórbrotna' 'verks' 'í' 'svo' 'vönduðum' 'flutningi' 'sem' 'hér' '.'] | C26: [array([], dtype=object) array([], dtype=object) array([], dtype=object) array([], dtype=object) array([], dtype=object) array([], dtype=object) array([], dtype=object) array([], dtype=object) array([], dtype=object) array([], dtype=object) array([], dtype=object) array([], dtype=object) array([], dtype=object) array([], dtype=object) array([], dtype=object) array([], dtype=object) array([], dtype=object) array([], dtype=object) array([], dtype=object) array([], dtype=object)] | D26: False | E26: ['Var' 'mikill' 'fengur' 'að' 'því' 'að' 'fá' 'á' 'ný' 'notið' 'þessa' 'stórbrotna' 'verks' 'í' 'svo' 'vönduðum' 'flutningi' 'sem' 'hér' '.'] | F26: OK | H26: OK | I26: OK
A27: 25848 | B27: ['Hlaupið' 'í' 'Múlakvísl' 'hófst' 'skömmu' 'fyrir' 'miðnætti' 'í' 'gærkvöldi' '.'] | C27: [array([], dtype=object) array([], dtype=object) array([], dtype=object) array([], dtype=object) array([], dtype=object) array([], dtype=object) array([], dtype=object) array([], dtype=object) array([], dtype=object) array([], dtype=object)] | D27: False | E27: ['Hlaupið' 'í' 'Múlakvísl' 'hófst' 'skömmu' 'fyrir' 'miðnætti' 'í' 'gærkvöldi' '.'] | F27: OK | H27: OK | I27: OK
A28: 3845 | B28: ['Á' 'vefsíðunni' 'fótbolti.net' 'kemur' 'fram' 'að' 'starfsmenn' 'KSÍ' 'hafði' 'þurft' 'að' 'hafa' 'hraðar' 'hendur' 'að' 'útvega' 'skó' 'í' 'gærkvöldi' '.'] | C28: [array([], dtype=object) array([], dtype=object) array([], dtype=object) array([], dtype=object) array([], dtype=object) array([], dtype=object) array([], dtype=object) array([], dtype=object) array(['grammar', 'grammar'], dtype=object) array([], dtype=object) array([], dtype=object) array([], dtype=object) array([], dtype=object) array(['grammar'], dtype=object) array([], dtype=object) array([], dtype=object) array([], dtype=object) array([], dtype=object) array([], dtype=object) array([], dtype=object)] | D28: True | E28: ['Á' 'vefsíðunni' 'fótbolti.net' 'kemur' 'fram' 'að' 'starfsmenn' 'KSÍ' 'hefðu' 'þurft' 'að' 'hafa' 'hraðar' 'hendur' 'við' 'að' 'útvega' 'skó' 'í' 'gærkvöldi' '.'] | F28: OK | H28: F | I28: OK
A29: 18378 | B29: ['Óskað' 'var' 'eftir' 'aðstoð' 'sjúkraflutningamanna' 'þegar' 'kona' 'féll' 'um' 'tvo' 'metra' 'í' 'Varmárdal' ',' 'fyrir' 'ofan' 'Reyki' ',' 'um' 'tíuleytið' 'í' 'morgun' '.'] | C29: [array([], dtype=object) array([], dtype=object) array([], dtype=object) array([], dtype=object) array([], dtype=object) array([], dtype=object) array([], dtype=object) array([], dtype=object) array([], dtype=object) array([], dtype=object) array([], dtype=object) array([], dtype=object) array([], dtype=object) array([], dtype=object) array([], dtype=object) array([], dtype=object) array([], dtype=object) array([], dtype=object) array([], dtype=object) array([], dtype=object) array([], dtype=object) array([], dtype=object) array([], dtype=object)] | D29: False | E29: ['Óskað' 'var' 'eftir' 'aðstoð' 'sjúkraflutningamanna' 'þegar' 'kona' 'féll' 'um' 'tvo' 'metra' 'í' 'Varmárdal' ',' 'fyrir' 'ofan' 'Reyki' ',' 'um' 'tíuleytið' 'í' 'morgun' '.'] | F29: OK | H29: OK | I29: OK
A30: 28198 | B30: ['Ekkert' 'bannar' 'þeim' 'þó' 'að' 'aka' 'í' 'ytri' 'hring' ',' 'en' 'í' 'mikilli' 'umferð' 'má' 'búast' 'við' 'að' 'þeir' 'valdi' 'truflun' 'og' 'óþægindum' 'fyrir' 'aðra' 'ökumenn' 'haldi' 'þeir' 'sig' 'í' 'ytri' 'akrein' 'fram' 'hjá' 'svo' 'mörgum' 'gatnamótum' '.'] | C30: [array([], dtype=object) array([], dtype=object) array([], dtype=object) array([], dtype=object) array([], dtype=object) array([], dtype=object) array([], dtype=object) array([], dtype=object) array([], dtype=object) array([], dtype=object) array([], dtype=object) array([], dtype=object) array([], dtype=object) array([], dtype=object) array([], dtype=object) array([], dtype=object) array([], dtype=object) array([], dtype=object) array([], dtype=object) array([], dtype=object) array([], dtype=object) array([], dtype=object) array([], dtype=object) array([], dtype=object) array([], dtype=object) array([], dtype=object) array([], dtype=object) array([], dtype=object) array([], dtype=object) array([], dtype=object) array([], dtype=object) array([], dtype=object) array([], dtype=object) array([], dtype=object) array([], dtype=object) array([], dtype=object) array([], dtype=object) array([], dtype=object)] | D30: False | E30: ['Ekkert' 'bannar' 'þeim' 'þó' 'að' 'aka' 'í' 'ytri' 'hring' ',' 'en' 'í' 'mikilli' 'umferð' 'má' 'búast' 'við' 'að' 'þeir' 'valdi' 'truflun' 'og' 'óþægindum' 'fyrir' 'aðra' 'ökumenn' 'haldi' 'þeir' 'sig' 'í' 'ytri' 'akrein' 'fram' 'hjá' 'svo' 'mörgum' 'gatnamótum' '.'] | F30: OK | H30: OK | I30: OK
A31: 29838 | B31: ['Meðlimir' 'hljómsveitarinnar' 'eru' 'flestir' 'mjög' 'gamlir' 'og' 'voru' 'margir' 'hættir' 'að' 'spila' 'þegar' 'þeim' 'voru' 'kallaði' 'saman' 'til' 'þessa' 'að' 'gera' 'fyrstu' 'plötuna' 'árið' '1996' '.'] | C31: [array([], dtype=object) array([], dtype=object) array([], dtype=object) array([], dtype=object) array([], dtype=object) array([], dtype=object) array([], dtype=object) array([], dtype=object) array([], dtype=object) array([], dtype=object) array([], dtype=object) array([], dtype=object) array([], dtype=object) array(['grammar'], dtype=object) array([], dtype=object) array(['grammar'], dtype=object) array([], dtype=object) array([], dtype=object) array(['grammar'], dtype=object) array([], dtype=object) array([], dtype=object) array([], dtype=object) array([], dtype=object) array([], dtype=object) array([], dtype=object) array([], dtype=object)] | D31: True | E31: ['Meðlimir' 'hljómsveitarinnar' 'eru' 'flestir' 'mjög' 'gamlir' 'og' 'voru' 'margir' 'hættir' 'að' 'spila' 'þegar' 'þeir' 'voru' 'kallaðir' 'saman' 'til' '' 'að' 'gera' 'fyrstu' 'plötuna' 'árið 1996' '.'] | F31: OK | G31: þeim -> þeir, kallaði -> kallaðir | H31: OK | I31: OK
A32: 51420 | B32: ['Vegna' 'þess' 'hve' 'góð' 'og' 'mikilvæg' 'fjárfesting' 'menntun' 'er' 'þá' 'er' 'það' 'brýn' 'nauðsyn' 'að' 'við' 'bætum' 'kerfið' 'okkar' '.'] | C32: [array([], dtype=object) array([], dtype=object) array([], dtype=object) array([], dtype=object) array([], dtype=object) array([], dtype=object) array([], dtype=object) array([], dtype=object) array(['orthography'], dtype=object) array([], dtype=object) array([], dtype=object) array([], dtype=object) array([], dtype=object) array([], dtype=object) array([], dtype=object) array([], dtype=object) array([], dtype=object) array([], dtype=object) array([], dtype=object) array([], dtype=object)] | D32: True | E32: ['Vegna' 'þess' 'hve' 'góð' 'og' 'mikilvæg' 'fjárfesting' 'menntun' 'er' ',' 'þá' 'er' 'það' 'brýn' 'nauðsyn' 'að' 'við' 'bætum' 'kerfið' 'okkar' '.'] | F32: IC | H32: F | I32: F
A33: 264 | B33: ['Guðjón' 'tók' 'við' 'starfi' 'knattspyrnustjóra' 'hjá' 'Grindavík' 'í' 'nóvember' '2011' '.'] | C33: [array([], dtype=object) array([], dtype=object) array([], dtype=object) array([], dtype=object) array([], dtype=object) array([], dtype=object) array([], dtype=object) array([], dtype=object) array([], dtype=object) array([], dtype=object) array([], dtype=object)] | D33: False | E33: ['Guðjón' 'tók' 'við' 'starfi' 'knattspyrnustjóra' 'hjá' 'Grindavík' 'í' 'nóvember' '2011' '.'] | F33: OK | H33: OK | I33: OK
A34: 56915 | B34: ['Morgunblaðið' ',' 'DV' 'og' 'Séð' 'og' 'heyrt' ')' 'og' 'Internetið' '.'] | C34: [array([], dtype=object) array([], dtype=object) array([], dtype=object) array([], dtype=object) array([], dtype=object) array([], dtype=object) array([], dtype=object) array(['orthography'], dtype=object) array([], dtype=object) array([], dtype=object) array([], dtype=object)] | D34: True | E34: ['Morgunblaðið' ',' 'DV' 'og' 'Séð' 'og' 'heyrt' '' 'og' 'Internetið' '.'] | F34: OK | G34: eina villan hér er ) | H34: OK | I34: OK
A35: 46983 | B35: ['Þeir' 'finna' 'Ófeig' 'særðan' 'eftir' 'árás' 'þrjótanna' '.'] | C35: [array([], dtype=object) array([], dtype=object) array(['style'], dtype=object) array([], dtype=object) array([], dtype=object) array([], dtype=object) array([], dtype=object) array([], dtype=object)] | D35: True | E35: ['Þeir' 'finna' 'Ófeig' 'særðan' 'eftir' 'árás' 'þrjótanna' '.'] | F35: IC | G35: engin breyting??? | H35: F | I35: IC
A36: 43861 | B36: ['Harðlínu' 'kommúnismi' 'var' 'þó' 'aldrei' 'allsráðandi' ',' 'til' 'dæmis' 'voru' 'tilraunir' 'til' 'að' 'koma' 'á' 'samyrkjubúum' 'fljótlega' 'lagðar' 'af' '.'] | C36: [array(['orthography'], dtype=object) array(['orthography'], dtype=object) array([], dtype=object) array([], dtype=object) array([], dtype=object) array([], dtype=object) array([], dtype=object) array([], dtype=object) array([], dtype=object) array([], dtype=object) array([], dtype=object) array([], dtype=object) array([], dtype=object) array([], dtype=object) array([], dtype=object) array([], dtype=object) array([], dtype=object) array([], dtype=object) array([], dtype=object) array([], dtype=object)] | D36: True | E36: ['Harðlínukommúnismi' 'var' 'þó' 'aldrei' 'allsráðandi' ',' 'til' 'dæmis' 'voru' 'tilraunir' 'til' 'að' 'koma' 'á' 'samyrkjubúum' 'fljótlega' 'lagðar' 'af' '.'] | F36: OK | G36: harðlínu kommúnismi -> eitt orð | H36: OK | I36: OK
A37: 32163 | B37: ['Ekki' 'er' 'óhugsandi' 'að' 'enn' 'eigi' 'eftir' 'að' 'koma' 'á' 'daginn' 'hver' 'hinn' 'raunverulegi' 'höfundur' 'hennar' 'var' '.'] | C37: [array([], dtype=object) array([], dtype=object) array([], dtype=object) array([], dtype=object) array([], dtype=object) array([], dtype=object) array([], dtype=object) array([], dtype=object) array([], dtype=object) array([], dtype=object) array([], dtype=object) array([], dtype=object) array([], dtype=object) array([], dtype=object) array([], dtype=object) array([], dtype=object) array([], dtype=object) array([], dtype=object)] | D37: False | E37: ['Ekki' 'er' 'óhugsandi' 'að' 'enn' 'eigi' 'eftir' 'að' 'koma' 'á' 'daginn' 'hver' 'hinn' 'raunverulegi' 'höfundur' 'hennar' 'var' '.'] | F37: OK | H37: OK | I37: OK
A38: 18666 | B38: ['Bjarni' 'Harðarson' ',' 'fyrrum' 'þingmaður' 'Framsóknarflokksins' ',' 'óskar' 'Össuri' 'Skarphéðinsson' ',' 'utanríkisráðherra' ',' 'til' 'hamingju' 'með' 'eldvoðann' 'á' 'Þingvöllum' 'og' 'umfjöllun' 'Alþingis' 'um' 'aðildarviðræður' 'við' 'Evrópusambandið' '.'] | C38: [array([], dtype=object) array([], dtype=object) array([], dtype=object) array([], dtype=object) array([], dtype=object) array([], dtype=object) array([], dtype=object) array([], dtype=object) array([], dtype=object) array([], dtype=object) array(['orthography'], dtype=object) array([], dtype=object) array(['orthography'], dtype=object) array([], dtype=object) array([], dtype=object) array([], dtype=object) array(['orthography', 'orthography'], dtype=object) array([], dtype=object) array([], dtype=object) array([], dtype=object) array([], dtype=object) array([], dtype=object) array([], dtype=object) array([], dtype=object) array([], dtype=object) array([], dtype=object) array([], dtype=object)] | D38: True | E38: ['Bjarni' 'Harðarson' ',' 'fyrrum' 'þingmaður' 'Framsóknarflokksins' ',' 'óskar' 'Össuri' 'Skarphéðinsson' '' 'utanríkisráðherra' '' 'til' 'hamingju' 'með' 'eldsvoðann' 'á' 'Þingvöllum' 'og' 'umfjöllun' 'Alþingis' 'um' 'aðildarviðræður' 'við' 'Evrópusambandið' '.'] | F38: OK | G38: eldvoðann -> eldsvoðann | H38: OK | I38: F
A39: 33966 | B39: ['Á' 'ráðstefnu' 'um' 'Samóakreppuna' 'árið' '1899' 'tóku' 'Bandaríkin' 'sér' 'yfirráð' 'yfir' 'Tutuila' 'og' 'öðrum' 'eyjum' 'austan' 'við' '171.' 'lengdargráðu' ',' 'sem' 'urðu' 'Bandaríska' 'Samóa' ',' 'en' 'eyjarnar' 'vestan' 'við' 'urðu' 'þýskt' 'yfirráðasvæði' ',' 'Þýska' 'Samóa' '.'] | C39: [array([], dtype=object) array([], dtype=object) array([], dtype=object) array([], dtype=object) array([], dtype=object) array([], dtype=object) array([], dtype=object) array([], dtype=object) array([], dtype=object) array([], dtype=object) array([], dtype=object) array([], dtype=object) array([], dtype=object) array([], dtype=object) array([], dtype=object) array([], dtype=object) array([], dtype=object) array([], dtype=object) array([], dtype=object) array([], dtype=object) array([], dtype=object) array([], dtype=object) array([], dtype=object) array([], dtype=object) array([], dtype=object) array([], dtype=object) array([], dtype=object) array([], dtype=object) array([], dtype=object) array([], dtype=object) array([], dtype=object) array([], dtype=object) array([], dtype=object) array([], dtype=object) array([], dtype=object) array([], dtype=object)] | D39: False | E39: ['Á' 'ráðstefnu' 'um' 'Samóakreppuna' 'árið' '1899' 'tóku' 'Bandaríkin' 'sér' 'yfirráð' 'yfir' 'Tutuila' 'og' 'öðrum' 'eyjum' 'austan' 'við' '171.' 'lengdargráðu' ',' 'sem' 'urðu' 'Bandaríska' 'Samóa' ',' 'en' 'eyjarnar' 'vestan' 'við' 'urðu' 'þýskt' 'yfirráðasvæði' ',' 'Þýska' 'Samóa' '.'] | F39: OK | H39: OK | I39: OK
A40: 7609 | B40: ['Setjið' 'safann' ',' 'vatn' 'og' 'sykur' 'í' 'lítinn' 'pott' 'og' 'hitið' 'yfir' 'lágum' 'hita' '.'] | C40: [array([], dtype=object) array([], dtype=object) array([], dtype=object) array([], dtype=object) array([], dtype=object) array([], dtype=object) array([], dtype=object) array([], dtype=object) array([], dtype=object) array([], dtype=object) array([], dtype=object) array([], dtype=object) array([], dtype=object) array([], dtype=object) array([], dtype=object)] | D40: False | E40: ['Setjið' 'safann' ',' 'vatn' 'og' 'sykur' 'í' 'lítinn' 'pott' 'og' 'hitið' 'yfir' 'lágum' 'hita' '.'] | F40: OK | H40: OK | I40: OK
A41: 38424 | B41: ['Myndin' 'sýnir' 'hljómsveitina' 'spila' 'fyrir' 'orkumikla' 'mannfjölda' 'og' 'slæpast' 'um' 'í' 'áfengisvímu' 'þegar' 'þeir' 'eru' 'ekki' 'að' 'spila' '.'] | C41: [array([], dtype=object) array([], dtype=object) array([], dtype=object) array([], dtype=object) array([], dtype=object) array(['style'], dtype=object) array(['style'], dtype=object) array([], dtype=object) array([], dtype=object) array([], dtype=object) array([], dtype=object) array([], dtype=object) array([], dtype=object) array([], dtype=object) array([], dtype=object) array([], dtype=object) array([], dtype=object) array([], dtype=object) array([], dtype=object)] | D41: True | E41: ['Myndin' 'sýnir' 'hljómsveitina' 'spila' 'fyrir' 'orkumiklar mannmergðir' 'og' 'slæpast' 'um' 'í' 'áfengisvímu' 'þegar' 'þeir' 'eru' 'ekki' 'að' 'spila' '.'] | F41: OK | G41: orkumikla mannfjölda -> orkumiklar mannmergðir | H41: F | I41: F
A42: 33650 | B42: ['Nýir' 'landnemar' 'voru' 'hvattir' 'til' 'þess' 'að' 'ræna' 'landi' 'frá' 'innfæddum' 'og' 'þröngva' 'þeim' 'til' 'nauðungarvinnu' '.'] | C42: [array([], dtype=object) array([], dtype=object) array([], dtype=object) array([], dtype=object) array([], dtype=object) array([], dtype=object) array([], dtype=object) array([], dtype=object) array([], dtype=object) array([], dtype=object) array([], dtype=object) array([], dtype=object) array(['style'], dtype=object) array(['style'], dtype=object) array(['style'], dtype=object) array([], dtype=object) array([], dtype=object)] | D42: True | E42: ['Nýir' 'landnemar' 'voru' 'hvattir' 'til' 'þess' 'að' 'ræna' 'landi' 'frá' 'innfæddum' 'og' 'þvinga þá í' 'nauðungarvinnu' '.'] | F42: IC | G42: þröngva þeim -> þröngva þá | H42: F | I42: IC
A43: 15109 | B43: ['"' 'Steven' 'Feldman' 'var' 'ekki' 'rekinn' '.'] | C43: [array(['orthography'], dtype=object) array([], dtype=object) array([], dtype=object) array([], dtype=object) array([], dtype=object) array([], dtype=object) array([], dtype=object)] | D43: True | E43: ['„' 'Steven' 'Feldman' 'var' 'ekki' 'rekinn' '.'] | F43: OK | G43: gæsalappir | H43: OK | I43: F
A44: 7138 | B44: ['Shilton' 'er' 'einn' 'besti' 'knattspyrnumaður' 'sem' 'England' 'hefur' 'alið' ',' 'Líka' 'sá' 'landsleikjahæsti' ',' 'en' 'árið' '1990' 'var' 'hann' 'bara' 'löngu' 'kominn' 'yfir' 'sitt' 'besta' '.'] | C44: [array([], dtype=object) array([], dtype=object) array([], dtype=object) array([], dtype=object) array([], dtype=object) array([], dtype=object) array([], dtype=object) array([], dtype=object) array([], dtype=object) array([], dtype=object) array(['style'], dtype=object) array([], dtype=object) array([], dtype=object) array([], dtype=object) array([], dtype=object) array([], dtype=object) array([], dtype=object) array([], dtype=object) array([], dtype=object) array(['style'], dtype=object) array([], dtype=object) array([], dtype=object) array([], dtype=object) array([], dtype=object) array([], dtype=object) array([], dtype=object)] | D44: True | E44: ['Shilton' 'er' 'einn' 'besti' 'knattspyrnumaður' 'sem' 'England' 'hefur' 'alið' ',' 'og' 'sá' 'landsleikjahæsti' ',' 'en' 'árið 1990' 'var' 'hann' 'einfaldlega' 'löngu' 'kominn' 'yfir' 'sitt' 'besta' '.'] | F44: OK | G44: , Líka sá -> , og sá | H44: OK | I44: F
A45: 51037 | B45: ['Fólk' 'með' 'ákveðna' 'menntun' 'kemst' 'lengra' 'en' 'aðrir' 'sem' 'bara' 'ljúka' 'grunnskólaprófi' '.'] | C45: [array([], dtype=object) array([], dtype=object) array([], dtype=object) array([], dtype=object) array([], dtype=object) array([], dtype=object) array([], dtype=object) array([], dtype=object) array([], dtype=object) array(['style'], dtype=object) array(['style'], dtype=object) array([], dtype=object) array([], dtype=object)] | D45: True | E45: ['Fólk' 'með' 'ákveðna' 'menntun' 'kemst' 'lengra' 'en' 'aðrir' 'sem' '' 'ljúka' 'bara' 'grunnskólaprófi' '.'] | F45: OK | G45: bara ljúka -> ljúka bara | H45: OK | I45: F
A46: 7052 | B46: ['Fjármunum' 'var' 'ráðstafað' 'af' 'reikningum' 'félaganna' 'með' 'millifærslum' ',' 'úttektum' 'í' 'banka' ',' 'úttektum' 'í' 'hraðbanka' 'og' 'framvísun' 'debetkorts' 'til' 'greiðslu' 'fyrir' 'vöru' 'og' 'þjónustu' '.'] | C46: [array([], dtype=object) array([], dtype=object) array([], dtype=object) array([], dtype=object) array([], dtype=object) array([], dtype=object) array([], dtype=object) array([], dtype=object) array([], dtype=object) array([], dtype=object) array([], dtype=object) array([], dtype=object) array([], dtype=object) array([], dtype=object) array([], dtype=object) array([], dtype=object) array([], dtype=object) array([], dtype=object) array([], dtype=object) array([], dtype=object) array([], dtype=object) array([], dtype=object) array(['vocabulary'], dtype=object) array([], dtype=object) array([], dtype=object) array([], dtype=object)] | D46: True | E46: ['Fjármunum' 'var' 'ráðstafað' 'af' 'reikningum' 'félaganna' 'með' 'millifærslum' ',' 'úttektum' 'í' 'banka' ',' 'úttektum' 'í' 'hraðbanka' 'og' 'framvísun' 'debetkorts' 'til' 'greiðslu' 'fyrir' 'vörur' 'og' 'þjónustu' '.'] | F46: IC | G46: vöru -> vörur | H46: OK | I46: F
A47: 4572 | B47: ['Scolari' 'var' 'þjálfari' 'liðsins' 'þegar' 'það' 'hampaði' 'heimsmeistaratitli' 'árið' '2002' 'en' 'það' 'mun' 'engu' 'skipta' '.'] | C47: [array([], dtype=object) array([], dtype=object) array([], dtype=object) array([], dtype=object) array([], dtype=object) array([], dtype=object) array([], dtype=object) array([], dtype=object) array([], dtype=object) array([], dtype=object) array([], dtype=object) array([], dtype=object) array([], dtype=object) array([], dtype=object) array([], dtype=object) array([], dtype=object)] | D47: False | E47: ['Scolari' 'var' 'þjálfari' 'liðsins' 'þegar' 'það' 'hampaði' 'heimsmeistaratitli' 'árið' '2002' 'en' 'það' 'mun' 'engu' 'skipta' '.'] | F47: OK | H47: OK | I47: OK
A48: 24079 | B48: ['Við' 'þurfum' 'bara' 'að' 'koma' 'þessum' 'leik' 'úr' 'hausnum' 'og' 'skrokknum' 'á' 'okkur' '.'] | C48: [array([], dtype=object) array([], dtype=object) array([], dtype=object) array([], dtype=object) array([], dtype=object) array([], dtype=object) array([], dtype=object) array([], dtype=object) array([], dtype=object) array([], dtype=object) array([], dtype=object) array([], dtype=object) array([], dtype=object) array([], dtype=object)] | D48: False | E48: ['Við' 'þurfum' 'bara' 'að' 'koma' 'þessum' 'leik' 'úr' 'hausnum' 'og' 'skrokknum' 'á' 'okkur' '.'] | F48: OK | H48: OK | I48: OK
A49: 17344 | B49: ['Yao' 'Ming' 'hefur' 'nóg' 'af' 'pening' 'milli' 'handanna' 'og' 'var' 'hann' 'sem' 'dæmi' 'efstur' 'á' 'lista' 'Forbes' 'yfir' 'það' 'fræga' 'fólk' 'í' 'Kína' 'sem' 'vann' 'sér' 'inn' 'mestan' 'pening' 'á' 'síðast' 'ári' '.'] | C49: [array([], dtype=object) array([], dtype=object) array([], dtype=object) array([], dtype=object) array([], dtype=object) array([], dtype=object) array([], dtype=object) array([], dtype=object) array([], dtype=object) array([], dtype=object) array([], dtype=object) array([], dtype=object) array([], dtype=object) array([], dtype=object) array([], dtype=object) array([], dtype=object) array([], dtype=object) array([], dtype=object) array([], dtype=object) array([], dtype=object) array([], dtype=object) array([], dtype=object) array([], dtype=object) array([], dtype=object) array([], dtype=object) array([], dtype=object) array([], dtype=object) array([], dtype=object) array([], dtype=object) array([], dtype=object) array([], dtype=object) array([], dtype=object) array([], dtype=object)] | D49: False | E49: ['Yao' 'Ming' 'hefur' 'nóg' 'af' 'pening' 'milli' 'handanna' 'og' 'var' 'hann' 'sem' 'dæmi' 'efstur' 'á' 'lista' 'Forbes' 'yfir' 'það' 'fræga' 'fólk' 'í' 'Kína' 'sem' 'vann' 'sér' 'inn' 'mestan' 'pening' 'á' 'síðast' 'ári' '.'] | F49: IC | G49: síðast (og pening í þgf.et.) | H49: F | I49: IC
A50: 49516 | B50: ['Það' 'er' 'innan' 'landamæra' 'Frakklands' 'með' 'strandlengju' 'að' 'Miðjarðarhafi' 'við' 'frönsku' 'rívíeruna' '.'] | C50: [array([], dtype=object) array([], dtype=object) array([], dtype=object) array([], dtype=object) array([], dtype=object) array([], dtype=object) array([], dtype=object) array([], dtype=object) array([], dtype=object) array([], dtype=object) array([], dtype=object) array([], dtype=object) array([], dtype=object)] | D50: False | E50: ['Það' 'er' 'innan' 'landamæra' 'Frakklands' 'með' 'strandlengju' 'að' 'Miðjarðarhafi' 'við' 'frönsku' 'rívíeruna' '.'] | F50: OK | H50: OK | I50: OK
A51: 48267 | B51: ['Viðarkol' 'fundust' 'í' 'göngunum' 'og' 'var' 'viðurinn' 'greindur' 'víðir' 'og' 'aldursgreindur' 'á' '13.' '-' '15.' 'öld' '.'] | C51: [array([], dtype=object) array([], dtype=object) array([], dtype=object) array([], dtype=object) array([], dtype=object) array([], dtype=object) array([], dtype=object) array([], dtype=object) array([], dtype=object) array([], dtype=object) array([], dtype=object) array([], dtype=object) array([], dtype=object) array([], dtype=object) array([], dtype=object) array([], dtype=object) array([], dtype=object)] | D51: False | E51: ['Viðarkol' 'fundust' 'í' 'göngunum' 'og' 'var' 'viðurinn' 'greindur' 'víðir' 'og' 'aldursgreindur' 'á' '13.' '-' '15.' 'öld' '.'] | F51: OK | H51: OK | I51: OK
A52: 682 | B52: ['„' 'Þetta' 'er' 'laust' 'grindverk' '.'] | C52: [array([], dtype=object) array([], dtype=object) array([], dtype=object) array([], dtype=object) array([], dtype=object) array([], dtype=object)] | D52: False | E52: ['„' 'Þetta' 'er' 'laust' 'grindverk' '.'] | F52: OK | G52: Skrítið að hafa ekki seinni gæsalöppina | H52: F | I52: OK
A53: 53242 | B53: ['Hvernig' 'haldast' 'lífshamingja' 'og' 'auður' 'saman' 'í' 'hendur' '?'] | C53: [array([], dtype=object) array([], dtype=object) array([], dtype=object) array([], dtype=object) array([], dtype=object) array([], dtype=object) array([], dtype=object) array([], dtype=object) array([], dtype=object)] | D53: False | E53: ['Hvernig' 'haldast' 'lífshamingja' 'og' 'auður' 'saman' 'í' 'hendur' '?'] | F53: OK | H53: OK | I53: F
A54: 17395 | B54: ['Ljóst' 'liggur' 'fyrir' 'að' 'verðbólgan' 'og' 'efnahagshrunið' 'hafa' 'haft' 'mikil' 'áhrif' 'á' 'rekstur' 'og' 'efnahag' 'sveitarfélaganna' '.'] | C54: [array([], dtype=object) array([], dtype=object) array([], dtype=object) array([], dtype=object) array([], dtype=object) array([], dtype=object) array([], dtype=object) array([], dtype=object) array([], dtype=object) array([], dtype=object) array([], dtype=object) array([], dtype=object) array([], dtype=object) array([], dtype=object) array([], dtype=object) array([], dtype=object) array([], dtype=object)] | D54: False | E54: ['Ljóst' 'liggur' 'fyrir' 'að' 'verðbólgan' 'og' 'efnahagshrunið' 'hafa' 'haft' 'mikil' 'áhrif' 'á' 'rekstur' 'og' 'efnahag' 'sveitarfélaganna' '.'] | F54: OK | H54: OK | I54: OK
A55: 56830 | B55: ['Þetta' 'finnst' 'mörgum' 'vanvirðing' 'fyrir' 'þeirri' 'stofnum' 'sem' 'kallast' 'hjónaband' '.'] | C55: [array([], dtype=object) array([], dtype=object) array([], dtype=object) array([], dtype=object) array([], dtype=object) array([], dtype=object) array(['style'], dtype=object) array([], dtype=object) array([], dtype=object) array([], dtype=object) array([], dtype=object)] | D55: True | E55: ['Þetta' 'finnst' 'mörgum' 'vanvirðing' 'fyrir' 'þeirri' 'stofnun' 'sem' 'kallast' 'hjónaband' '.'] | F55: OK | G55: stofnum -> stofnun | H55: OK | I55: OK
A56: 19057 | B56: ['En' 'fráfarandi' 'nefnd' 'hefur' 'lagt' 'til' 'að' 'á' 'þessum' 'stað' 'rísi' 'aðstaða' 'til' 'að' 'halda' 'minni' 'ráðstefnur' 'bæði' 'á' 'vegum' 'ríkis' ',' 'Alþingis' 'og' 'einkaaðila' '.'] | C56: [array([], dtype=object) array([], dtype=object) array([], dtype=object) array([], dtype=object) array([], dtype=object) array([], dtype=object) array([], dtype=object) array([], dtype=object) array([], dtype=object) array([], dtype=object) array([], dtype=object) array([], dtype=object) array([], dtype=object) array([], dtype=object) array([], dtype=object) array([], dtype=object) array([], dtype=object) array([], dtype=object) array([], dtype=object) array([], dtype=object) array([], dtype=object) array([], dtype=object) array([], dtype=object) array([], dtype=object) array([], dtype=object) array([], dtype=object)] | D56: False | E56: ['En' 'fráfarandi' 'nefnd' 'hefur' 'lagt' 'til' 'að' 'á' 'þessum' 'stað' 'rísi' 'aðstaða' 'til' 'að' 'halda' 'minni' 'ráðstefnur' 'bæði' 'á' 'vegum' 'ríkis' ',' 'Alþingis' 'og' 'einkaaðila' '.'] | F56: OK | H56: OK | I56: OK
A57: 49722 | B57: ['Mikið' 'er' 'af' 'litaafbrigðum' 'gára' ',' 'en' 'stökkbreytingarnar' 'eru' 'alls' '32' '.'] | C57: [array([], dtype=object) array([], dtype=object) array([], dtype=object) array([], dtype=object) array([], dtype=object) array(['orthography'], dtype=object) array([], dtype=object) array([], dtype=object) array([], dtype=object) array([], dtype=object) array([], dtype=object) array([], dtype=object)] | D57: True | E57: ['Mikið' 'er' 'af' 'litaafbrigðum' 'gára' '' 'en' 'stökkbreytingarnar' 'eru' 'alls' '32' '.'] | F57: IC | G57: kommu á undan en eytt [SRF: það er samkvæmt ritreglum, aldrei komma á undan en á íslensku] | H57: OK | I57: F
A58: 6602 | B58: ['Nýjungarnar' 'hafa' 'verið' 'mjög' 'spennandi' ',' 't.d.' 'raksápan' 'góða' 'og' 'marklínutæknin' 'en' 'líka' 'taktísku' 'brotin' 'sem' 'hafa' 'einkennt' 'útsláttakeppnina' 'og' 'dómararnir' 'eru' 'engan' 'veginn' 'búnir' 'að' 'ná' 'að' 'bregðast' 'við' '.'] | C58: [array([], dtype=object) array([], dtype=object) array([], dtype=object) array([], dtype=object) array([], dtype=object) array([], dtype=object) array([], dtype=object) array([], dtype=object) array([], dtype=object) array([], dtype=object) array([], dtype=object) array([], dtype=object) array([], dtype=object) array([], dtype=object) array([], dtype=object) array([], dtype=object) array([], dtype=object) array([], dtype=object) array(['orthography'], dtype=object) array([], dtype=object) array([], dtype=object) array([], dtype=object) array([], dtype=object) array([], dtype=object) array([], dtype=object) array([], dtype=object) array([], dtype=object) array([], dtype=object) array([], dtype=object) array([], dtype=object) array([], dtype=object)] | D58: True | E58: ['Nýjungarnar' 'hafa' 'verið' 'mjög' 'spennandi' ',' 't.d.' 'raksápan' 'góða' 'og' 'marklínutæknin' 'en' 'líka' 'taktísku' 'brotin' 'sem' 'hafa' 'einkennt' 'útsláttarkeppnina' 'og' 'dómararnir' 'eru' 'engan' 'veginn' 'búnir' 'að' 'ná' 'að' 'bregðast' 'við' '.'] | F58: OK | G58: útslátta -> útsláttar | H58: OK | I58: OK
A59: 23470 | B59: ['Aðfaranótt' 'laugardags' 'var' 'ein' 'nauðgun' 'kærð' 'sem' 'og' 'líkamsárás' '.'] | C59: [array([], dtype=object) array([], dtype=object) array([], dtype=object) array([], dtype=object) array([], dtype=object) array([], dtype=object) array([], dtype=object) array([], dtype=object) array([], dtype=object) array([], dtype=object)] | D59: False | E59: ['Aðfaranótt' 'laugardags' 'var' 'ein' 'nauðgun' 'kærð' 'sem' 'og' 'líkamsárás' '.'] | F59: OK | H59: OK | I59: OK
A60: 38360 | B60: ['Foreldara' 'hennar' 'voru' 'Stefán' 'Eiríksson' 'alþingismaður' 'og' 'bóndi' 'í' 'Árnanesi' 'og' 'Guðrún' 'Einarsdóttir' 'frá' 'Ytri-Skógum' 'undir' 'Eyjafjöllum' '.'] | C60: [array(['orthography'], dtype=object) array([], dtype=object) array([], dtype=object) array([], dtype=object) array([], dtype=object) array([], dtype=object) array([], dtype=object) array([], dtype=object) array([], dtype=object) array([], dtype=object) array([], dtype=object) array([], dtype=object) array([], dtype=object) array([], dtype=object) array([], dtype=object) array([], dtype=object) array([], dtype=object) array([], dtype=object)] | D60: True | E60: ['Foreldrar' 'hennar' 'voru' 'Stefán' 'Eiríksson' 'alþingismaður' 'og' 'bóndi' 'í' 'Árnanesi' 'og' 'Guðrún' 'Einarsdóttir' 'frá' 'Ytri-Skógum' 'undir' 'Eyjafjöllum' '.'] | F60: OK | G60: foreldara -> foreldrar | H60: OK | I60: OK
A61: 48037 | B61: ['Þegar' 'nýlendan' 'var' 'leyst' 'upp' 'árið' '1958' '-' '62' 'varð' 'Sankti' 'Lúsía' 'hluti' 'af' 'Sambandsríki' 'Vestur-Indía' '.'] | C61: [array([], dtype=object) array([], dtype=object) array([], dtype=object) array([], dtype=object) array([], dtype=object) array([], dtype=object) array([], dtype=object) array([], dtype=object) array([], dtype=object) array([], dtype=object) array([], dtype=object) array([], dtype=object) array([], dtype=object) array([], dtype=object) array([], dtype=object) array([], dtype=object) array([], dtype=object)] | D61: False | E61: ['Þegar' 'nýlendan' 'var' 'leyst' 'upp' 'árið' '1958' '-' '62' 'varð' 'Sankti' 'Lúsía' 'hluti' 'af' 'Sambandsríki' 'Vestur-Indía' '.'] | F61: OK | H61: OK | I61: OK
A62: 2694 | B62: ['Óeðlilegt' 'er' 'að' 'tengja' 'slíkan' 'atburð' 'við' 'skemmtun' ',' '“' 'bókaði' 'bæjarráð' 'Hveragerðis' '.'] | C62: [array(['orthography'], dtype=object) array([], dtype=object) array([], dtype=object) array([], dtype=object) array([], dtype=object) array([], dtype=object) array([], dtype=object) array([], dtype=object) array([], dtype=object) array([], dtype=object) array([], dtype=object) array([], dtype=object) array([], dtype=object) array([], dtype=object)] | D62: True | E62: ['„' 'Óeðlilegt' 'er' 'að' 'tengja' 'slíkan' 'atburð' 'við' 'skemmtun' ',' '“' 'bókaði' 'bæjarráð' 'Hveragerðis' '.'] | F62: OK | G62: gæsalöppum bætt við fremst | H62: OK | I62: F
A63: 7877 | B63: ['Samdráttur' 'varð' 'aftur' 'á' 'móti' 'í' 'sölu' 'vindla' 'um' 'tæplega' '1' 'prósent' '.'] | C63: [array([], dtype=object) array([], dtype=object) array([], dtype=object) array([], dtype=object) array([], dtype=object) array([], dtype=object) array([], dtype=object) array([], dtype=object) array([], dtype=object) array([], dtype=object) array([], dtype=object) array([], dtype=object) array([], dtype=object)] | D63: False | E63: ['Samdráttur' 'varð' 'aftur' 'á' 'móti' 'í' 'sölu' 'vindla' 'um' 'tæplega' '1' 'prósent' '.'] | F63: OK | H63: OK | I63: OK
A64: 41098 | B64: ['Lítið' 'er' 'vitað' 'um' 'Solveigu' 'í' 'nærri' 'tvo' 'áratugi' 'eftir' 'þetta' 'en' 'hún' 'hefur' 'ekki' 'átt' 'sér' 'öfluga' 'bandamenn' 'sem' 'treystu' 'sér' 'til' 'að' 'fara' 'gegn' 'frændum' 'hennar' '.'] | C64: [array([], dtype=object) array([], dtype=object) array([], dtype=object) array([], dtype=object) array([], dtype=object) array([], dtype=object) array([], dtype=object) array([], dtype=object) array([], dtype=object) array([], dtype=object) array([], dtype=object) array([], dtype=object) array([], dtype=object) array([], dtype=object) array([], dtype=object) array([], dtype=object) array([], dtype=object) array([], dtype=object) array([], dtype=object) array([], dtype=object) array([], dtype=object) array([], dtype=object) array([], dtype=object) array([], dtype=object) array([], dtype=object) array([], dtype=object) array([], dtype=object) array([], dtype=object) array([], dtype=object)] | D64: False | E64: ['Lítið' 'er' 'vitað' 'um' 'Solveigu' 'í' 'nærri' 'tvo' 'áratugi' 'eftir' 'þetta' 'en' 'hún' 'hefur' 'ekki' 'átt' 'sér' 'öfluga' 'bandamenn' 'sem' 'treystu' 'sér' 'til' 'að' 'fara' 'gegn' 'frændum' 'hennar' '.'] | F64: OK | G64: Ætti ekki að vera komma yfir ó-inu í Sólveig? | H64: F | I64: OK
A65: 21428 | B65: ['Fyrr' 'í' 'dag' 'töldu' 'fréttamiðlar' 'vestanhafs' ',' 'þar' 'á' 'meðal' 'ESPN' ',' 'að' 'New' 'York' 'Knicks' 'væri' 'líklegasti' 'áfangastaður' 'Nash' 'sem' 'er' 'á' '38.' 'aldursári' '.'] | C65: [array([], dtype=object) array([], dtype=object) array([], dtype=object) array([], dtype=object) array([], dtype=object) array([], dtype=object) array([], dtype=object) array([], dtype=object) array([], dtype=object) array([], dtype=object) array([], dtype=object) array([], dtype=object) array([], dtype=object) array([], dtype=object) array([], dtype=object) array([], dtype=object) array([], dtype=object) array([], dtype=object) array([], dtype=object) array([], dtype=object) array([], dtype=object) array([], dtype=object) array([], dtype=object) array([], dtype=object) array([], dtype=object) array([], dtype=object)] | D65: False | E65: ['Fyrr' 'í' 'dag' 'töldu' 'fréttamiðlar' 'vestanhafs' ',' 'þar' 'á' 'meðal' 'ESPN' ',' 'að' 'New' 'York' 'Knicks' 'væri' 'líklegasti' 'áfangastaður' 'Nash' 'sem' 'er' 'á' '38.' 'aldursári' '.'] | F65: OK | H65: OK | I65: OK
A66: 11295 | B66: ['En' 'hefur' 'lögreglan' 'heimild' 'til' 'þess' 'að' 'taka' 'saman' 'upplýsingar' 'með' 'þessum' 'hætti' '?'] | C66: [array(['orthography'], dtype=object) array(['orthography'], dtype=object) array([], dtype=object) array([], dtype=object) array([], dtype=object) array([], dtype=object) array([], dtype=object) array([], dtype=object) array([], dtype=object) array([], dtype=object) array([], dtype=object) array([], dtype=object) array([], dtype=object) array([], dtype=object)] | D66: True | E66: ['Hefur' 'lögreglan' 'heimild' 'til' 'þess' 'að' 'taka' 'saman' 'upplýsingar' 'með' 'þessum' 'hætti' '?'] | F66: IC | G66: en eytt í upphafi setningar | H66: IC | I66: IC
A67: 24332 | B67: ['Í' 'tilkynningu' 'frá' 'Atlantsolíu' 'segir' 'að' 'þetta' 'sé' 'í' 'þriðja' 'sinn' 'sem' 'dagurinn' 'er' 'haldinn' 'og' 'er' 'búist' 'við' 'fjölmenni' '.'] | C67: [array([], dtype=object) array([], dtype=object) array([], dtype=object) array([], dtype=object) array([], dtype=object) array([], dtype=object) array([], dtype=object) array([], dtype=object) array([], dtype=object) array([], dtype=object) array([], dtype=object) array([], dtype=object) array([], dtype=object) array([], dtype=object) array([], dtype=object) array([], dtype=object) array([], dtype=object) array([], dtype=object) array([], dtype=object) array([], dtype=object) array([], dtype=object)] | D67: False | E67: ['Í' 'tilkynningu' 'frá' 'Atlantsolíu' 'segir' 'að' 'þetta' 'sé' 'í' 'þriðja' 'sinn' 'sem' 'dagurinn' 'er' 'haldinn' 'og' 'er' 'búist' 'við' 'fjölmenni' '.'] | F67: OK | H67: OK | I67: OK
A68: 17444 | B68: ['Klifurgrind' 'á' 'leikssvæði' 'við' 'Engidalsskóla' 'í' 'Hafnarfirði' 'þar' 'sem' 'átta' 'ára' 'stúlka' 'var' 'hætt' 'komin' 'í' 'fyrradag' 'hefur' 'verið' 'tekin' 'niður' '.'] | C68: [array([], dtype=object) array([], dtype=object) array(['orthography'], dtype=object) array([], dtype=object) array([], dtype=object) array([], dtype=object) array([], dtype=object) array([], dtype=object) array([], dtype=object) array([], dtype=object) array([], dtype=object) array([], dtype=object) array([], dtype=object) array([], dtype=object) array([], dtype=object) array([], dtype=object) array([], dtype=object) array([], dtype=object) array([], dtype=object) array([], dtype=object) array([], dtype=object) array([], dtype=object)] | D68: True | E68: ['Klifurgrind' 'á' 'leiksvæði' 'við' 'Engidalsskóla' 'í' 'Hafnarfirði' 'þar' 'sem' 'átta' 'ára' 'stúlka' 'var' 'hætt' 'komin' 'í' 'fyrradag' 'hefur' 'verið' 'tekin' 'niður' '.'] | F68: OK | G68: leikssvæði -> leiksvæði | H68: OK | I68: OK
A69: 40229 | B69: ['Hugtakið' 'tyggigúmmítónlist' 'var' 'sett' 'fram' 'af' 'Kasenetz-Katz' '.'] | C69: [array([], dtype=object) array(['style'], dtype=object) array([], dtype=object) array([], dtype=object) array([], dtype=object) array([], dtype=object) array(['orthography', 'orthography'], dtype=object) array([], dtype=object)] | D69: True | E69: ['Hugtakið' 'tyggjótónlist' 'var' 'sett' 'fram' 'af' 'Kasenetz og Katz' '.'] | F69: IC | G69: tyggigúmmí -> tyggjó | H69: IC | I69: IC
A70: 56761 | B70: ['Berum' 'þetta' 'svo' 'saman' 'við' 'einstakling' 'sem' 'að' 'loknum' 'grunnskóla' 'fer' 'í' 'iðnskóla' 'og' 'lærir' 'þá' 'iðngrein' 'sem' 'hann' 'kann' 'að' 'hafa' 'áhuga' 'á' '.'] | C70: [array([], dtype=object) array([], dtype=object) array([], dtype=object) array([], dtype=object) array([], dtype=object) array([], dtype=object) array([], dtype=object) array([], dtype=object) array([], dtype=object) array([], dtype=object) array([], dtype=object) array([], dtype=object) array([], dtype=object) array([], dtype=object) array([], dtype=object) array([], dtype=object) array([], dtype=object) array([], dtype=object) array([], dtype=object) array([], dtype=object) array([], dtype=object) array([], dtype=object) array([], dtype=object) array([], dtype=object) array([], dtype=object)] | D70: False | E70: ['Berum' 'þetta' 'svo' 'saman' 'við' 'einstakling' 'sem' 'að' 'loknum' 'grunnskóla' 'fer' 'í' 'iðnskóla' 'og' 'lærir' 'þá' 'iðngrein' 'sem' 'hann' 'kann' 'að' 'hafa' 'áhuga' 'á' '.'] | F70: OK | H70: OK | I70: OK
A71: 465 | B71: ['Við' 'mætum' 'ekki' 'á' 'æfingar' 'til' 'að' 'reykja' 'vindla' 'og' 'spila' 'spil' '.'] | C71: [array([], dtype=object) array([], dtype=object) array([], dtype=object) array([], dtype=object) array([], dtype=object) array([], dtype=object) array([], dtype=object) array([], dtype=object) array([], dtype=object) array([], dtype=object) array([], dtype=object) array([], dtype=object) array([], dtype=object)] | D71: False | E71: ['Við' 'mætum' 'ekki' 'á' 'æfingar' 'til' 'að' 'reykja' 'vindla' 'og' 'spila' 'spil' '.'] | F71: OK | H71: OK | I71: OK
A72: 53523 | B72: ['Sjálfur' 'er' 'ég' 'rétt' 'skriðinn' 'yfir' 'tvítugt' 'og' 'telst' 'ekki' 'mjög' 'lífsreyndur' 'en' 'þó' 'er' 'ég' 'það' 'reyndur' 'að' 'ég' 'veit' 'að' 'hamingjan' 'finnst' 'ekki' 'í' 'peningum' '.'] | C72: [array([], dtype=object) array([], dtype=object) array([], dtype=object) array([], dtype=object) array([], dtype=object) array([], dtype=object) array([], dtype=object) array([], dtype=object) array([], dtype=object) array([], dtype=object) array([], dtype=object) array([], dtype=object) array([], dtype=object) array([], dtype=object) array([], dtype=object) array([], dtype=object) array([], dtype=object) array([], dtype=object) array([], dtype=object) array([], dtype=object) array([], dtype=object) array([], dtype=object) array([], dtype=object) array([], dtype=object) array([], dtype=object) array([], dtype=object) array([], dtype=object) array([], dtype=object)] | D72: False | E72: ['Sjálfur' 'er' 'ég' 'rétt' 'skriðinn' 'yfir' 'tvítugt' 'og' 'telst' 'ekki' 'mjög' 'lífsreyndur' 'en' 'þó' 'er' 'ég' 'það' 'reyndur' 'að' 'ég' 'veit' 'að' 'hamingjan' 'finnst' 'ekki' 'í' 'peningum' '.'] | F72: OK | H72: OK | I72: OK
A73: 6252 | B73: ['Kolbeinn' 'sagði' 'eftir' 'að' 'síðasta' 'keppnistímabili' 'lauk' 'að' 'hann' 'vildi' 'reyna' 'fyrir' 'sér' 'utan' 'Hollands' 'og' 'hann' 'var' 'orðaður' 'við' 'nokkur' 'lið' ',' 'til' 'að' 'mynda' 'í' 'Englandi' '.' 'En' 'ekkert' 'varð' 'af' 'félagaskiptunum' '.'] | C73: [array([], dtype=object) array([], dtype=object) array([], dtype=object) array([], dtype=object) array([], dtype=object) array([], dtype=object) array([], dtype=object) array([], dtype=object) array([], dtype=object) array([], dtype=object) array([], dtype=object) array([], dtype=object) array([], dtype=object) array([], dtype=object) array([], dtype=object) array([], dtype=object) array([], dtype=object) array([], dtype=object) array([], dtype=object) array([], dtype=object) array([], dtype=object) array([], dtype=object) array([], dtype=object) array([], dtype=object) array([], dtype=object) array([], dtype=object) array([], dtype=object) array([], dtype=object) array(['orthography'], dtype=object) array(['orthography'], dtype=object) array([], dtype=object) array([], dtype=object) array([], dtype=object) array([], dtype=object) array([], dtype=object)] | D73: True | E73: ['Kolbeinn' 'sagði' 'eftir' 'að' 'síðasta' 'keppnistímabili' 'lauk' 'að' 'hann' 'vildi' 'reyna' 'fyrir' 'sér' 'utan' 'Hollands' 'og' 'hann' 'var' 'orðaður' 'við' 'nokkur' 'lið' ',' 'til' 'að' 'mynda' 'í' 'Englandi' 'en' 'ekkert' 'varð' 'af' 'félagaskiptunum' '.'] | F73: OK | G73: . En ekkert -> en ekkert | H73: OK | I73: F
A74: 47291 | B74: ['Á' 'Íslandi' 'fékk' 'Rauði' 'krossinn' 'leyfi' 'fyrir' 'þessum' 'spilum' 'árið' '1972' 'sem' 'var' 'upphafið' 'að' 'spilakassarekstri' 'samtakanna' '.'] | C74: [array([], dtype=object) array([], dtype=object) array([], dtype=object) array([], dtype=object) array([], dtype=object) array([], dtype=object) array([], dtype=object) array([], dtype=object) array([], dtype=object) array([], dtype=object) array([], dtype=object) array([], dtype=object) array([], dtype=object) array([], dtype=object) array(['grammar'], dtype=object) array([], dtype=object) array([], dtype=object) array([], dtype=object)] | D74: True | E74: ['Á' 'Íslandi' 'fékk' 'Rauði' 'krossinn' 'leyfi' 'fyrir' 'þessum' 'spilum' 'árið 1972' 'sem' 'var' 'upphafið' 'á' 'spilakassarekstri' 'samtakanna' '.'] | F74: IC | G74: upphafið að -> upphafið á | H74: IC | I74: IC
A75: 18965 | B75: ['Jenson' 'Button' 'er' 'efstur' 'í' 'stigamótinu' ',' 'en' 'Vettel' 'og' 'Webber' 'hafa' 'færst' 'upp' 'fyrir' 'Rubens' 'Barrichello' '.'] | C75: [array([], dtype=object) array([], dtype=object) array([], dtype=object) array([], dtype=object) array([], dtype=object) array([], dtype=object) array([], dtype=object) array([], dtype=object) array([], dtype=object) array([], dtype=object) array([], dtype=object) array([], dtype=object) array([], dtype=object) array([], dtype=object) array([], dtype=object) array([], dtype=object) array([], dtype=object) array([], dtype=object)] | D75: False | E75: ['Jenson' 'Button' 'er' 'efstur' 'í' 'stigamótinu' ',' 'en' 'Vettel' 'og' 'Webber' 'hafa' 'færst' 'upp' 'fyrir' 'Rubens' 'Barrichello' '.'] | F75: OK | H75: OK | I75: OK
A76: 5786 | B76: ['Þá' 'bætist' 'við' 'að' 'ekki' 'megi' 'blanda' 'saman' 'fisktegundum' 'í' 'körum' '.'] | C76: [array([], dtype=object) array([], dtype=object) array([], dtype=object) array([], dtype=object) array([], dtype=object) array([], dtype=object) array([], dtype=object) array([], dtype=object) array([], dtype=object) array([], dtype=object) array([], dtype=object) array([], dtype=object)] | D76: False | E76: ['Þá' 'bætist' 'við' 'að' 'ekki' 'megi' 'blanda' 'saman' 'fisktegundum' 'í' 'körum' '.'] | F76: OK | H76: OK | I76: OK
A77: 26516 | B77: ['Holtavirkjun' 'og' 'Hvammsvirkjun' 'eru' 'í' 'fimmtánda' 'og' 'sextánda' 'sæti' 'yfir' 'svæði' 'sem' 'æskilegt' 'er' 'að' 'virkja' 'og' 'í' 'tuttugasta' 'og' 'áttunda' 'sæti' 'er' 'síðan' 'Urriðafossvirkjun' '.'] | C77: [array([], dtype=object) array([], dtype=object) array([], dtype=object) array([], dtype=object) array([], dtype=object) array([], dtype=object) array([], dtype=object) array([], dtype=object) array([], dtype=object) array([], dtype=object) array([], dtype=object) array([], dtype=object) array([], dtype=object) array([], dtype=object) array([], dtype=object) array([], dtype=object) array([], dtype=object) array([], dtype=object) array([], dtype=object) array([], dtype=object) array([], dtype=object) array([], dtype=object) array([], dtype=object) array(['vocabulary'], dtype=object) array([], dtype=object) array([], dtype=object)] | D77: True | E77: ['Holtavirkjun' 'og' 'Hvammsvirkjun' 'eru' 'í' 'fimmtánda' 'og' 'sextánda' 'sæti' 'yfir' 'svæði' 'sem' 'æskilegt' 'er' 'að' 'virkja' 'og' 'í' 'tuttugasta' 'og' 'áttunda' 'sæti' 'er' '' 'Urriðafossvirkjun' '.'] | F77: OK | G77: síðan eytt | H77: F | I77: IC
A78: 34282 | B78: ['Hún' 'gerði' 'mörg' 'verk' 'tengd' 'Valentínusardegi' ',' 'Degi' 'heilags' 'Patreks' ',' '4.' 'júlí' ',' 'Hrekkjavöku' 'og' 'Jólum' '.'] | C78: [array([], dtype=object) array([], dtype=object) array([], dtype=object) array([], dtype=object) array([], dtype=object) array(['grammar'], dtype=object) array([], dtype=object) array(['orthography'], dtype=object) array([], dtype=object) array([], dtype=object) array([], dtype=object) array([], dtype=object) array([], dtype=object) array([], dtype=object) array(['orthography'], dtype=object) array([], dtype=object) array(['orthography'], dtype=object) array([], dtype=object)] | D78: True | E78: ['Hún' 'gerði' 'mörg' 'verk' 'tengd' 'Valentínusardeginum' ',' 'degi' 'heilags' 'Patreks' ',' '4. júlí' ',' 'hrekkjavöku' 'og' 'jólum' '.'] | F78: IC | G78: Valentínusardegi -> Valentínusardeginum | H78: F | I78: IC
A79: 57864 | B79: ['Lífið' 'er' 'allt' 'of' 'stutt' 'til' 'þess' 'að' 'velta' 'sér' 'upp' 'úr' 'því' 'sem' 'miður' 'fer' '.'] | C79: [array([], dtype=object) array([], dtype=object) array([], dtype=object) array([], dtype=object) array([], dtype=object) array([], dtype=object) array([], dtype=object) array([], dtype=object) array([], dtype=object) array([], dtype=object) array([], dtype=object) array([], dtype=object) array([], dtype=object) array([], dtype=object) array([], dtype=object) array([], dtype=object) array([], dtype=object)] | D79: False | E79: ['Lífið' 'er' 'allt' 'of' 'stutt' 'til' 'þess' 'að' 'velta' 'sér' 'upp' 'úr' 'því' 'sem' 'miður' 'fer' '.'] | F79: OK | H79: OK | I79: OK
A80: 19119 | B80: ['Í' 'fyrsta' 'lagi' 'eru' 'fáir' 'sérlega' 'skemmtilegir' 'þannig' 'og' 'í' 'öðru' 'lagi' 'breytist' 'ástandið' 'lítið' 'við' 'að' 'láta' 'reiðina' 'taka' 'völdin' '.'] | C80: [array([], dtype=object) array([], dtype=object) array([], dtype=object) array([], dtype=object) array([], dtype=object) array([], dtype=object) array([], dtype=object) array([], dtype=object) array([], dtype=object) array([], dtype=object) array([], dtype=object) array([], dtype=object) array([], dtype=object) array([], dtype=object) array([], dtype=object) array([], dtype=object) array([], dtype=object) array([], dtype=object) array([], dtype=object) array([], dtype=object) array([], dtype=object) array([], dtype=object)] | D80: False | E80: ['Í' 'fyrsta' 'lagi' 'eru' 'fáir' 'sérlega' 'skemmtilegir' 'þannig' 'og' 'í' 'öðru' 'lagi' 'breytist' 'ástandið' 'lítið' 'við' 'að' 'láta' 'reiðina' 'taka' 'völdin' '.'] | F80: OK | H80: OK | I80: OK
A81: 25409 | B81: ['Það' 'myndi' 'vera' 'mér' 'allt' 'ef' 'ég' 'næði' 'að' 'vinna' 'á' 'heimavelli' ',' 'draumur' 'sem' 'myndi' 'rætast' '.'] | C81: [array([], dtype=object) array([], dtype=object) array([], dtype=object) array([], dtype=object) array([], dtype=object) array([], dtype=object) array([], dtype=object) array([], dtype=object) array([], dtype=object) array([], dtype=object) array([], dtype=object) array([], dtype=object) array([], dtype=object) array([], dtype=object) array([], dtype=object) array([], dtype=object) array([], dtype=object) array([], dtype=object)] | D81: False | E81: ['Það' 'myndi' 'vera' 'mér' 'allt' 'ef' 'ég' 'næði' 'að' 'vinna' 'á' 'heimavelli' ',' 'draumur' 'sem' 'myndi' 'rætast' '.'] | F81: OK | H81: OK | I81: OK
A82: 16520 | B82: ['Akstur' 'undir' 'áhrifum' 'vímuefna' 'hefur' 'færst' 'verulega' 'í' 'vöxt' 'á' 'Akureyri' 'síðustu' 'misserin' ',' 'líkt' 'og' 'víða' 'annars' 'staðar' 'á' 'landinu' 'og' 'eru' 'slík' 'tilvik' 'sumstaðar' 'orðin' 'algengari' 'en' 'ölvunarakstur' '.'] | C82: [array([], dtype=object) array([], dtype=object) array([], dtype=object) array([], dtype=object) array([], dtype=object) array([], dtype=object) array([], dtype=object) array([], dtype=object) array([], dtype=object) array([], dtype=object) array([], dtype=object) array([], dtype=object) array([], dtype=object) array([], dtype=object) array([], dtype=object) array([], dtype=object) array([], dtype=object) array([], dtype=object) array([], dtype=object) array([], dtype=object) array(['orthography'], dtype=object) array([], dtype=object) array([], dtype=object) array([], dtype=object) array([], dtype=object) array(['orthography'], dtype=object) array([], dtype=object) array([], dtype=object) array([], dtype=object) array([], dtype=object) array([], dtype=object)] | D82: True | E82: ['Akstur' 'undir' 'áhrifum' 'vímuefna' 'hefur' 'færst' 'verulega' 'í' 'vöxt' 'á' 'Akureyri' 'síðustu' 'misserin' ',' 'líkt' 'og' 'víða' 'annars' 'staðar' 'á' 'landinu' ',' 'og' 'eru' 'slík' 'tilvik' 'sums staðar' 'orðin' 'algengari' 'en' 'ölvunarakstur' '.'] | F82: OK | G82: sumstaðar -> sums staðar | H82: OK | I82: F
A83: 50519 | B83: ['Þeir' 'voru' 'svangir' 'og' 'blankir' 'eitt' 'föstudagskvöld' 'og' 'fengu' 'þá' 'að' 'vita' 'að' 'það' 'væri' 'frír' 'bjór' 'og' 'pítsa' 'fyrir' 'þá' 'sem' 'skráðu' 'sig' 'í' 'flokkinn' 'það' 'kvöldið' '.'] | C83: [array([], dtype=object) array([], dtype=object) array([], dtype=object) array([], dtype=object) array([], dtype=object) array([], dtype=object) array([], dtype=object) array([], dtype=object) array([], dtype=object) array([], dtype=object) array([], dtype=object) array([], dtype=object) array([], dtype=object) array([], dtype=object) array([], dtype=object) array([], dtype=object) array([], dtype=object) array([], dtype=object) array([], dtype=object) array([], dtype=object) array([], dtype=object) array([], dtype=object) array([], dtype=object) array([], dtype=object) array([], dtype=object) array([], dtype=object) array([], dtype=object) array([], dtype=object) array([], dtype=object)] | D83: False | E83: ['Þeir' 'voru' 'svangir' 'og' 'blankir' 'eitt' 'föstudagskvöld' 'og' 'fengu' 'þá' 'að' 'vita' 'að' 'það' 'væri' 'frír' 'bjór' 'og' 'pítsa' 'fyrir' 'þá' 'sem' 'skráðu' 'sig' 'í' 'flokkinn' 'það' 'kvöldið' '.'] | F83: OK | H83: OK | I83: OK
A84: 558 | B84: ['Sjóðurinn' 'dreifir' 'áhættunni' 'á' 'bankana' 'sex' 'þúsund' 'og' 'færir' 'þannig' 'áhættuna' 'af' 'ríkissjóðum' 'aðildarríkjanna' 'og' 'evrópskum' 'skattgreiðendum' '.'] | C84: [array([], dtype=object) array([], dtype=object) array([], dtype=object) array([], dtype=object) array([], dtype=object) array([], dtype=object) array([], dtype=object) array([], dtype=object) array([], dtype=object) array([], dtype=object) array([], dtype=object) array([], dtype=object) array([], dtype=object) array([], dtype=object) array([], dtype=object) array([], dtype=object) array([], dtype=object) array([], dtype=object)] | D84: False | E84: ['Sjóðurinn' 'dreifir' 'áhættunni' 'á' 'bankana' 'sex' 'þúsund' 'og' 'færir' 'þannig' 'áhættuna' 'af' 'ríkissjóðum' 'aðildarríkjanna' 'og' 'evrópskum' 'skattgreiðendum' '.'] | F84: OK | H84: OK | I84: OK
A85: 52604 | B85: ['Koma' 'má' 'í' 'veg' 'fyrir' 'þjófnað' 'með' 'því' 'að' 'telja' 'ekki' 'sjaldgæfa' 'hluti' 'verðmæta' '.'] | C85: [array([], dtype=object) array([], dtype=object) array([], dtype=object) array([], dtype=object) array([], dtype=object) array([], dtype=object) array([], dtype=object) array([], dtype=object) array([], dtype=object) array([], dtype=object) array([], dtype=object) array([], dtype=object) array([], dtype=object) array([], dtype=object) array([], dtype=object)] | D85: False | E85: ['Koma' 'má' 'í' 'veg' 'fyrir' 'þjófnað' 'með' 'því' 'að' 'telja' 'ekki' 'sjaldgæfa' 'hluti' 'verðmæta' '.'] | F85: OK | H85: OK | I85: OK
A86: 9041 | B86: ['Sjómaðurinn' 'káti' 'er' 'í' 'skýjunum' 'með' 'fenginn' 'en' 'fiskurinn' 'verður' 'verkaður' 'í' 'fiskverkuninni' 'Þorbjörn' 'í' 'Grindavík' '.'] | C86: [array([], dtype=object) array([], dtype=object) array([], dtype=object) array([], dtype=object) array([], dtype=object) array([], dtype=object) array([], dtype=object) array([], dtype=object) array([], dtype=object) array([], dtype=object) array([], dtype=object) array([], dtype=object) array([], dtype=object) array(['grammar', 'grammar'], dtype=object) array([], dtype=object) array([], dtype=object) array([], dtype=object)] | D86: True | E86: ['Sjómaðurinn' 'káti' 'er' 'í' 'skýjunum' 'með' 'fenginn' 'en' 'fiskurinn' 'verður' 'verkaður' 'í' 'fiskverkuninni' 'Þorbirni' 'í' 'Grindavík' '.'] | F86: OK | G86: Þorbjörn -> Þorbirni | H86: OK | I86: F
A87: 2295 | B87: ['Sérstakt' 'átak' 'í' 'hagræðingarferlinu' 'muni' 'standa' 'yfir' 'í' 'ár' 'og' 'næsta' 'ár' '.'] | C87: [array([], dtype=object) array([], dtype=object) array([], dtype=object) array([], dtype=object) array([], dtype=object) array([], dtype=object) array([], dtype=object) array([], dtype=object) array([], dtype=object) array([], dtype=object) array([], dtype=object) array([], dtype=object) array([], dtype=object)] | D87: False | E87: ['Sérstakt' 'átak' 'í' 'hagræðingarferlinu' 'muni' 'standa' 'yfir' 'í' 'ár' 'og' 'næsta' 'ár' '.'] | F87: OK | H87: OK | I87: OK
A88: 25786 | B88: ['Þau' 'voru' '10,6' 'milljörðum' 'króna' 'lakari' 'en' 'á' 'sama' 'tímabili' 'á' 'síðasta' 'ári' '.'] | C88: [array([], dtype=object) array([], dtype=object) array([], dtype=object) array([], dtype=object) array([], dtype=object) array([], dtype=object) array([], dtype=object) array([], dtype=object) array([], dtype=object) array([], dtype=object) array([], dtype=object) array([], dtype=object) array([], dtype=object) array([], dtype=object)] | D88: False | E88: ['Þau' 'voru' '10,6' 'milljörðum' 'króna' 'lakari' 'en' 'á' 'sama' 'tímabili' 'á' 'síðasta' 'ári' '.'] | F88: OK | H88: OK | I88: OK
A89: 44170 | B89: ['Konan' 'fékk' 'drepbólu' 'á' 'eyra' 'en' 'læknaðist' ',' 'maður' 'á' 'bænum' 'fékk' 'bólu' 'á' 'vör' 'og' 'dó' '.'] | C89: [array([], dtype=object) array([], dtype=object) array([], dtype=object) array([], dtype=object) array([], dtype=object) array([], dtype=object) array([], dtype=object) array([], dtype=object) array([], dtype=object) array([], dtype=object) array([], dtype=object) array([], dtype=object) array([], dtype=object) array([], dtype=object) array([], dtype=object) array([], dtype=object) array([], dtype=object) array([], dtype=object)] | D89: False | E89: ['Konan' 'fékk' 'drepbólu' 'á' 'eyra' 'en' 'læknaðist' ',' 'maður' 'á' 'bænum' 'fékk' 'bólu' 'á' 'vör' 'og' 'dó' '.'] | F89: OK | H89: OK | I89: OK
A90: 27144 | B90: ['Þetta' 'sýna' 'niðurstöður' 'nýjustu' 'verðkönnunar' 'ASÍ' '.'] | C90: [array([], dtype=object) array([], dtype=object) array([], dtype=object) array([], dtype=object) array([], dtype=object) array([], dtype=object) array([], dtype=object)] | D90: False | E90: ['Þetta' 'sýna' 'niðurstöður' 'nýjustu' 'verðkönnunar' 'ASÍ' '.'] | F90: OK | H90: OK | I90: OK
A91: 53993 | B91: ['Einnig' 'mætti' 'líka' 'færa' 'eitthvað' 'af' 'kennslunni' 'í' 'leikskólana' ',' 'byrja' 'að' 'kenna' 'krökkum' 'stafrófið' 'þegar' 'þau' 'eru' 'fimm' 'ára' '.'] | C91: [array([], dtype=object) array([], dtype=object) array([], dtype=object) array([], dtype=object) array([], dtype=object) array([], dtype=object) array([], dtype=object) array([], dtype=object) array([], dtype=object) array([], dtype=object) array([], dtype=object) array([], dtype=object) array([], dtype=object) array([], dtype=object) array([], dtype=object) array([], dtype=object) array([], dtype=object) array([], dtype=object) array([], dtype=object) array([], dtype=object) array([], dtype=object)] | D91: False | E91: ['Einnig' 'mætti' 'líka' 'færa' 'eitthvað' 'af' 'kennslunni' 'í' 'leikskólana' ',' 'byrja' 'að' 'kenna' 'krökkum' 'stafrófið' 'þegar' 'þau' 'eru' 'fimm' 'ára' '.'] | F91: OK | G91: en þau ætti strangt til tekið að vera þeir | H91: OK | I91: OK
A92: 14600 | B92: ['"' 'Loksins' ',' 'eftir' 'að' 'hafa' 'kysst' 'marga' 'froska' ',' 'hef' 'ég' 'fundið' 'prinsinn' 'minn' '.' '"'] | C92: [array(['orthography'], dtype=object) array([], dtype=object) array([], dtype=object) array([], dtype=object) array([], dtype=object) array([], dtype=object) array([], dtype=object) array([], dtype=object) array([], dtype=object) array([], dtype=object) array([], dtype=object) array([], dtype=object) array([], dtype=object) array([], dtype=object) array([], dtype=object) array([], dtype=object) array(['orthography'], dtype=object)] | D92: True | E92: ['„' 'Loksins' ',' 'eftir' 'að' 'hafa' 'kysst' 'marga' 'froska' ',' 'hef' 'ég' 'fundið' 'prinsinn' 'minn' '.' '“'] | F92: OK | G92: gæsalappir | H92: OK | I92: F
A93: 25869 | B93: ['Svíþjóð' 'lagði' 'Bandaríkin' '2' '-' '1' 'í' 'lokaumferð' 'C-riðils' 'á' 'heimsmeistaramóti' 'kvenna' 'í' 'knattspyrnu' 'í' 'gærkvöldi' '.'] | C93: [array([], dtype=object) array([], dtype=object) array([], dtype=object) array([], dtype=object) array([], dtype=object) array([], dtype=object) array([], dtype=object) array([], dtype=object) array([], dtype=object) array([], dtype=object) array([], dtype=object) array([], dtype=object) array([], dtype=object) array([], dtype=object) array([], dtype=object) array([], dtype=object) array([], dtype=object)] | D93: False | E93: ['Svíþjóð' 'lagði' 'Bandaríkin' '2' '-' '1' 'í' 'lokaumferð' 'C-riðils' 'á' 'heimsmeistaramóti' 'kvenna' 'í' 'knattspyrnu' 'í' 'gærkvöldi' '.'] | F93: OK | H93: OK | I93: OK
A94: 56236 | B94: ['Þannig' 'græðir' 'hún' 'eitt' 'ár' 'og' 'þá' 'er' 'hún' 'komin' 'á' 'sama' 'stað' 'og' 'með' 'því' 'sem' 'hún' 'lagði' 'fram' '.'] | C94: [array([], dtype=object) array([], dtype=object) array([], dtype=object) array([], dtype=object) array([], dtype=object) array([], dtype=object) array([], dtype=object) array([], dtype=object) array([], dtype=object) array([], dtype=object) array([], dtype=object) array([], dtype=object) array([], dtype=object) array([], dtype=object) array([], dtype=object) array([], dtype=object) array([], dtype=object) array([], dtype=object) array([], dtype=object) array([], dtype=object) array([], dtype=object)] | D94: False | E94: ['Þannig' 'græðir' 'hún' 'eitt' 'ár' 'og' 'þá' 'er' 'hún' 'komin' 'á' 'sama' 'stað' 'og' 'með' 'því' 'sem' 'hún' 'lagði' 'fram' '.'] | F94: OK | H94: OK | I94: OK
A95: 8885 | B95: ['Þess' 'í' 'stað' 'er' 'áhorfendum' ',' 'á' 'öllum' 'aldri' ',' 'boðið' 'að' 'fylla' 'inn' 'í' 'eyðurnar' 'af' 'sinni' 'eigin' 'list' 'og' 'gefa' 'ímyndunaraflinu' 'lausan' 'tauminn' '.'] | C95: [array([], dtype=object) array([], dtype=object) array([], dtype=object) array([], dtype=object) array([], dtype=object) array([], dtype=object) array([], dtype=object) array([], dtype=object) array([], dtype=object) array([], dtype=object) array([], dtype=object) array([], dtype=object) array([], dtype=object) array([], dtype=object) array([], dtype=object) array([], dtype=object) array([], dtype=object) array([], dtype=object) array([], dtype=object) array([], dtype=object) array([], dtype=object) array([], dtype=object) array([], dtype=object) array([], dtype=object) array([], dtype=object) array([], dtype=object)] | D95: False | E95: ['Þess' 'í' 'stað' 'er' 'áhorfendum' ',' 'á' 'öllum' 'aldri' ',' 'boðið' 'að' 'fylla' 'inn' 'í' 'eyðurnar' 'af' 'sinni' 'eigin' 'list' 'og' 'gefa' 'ímyndunaraflinu' 'lausan' 'tauminn' '.'] | F95: OK | H95: OK | I95: OK
A96: 6709 | B96: ['„' 'Þetta' 'snýst' 'um' 'að' 'við' 'reynum' 'að' 'fjölga' 'þessum' 'köflum' 'og' 'þeir' 'reyna' 'að' 'hafa' 'þá' 'sem' 'fæsta' 'og' 'við' 'erum' 'enn' 'að' 'finna' 'okkur' 'dálítið' '.'] | C96: [array([], dtype=object) array([], dtype=object) array([], dtype=object) array([], dtype=object) array([], dtype=object) array([], dtype=object) array([], dtype=object) array([], dtype=object) array([], dtype=object) array([], dtype=object) array([], dtype=object) array([], dtype=object) array([], dtype=object) array([], dtype=object) array([], dtype=object) array([], dtype=object) array([], dtype=object) array([], dtype=object) array([], dtype=object) array([], dtype=object) array([], dtype=object) array([], dtype=object) array(['style'], dtype=object) array([], dtype=object) array([], dtype=object) array([], dtype=object) array(['style'], dtype=object) array([], dtype=object)] | D96: True | E96: ['„' 'Þetta' 'snýst' 'um' 'að' 'við' 'reynum' 'að' 'fjölga' 'þessum' 'köflum' 'og' 'þeir' 'reyna' 'að' 'hafa' 'þá' 'sem' 'fæsta' 'og' 'við' 'erum' 'enn' 'dálítið' 'að' 'finna' 'okkur' '' '.'] | F96: OK | G96: dálítið fært til [SRF: Það ætti klárlega ekki að færa það til innan beinnar tilvitnunar] | H96: F | I96: F
A97: 48097 | B97: ['Faðir' 'hans' ',' 'William' 'Hunter' 'Stanger' ',' 'var' 'frá' 'Orkneyjum' 'en' 'móðirin' ',' 'Sarah' 'Gudfinna' 'Johnston' '(' 'Guðfinna' 'Jónsdóttir' ')' 'var' 'íslensk' 'en' 'ekki' 'er' 'vitað' 'um' 'ætt' 'hennar' 'eða' 'hvaðan' 'af' 'Íslandi' 'hún' 'var' '.'] | C97: [array([], dtype=object) array([], dtype=object) array([], dtype=object) array([], dtype=object) array([], dtype=object) array([], dtype=object) array([], dtype=object) array([], dtype=object) array([], dtype=object) array([], dtype=object) array([], dtype=object) array([], dtype=object) array([], dtype=object) array([], dtype=object) array([], dtype=object) array([], dtype=object) array([], dtype=object) array([], dtype=object) array([], dtype=object) array([], dtype=object) array([], dtype=object) array([], dtype=object) array([], dtype=object) array([], dtype=object) array([], dtype=object) array([], dtype=object) array([], dtype=object) array([], dtype=object) array([], dtype=object) array([], dtype=object) array([], dtype=object) array([], dtype=object) array([], dtype=object) array([], dtype=object) array([], dtype=object) array([], dtype=object)] | D97: False | E97: ['Faðir' 'hans' ',' 'William' 'Hunter' 'Stanger' ',' 'var' 'frá' 'Orkneyjum' 'en' 'móðirin' ',' 'Sarah' 'Gudfinna' 'Johnston' '(' 'Guðfinna' 'Jónsdóttir' ')' 'var' 'íslensk' 'en' 'ekki' 'er' 'vitað' 'um' 'ætt' 'hennar' 'eða' 'hvaðan' 'af' 'Íslandi' 'hún' 'var' '.'] | F97: OK | H97: OK | I97: OK
A98: 32744 | B98: ['Ég' 'hugsaði' 'að' 'ég' 'ætti' 'nógu' 'erfitt' 'með' 'að' 'fá' 'leikarahutverk' ',' 'svo' 'ég' 'bjó' 'til' 'Martin' 'Sheen' '.'] | C98: [array([], dtype=object) array(['grammar', 'grammar'], dtype=object) array([], dtype=object) array([], dtype=object) array([], dtype=object) array([], dtype=object) array([], dtype=object) array([], dtype=object) array([], dtype=object) array([], dtype=object) array([], dtype=object) array([], dtype=object) array([], dtype=object) array([], dtype=object) array([], dtype=object) array([], dtype=object) array([], dtype=object) array([], dtype=object) array([], dtype=object)] | D98: True | E98: ['Ég' 'hugsaði' 'með mér' 'að' 'ég' 'ætti' 'nógu' 'erfitt' 'með' 'að' 'fá' 'leikarahutverk' ',' 'svo' 'ég' 'bjó' 'til' 'Martin' 'Sheen' '.'] | F98: IC | G98: leikarahutverk enn óbreytt í leiðréttri setningu [SRF: Það truflar mig ekki en til hvers er verið að bæta við "með mér" þarna?] | H98: IC | I98: IC
A99: 37453 | B99: ['Þetta' 'var' 'þriðja' 'uppfærsla' 'Pólýfónkórsins' 'á' 'H-moll' 'messunni' ',' 'þær' 'fyrri' 'voru' '1968' 'og' '1976' '.'] | C99: [array([], dtype=object) array([], dtype=object) array([], dtype=object) array([], dtype=object) array([], dtype=object) array([], dtype=object) array([], dtype=object) array([], dtype=object) array([], dtype=object) array([], dtype=object) array([], dtype=object) array([], dtype=object) array([], dtype=object) array([], dtype=object) array([], dtype=object) array([], dtype=object)] | D99: False | E99: ['Þetta' 'var' 'þriðja' 'uppfærsla' 'Pólýfónkórsins' 'á' 'H-moll' 'messunni' ',' 'þær' 'fyrri' 'voru' '1968' 'og' '1976' '.'] | F99: OK | H99: OK | I99: OK
A100: 27375 | B100: ['Hvernig' 'má' 'það' 'vera' 'að' 'umræða' 'um' 'rándýran' 'hjólastíg' 'yfir' 'Arnanesið' 'sé' 'yfirleitt' 'í' 'umræðunni' ',' 'til' 'að' 'hlífa' 'íbúum' 'á' 'Arnarnesi' 'við' 'hjólreiðamönnum' 'og' 'ónæði' 'sem' 'þeim' 'fylgir' ',' 'þegar' 'bæjaryfirvöld' 'sjá' 'sér' 'ekki' 'fært' 'að' 'leysa' 'bráðan' 'vanda' 'sem' 'nemur' '3' 'miljónum' '?'] | C100: [array([], dtype=object) array([], dtype=object) array([], dtype=object) array([], dtype=object) array([], dtype=object) array([], dtype=object) array([], dtype=object) array([], dtype=object) array([], dtype=object) array([], dtype=object) array([], dtype=object) array([], dtype=object) array([], dtype=object) array([], dtype=object) array([], dtype=object) array([], dtype=object) array([], dtype=object) array([], dtype=object) array([], dtype=object) array([], dtype=object) array([], dtype=object) array([], dtype=object) array([], dtype=object) array([], dtype=object) array([], dtype=object) array([], dtype=object) array([], dtype=object) array([], dtype=object) array([], dtype=object) array([], dtype=object) array([], dtype=object) array([], dtype=object) array([], dtype=object) array([], dtype=object) array([], dtype=object) array([], dtype=object) array([], dtype=object) array([], dtype=object) array([], dtype=object) array([], dtype=object) array([], dtype=object) array([], dtype=object) array([], dtype=object) array(['orthography'], dtype=object) array([], dtype=object)] | D100: True | E100: ['Hvernig' 'má' 'það' 'vera' 'að' 'umræða' 'um' 'rándýran' 'hjólastíg' 'yfir' 'Arnanesið' 'sé' 'yfirleitt' 'í' 'umræðunni' ',' 'til' 'að' 'hlífa' 'íbúum' 'á' 'Arnarnesi' 'við' 'hjólreiðamönnum' 'og' 'ónæði' 'sem' 'þeim' 'fylgir' ',' 'þegar' 'bæjaryfirvöld' 'sjá' 'sér' 'ekki' 'fært' 'að' 'leysa' 'bráðan' 'vanda' 'sem' 'nemur' '3' 'milljónum' '?'] | F100: IC | G100: Arnanesið er enn óbreytt í leiðréttri setningu | H100: IC | I100: IC
...

Sheet nqii_random_sample
A1: id | B1: title | C1: context | D1: question | E1: answers | F1: rater_1 | G1: rater_2 | H1: rater_3
A2: nqii_12435 | B2: Þorvaldur Thoroddsen | C2: Þorvaldur Thoroddsen ( 6. júní 1855 – 28. september 1921 ) var íslenskur jarðfræðingur og landfræðingur , einhver þekktasti vísindamaður Íslendinga á sinni tíð . Hann er hvað þekktastur fyrir " Lýsingu Íslands " . | D2: Hvað er Þorvaldur Thoroddsen þekktur fyrir ? | E2: {'text': array([' Hann er hvað þekktastur fyrir " Lýsingu Íslands "'], dtype=object), 'answer_start': array([161])} | F2: OK | G2: OK | H2: OK
A3: nqii_8632 | B3: Hákarl | C3: Hákarl hefur hvassar tennur í skoltum sínum í víðum kjafti . Augu og tálknop hákarls eru smá . Hákarlinn getur náð allt að 7 metra lengd en þó er algeng lengd hans um 2 - 5 metrar . Hákarlar lifa á blönduðu fæði . Lítið er vitað um kynæxlun hákarla en þó er vitað til þess að þeir gjóti ungviði sínu sem er u.þ.b. 40 cm. við got og afkvæmin geta verið allt að 10 talsins . Talið er að hann geti náð allt að 150 ára aldri og verði mjög seint kynþroska . Hákarlinn vex mjög hægt og hafa einhverjar rannsóknir leitt í ljós að fullorðin dýr vaxi ekki nema um 1 cm. á ári . Vitað er um tilfelli þess að hákarl sem merktur hafði verið og náð aftur eftir 16 ár , hafði vaxið frá 262 cm. til 270 cm. á þessum 16 árum . Allt sitt líf dvelur skepnan í köldum heimskautasjó ( 2 - 7°C ) á miklu dýpi , hann er eina tegund hákarla í heiminum sem vitað er um að það geri . Á sumrin heldur hákarlinn sig á 180 - 730 metra dýpi en færir sig nær yfirborðinu á veturna í þeirri von að ná sér í seli . Hákarlinn finnst allt frá Svalbarða , Bjarnareyju og Hvítahafi í norðri , og suður með ströndum Noregs inn í Norðursjó . Hann er einnig að finna við norðanverðar Bretlandseyjar , Færeyjar og Ísland . | D3: Hvað borðar hákarl ? | E3: {'text': array([' Hákarlar lifa á blönduðu fæði'], dtype=object), 'answer_start': array([181])} | F3: OK | G3: OK | H3: OK
A4: nqii_5440 | B4: Stapi | C4: Stapi eða móbergsstapi er sérstök gerð eldfjalla sem myndast í eldgosi undir jökli eða íshellu . Gosefnin hlaðast upp í því rými sem bráðnar undan hita gossins . Fyrst um sinn hleðst upp gjóska og bólstraberg en þegar gosið hefur hlaðið sig upp fyrir mörk jökulsins og gosrásin einangrast frá vatninu hefst hraungos . Þegar jökullinn hverfur stendur eftir reisulegt kringlótt fjall með bröttum hamrabrúnum og lítilli dyngju á annars flötum toppi . | D4: Hvað er móbergsstapi ? | E4: {'text': array([' gerð eldfjalla sem myndast í eldgosi undir jökli', ' sérstök gerð eldfjalla sem myndast í eldgosi undir jökli eða íshellu', 'Stapi eða móbergsstapi er sérstök gerð eldfjalla sem myndast í eldgosi undir jökli eða íshellu'], dtype=object), 'answer_start': array([33, 25, 0])} | F4: OK | G4: OK | H4: OK
A5: nqii_5884 | B5: Skipting ríkisvaldsins | C5: Í forsetaþingræði er forsetinn og löggjafarþingið kosið á aðgreindan hátt rétt eins og í forsetaræðisríkjum en forsetinn hefur vald til að leysa upp þing . Í forsetaþingræði má forsetinn ráða ríkisstjórn eins og í forsetaræðisríkjum en verður að fá samþykki þingsins , eins og í þingræðisríkjum . Það skiptir því miklu máli hvaða flokkur / ar ráða forsetaembættinu og löggjafarþinginu hverju sinni . Forsetaþingræði er þannig blönduð stjórnskipun sem hefur í för með sér að forysta framkvæmdarvaldsins er tvískipt , forsetinn fer með hluta framkvæmdarvaldsins en forsætisráðherrann og ríkisstjórn líka ( forsetinn skipar forsætisráðherrann ) . Mismunandi útfærslur af þessari tvískiptingu má finna meðal ríkja sem notast við þessa stjórnskipan . | D5: Hverjir fara með framkvæmdavald á Íslandi ? | E5: {'text': array(['forsetinn fer með hluta framkvæmdarvaldsins en forsætisráðherrann og ríkisstjórn líka'], dtype=object), 'answer_start': array([516])} | F5: OK | G5: OK | H5: OK
A6: nqii_8969 | B6: MDMA | C6: MDMA ( 3,4 - metýlendíoxýmetamfetamín ) , best þekkt undir nöfnunum alsæla , Molly eða e-pilla , er tilbúið fenetýlamín sem orkar á heilann á þann hátt að ýta snögglega undir framleiðslu á serótóníni , norepinefrín og dópamín , og einnig sem endurupptökuhemill , Það veldur skynjunaráhrifum hjá neytandanum , til dæmis einlægni , sæluvímu og góðri tilfinningu . Sumir neytendur finna fyrir meiri snertiáhrifum sem að gerir snertingu almennt ánægjulegri . Þrátt fyrir almennar sögusagnir um annað , hefur lyfið ekki almenn kynorkuaukandi áhrif . Sökum hæfni lyfsins til að hjálpa við að draga úr hræðslu við sjálfskoðun hefur það reynst nytsamlegt í ýmisskonar meðferðartilgangi , þá sérstaklega áfallaröskun , en er ekki viðurkennt sem lyf . | D6: Hver eru áhrif MDMA ? | E6: {'text': array([' Það veldur skynjunaráhrifum hjá neytandanum , til dæmis einlægni , sæluvímu og góðri tilfinningu'], dtype=object), 'answer_start': array([262])} | F6: OK | G6: OK | H6: OK
A7: nqii_17645 | B7: Nifteindastjörnur | C7: Nifteindastjörnur eru undraverðar stjörnur sem eru að stærstum hluta úr nifteindum . Þær verða til þegar gríðarstórar stjörnur springa og falla saman í miðju . Úr þessari miðju verða nifteindastjörnurnar til . Talið er að finna megi 100.000 nifteindastjörnur í Vetrarbrautinni okkar en nú til dags eru um 2.000 þekktar nifteindastjörnur í Vetrarbrautinni og Magellanskýjunum og um 1.000 þekktar tifstjörnur sem eru nifteindastjörnur með útgeislunarstraum sem lendir á jörðinni . Þessar stjörnur hafa bæði gríðarsterkt segulsvið , snúast mjög hratt og eru einstaklega heitar . Þær eru gríðarlega eðlisþungar að auki vegna þess hve þétt efnið í þeim er en engir fráhrindikraftar verka milli nifteinda . | D7: Hvað er tifstjarna ? | E7: {'text': array([' nifteindastjörnur', ' nifteindastjörnur með útgeislunarstraum sem lendir á jörðinni'], dtype=object), 'answer_start': array([414, 414])} | F7: OK | G7: OK | H7: OK
A8: nqii_11247 | B8: Svartbók kommúnismans | C8: Svartbók kommúnismans er bók , sem fjallar um glæpi kommúnistastjórna á 20. öld . Höfundar eru nokkrir franskir fræðimenn . Stéphane Courtois var ritstjóri og skrifar formála hennar , eftirmála og tvo kafla . Nicolas Werth skrifar lengstu greinina , sem er um ógnarstjórn Leníns og Stalíns í Rússlandi og síðar Ráðstjórnarríkjunum 1917 – 1953 . Jean-Louis Margolin skrifar tvær langar ritgerðir , um Kína í valdatíð Maós 1949 – 1976 og Kambódíu undir stjórn rauðu kmeranna 1975 – 1979 . Bókin kom fyrst út í Frakklandi haustið 1997 undir heitinu " Le livre noir du communisme : Crimes , terreur , répression " . Dr. Hannes Hólmsteinn Gissurarson prófessor þýddi bókina á íslensku og var ritstjóri hennar . | D8: Hvert er helsta framlag Hannesar Hólmsteins til fræðanna ? | E8: {'text': array([' Dr. Hannes Hólmsteinn Gissurarson prófessor þýddi bókina á íslensku og var ritstjóri hennar .'], dtype=object), 'answer_start': array([611])} | F8: IC | G8: IC | H8: IC
A9: nqii_16355 | B9: Konungur Svíþjóðar | C9: Konungur Svíþjóðar er þjóðhöfðingi Svíþjóðar , þar sem er þingbundin konungsstjórn . Sænska konungsveldið er eitt af þeim elstu í heimi en listar yfir konunga Svíþjóðar hefjast venjulega á Eiríki sigursæla ( d. 995 ) . | D9: Hver er þjóðhöfðingi Svíþjóðar ? | E9: {'text': array(['Konungur Svíþjóðar er þjóðhöfðingi Svíþjóðar'], dtype=object), 'answer_start': array([0])} | F9: OK | G9: OK | H9: OK
A10: nqii_14353 | B10: Gleðiganga | C10: Á Íslandi hefur hún verið gengin í Reykjavík annan laugardag í ágústmánuði frá árinu 2000 sem hluti af Hinsegin dögum sem haldnir eru á sama tíma . | D10: Hvenær er gleðigangan ? | E10: {'text': array(['Á Íslandi hefur hún verið gengin í Reykjavík annan laugardag í ágústmánuði', ' annan laugardag í ágústmánuði'], dtype=object), 'answer_start': array([ 0, 44])} | F10: F | G10: OK | H10: F
A11: nqii_1098 | B11: Júlíus Caesar | C11: Árið 46 f.Kr. hafði Cæsar náð öllu Rómveldi á sitt vald og lét hann öldungaráði gefa sér alræðisvald til 10 ára . Tveimur árum síðar tók hann sér alræðisvald til æviloka sem urðu í mars sama ár . Cæsar var snjall stjórnmálamaður og kom á ýmsum umbótum í stjórnkerfinu . Hann fjölgaði í öldungaráðinu upp í 900 og tilnefndi nýja öldunga sem voru honum hliðhollir úr ýmsum þjófélagshópum og úr ýmsum skattlöndum . Hann lækkaði skatta í skattlöndum , skipti löndum milli hermanna sinna og fátækra . Hann reyndi að stemma stigu við þrælahaldi með lögum . Hann sendi tugi þúsunda fátækra borgara í Róm , sem landnema til nýlendna sinna . Hinum fátæklingunum veitti hann vinnu við byggingaframkvæmdir . Hann tók upp tímatal með egypsku sniði sem var nefnt , júlíanska tímatalið og er dagatalið þar með fellt að gangi sólarinnar í stað tunglsins . 365 dagar eru í árinu og hlaupársdagur fjórða hvert ár . Hann tryggði gengi gjaldmiðils með því að slá mynt úr gulli og setti reglur um vexti og gjaldþrot . Hann kom á skipulagi og stjórn í Rómaveldi . | D11: Hvenær var Júlíus Sesar keisari ? | E11: {'text': array([' 46 f.Kr.'], dtype=object), 'answer_start': array([4])} | F11: IC | G11: IC | H11: IC
A12: nqii_10167 | B12: Sen | C12: Sen ( eða zen ) er form af búddisma , sem leggur megináherslu á hugleiðslu umfram dýrkun guðdóms , helgirita og regluverks . Í raun er það andstætt sen ( zen ) að það sé skilgreint , því hugmyndafræðin gengur út á að ekkert er í föstu formi . Allt er háð breytingum og það sem við höldum að sé veruleikinn er í raun okkar eigin túlkun samkvæmt hugmyndum zen . Sen varð til í Kína á 7. öld en breiddist þaðan til Víetnam , Kóreu og Japans . Japanski rithátturinn er " zen " en sá kínverski er " chan " ( 禪 ) en kínverska orðið er komið af orðinu dhyāna í sanskrít , sem merkir „ hugleiðsla “ . | D12: Hvað er Zen ? | E12: {'text': array([' form af búddisma', ' form af búddisma , sem leggur megináherslu á hugleiðslu umfram dýrkun guðdóms , helgirita og regluverks'], dtype=object), 'answer_start': array([18, 18])} | F12: OK | G12: OK | H12: OK
... A75: nqii_8860 | B75: Finnland | C75: Lífslíkur kvenna eru 82 ár og karla 75 ár . | D75: Hverjar eru lífslíkur karla í Finnlandi ? | E75: {'text': array([' 75 ár'], dtype=object), 'answer_start': array([35])} | F75: F | G75: F | H75: F
A76: nqii_6286 | B76: Hekla | C76: Hekla hefur gosið árið 1104 , 1158 , 1206 , 1222 , 1300 , 1341 , 1389 , 1510 , 1597 , 1636 , 1693 , 1766 , 1845 , 1947 , 1970 , 1980 , 1991 og 2000 . | D76: Hvenær gaus Hekla síðast ? | E76: {'text': array([' 2000'], dtype=object), 'answer_start': array([142])} | F76: OK | G76: OK | H76: F | I76: (svona spurningar eldast ekki vel og svarið getur breyst hvenær sem er)
A77: nqii_17075 | B77: Lego | C77: Lego er danskur leikfangaframleiðandi í eigu fjölskyldu , með höfuðstöðvar í Billund . Upprunalega framleiddi fyrirtækið hágæðaleikföng úr tré en síðustu fjörutíu ár hefur það framleitt plastkubba . Fyrirtækið var stofnað árið 1932 . | D77: Í hvaða landi var Legó stofnað ? | E77: {'text': array([' danskur', 'Lego er danskur leikfangaframleiðandi'], dtype=object), 'answer_start': array([7, 0])} | F77: OK | G77: F | H77: F
A78: nqii_6542 | B78: Ágústus | C78: Octavíanus var erfingi Júlíusar Cæsars , sem var ömmubróðir hans . Eftir morðið á Cæsari gekk Octavíanus í bandalag með Marcusi Antoniusi og Marcusi Lepidusi . Þegar slitnaði upp úr bandalaginu kom til átaka milli Marcusar Antoniusar og Octavíanusar , sem hafði betur . Í kjölfarið komst Octavíanus til valda í Róm . Hann viðhélt hefðum rómverska lýðveldisins að forminu til en var í reynd sjálfráður einvaldur í yfir 40 ár . Valdatími hans myndar skiptinguna á milli lýðveldistímans og keisaratímans í Róm en keisaratíminn er venjulega talinn hefjast árið 27 f.Kr. Hann batt enda á borgarastríð sem áður hafði geisað og leiddi Róm inn í nýjan tíma hagsælda og friðar , " Pax Romana " eða " Rómarfriðarins " . Hann var giftur Liviu Drusillu í 51 ár . | D78: Hvaða ár varð Ágústus keisari ? | E78: {'text': array([' 27 f.Kr', ' 27 f.Kr.', ' keisaratíminn er venjulega talinn hefjast árið 27 f.Kr.'], dtype=object), 'answer_start': array([556, 556, 509])} | F78: F | G78: IC | H78: F
A79: nqii_16536 | B79: Enheduanna | C79: Enheduanna var hofgyðja í Úr í Súmer sem var uppi um 2300 f.Kr. Enheduanna var dóttir Sargonar fyrsta keisara í Súmer . Sargon var frá Akkadíu en réðst inn í Súmer og sameinaði ríkin og myndaði þannig fyrsta keisararíki sem sögur fara af . Varðveist hafa þrjú ljóð Enheduönnu en þau eru ákall til gyðjunnar Inönnu sem og safn trúarlegra sálma . | D79: Hvað skrifaði Enheduanna ? | E79: {'text': array([' Varðveist hafa þrjú ljóð Enheduönnu'], dtype=object), 'answer_start': array([239])} | F79: F | G79: F | H79: F
A80: nqii_8192 | B80: Finnska | C80: Finnska virðist eiga rætur að rekja langt aftur til fortíðar . Sú finnska , sem töluð er af innfæddum í dag , er hinsvegar nokkuð nýleg smíð en ritmálið var búið til á 16. öld . Nútímafinnska kom til sögunnar á 19. öld og er sprottin af sterkri hreyfingu þjóðernissinna . Þegar Finnland varð sjálfstætt ríki árið 1917 varð Finnland að ríki þar sem töluð eru tvö tungumál , finnska og sænska . Þessi tvö tungumál teljast nú bæði opinber tungumál Finnlands þrátt fyrir að finnska sé ríkjandi en um 290.000 hafa sænsku að móðurmáli í landinu . | D80: Í hvaða landi er sænska töluð ? | E80: {'text': array([' Finnland að ríki þar sem töluð eru tvö tungumál , finnska og sænska'], dtype=object), 'answer_start': array([322])} | F80: IC | G80: F | H80: IC
A81: nqii_16471 | B81: Holland | C81: Konungsríkið Holland ( hollenska : " Koninkrijk der Nederlanden " ) er vesturevrópskt land staðsett við Norðursjó . Það er 41.548 km² að stærð og er stór hluti landsins er neðan sjávarmáls . Landið var efnahagslegt stórveldi frá 16. öld til 18. aldar . Holland er í Evrópusambandinu . Höfuðborgin er Amsterdam , þó svo að stjórnsýsla landsins sé í Haag . | D81: Hver er höfuðborg Hollands ? | E81: {'text': array([' Höfuðborgin er Amsterdam , þó svo að stjórnsýsla landsins sé í Haag', ' Höfuðborgin er Amsterdam', ' Amsterdam'], dtype=object), 'answer_start': array([284, 284, 299])} | F81: OK | G81: OK | H81: OK
A82: nqii_7961 | B82: Inkaveldið | C82: Inkaveldið var keisaraveldi indíána í Andesfjöllum , þar sem nú er Perú , og stofnað af Manco Capac . Veldi Inka stóð frá tólftu öld og fram á þá sextándu . Íbúar keisaraveldisins kölluðu land sitt Tawantinsuyu ( sem þýðir „ land fjórðunganna “ ) , og var það orðið meira en milljón ferkílómetrar að stærð á 15. öld og þá bjuggu þar meira en tíu milljónir íbúa . Veldinu var skipt í fernt ; Chinchaysuyu ( NV ) , Antisuyu ( NA ) , Qontisuyu ( SV ) , og Qollasuyu ( SA ) , en í miðjunni var höfuðborgin Cusco , þaðan sem veldinu var stjórnað . Til að tengja saman landið byggðu þeir vegi og brýr , en Inkar áttu afbragðs verkfræðinga . Um vegina fóru hraðboðar sem ferðuðust allt að 250 km á dag með skilaboð . Þannig gat inkinn , sem var æðsti leiðtoginn og jafnframt dýrkaður sem guð , komið mikilvægum boðum sínum til íbúanna og þannig hjálpuðu hraðboðarnir við stjórnun landsins . Inkar notuðu mjög öflugan her til þess að ná undir sig landi og sigra óvini sína og inkinn hafði jafnframt óskorað vald til þess að gera hvað sem hann vildi . < / onlyinclude > | D82: Hver var Manco Capac ? | E82: {'text': array(['Inkaveldið var keisaraveldi indíána í Andesfjöllum , þar sem nú er Perú , og stofnað af Manco Capac'], dtype=object), 'answer_start': array([0])} | F82: F | G82: IC | H82: F
A83: nqii_1889 | B83: Fellibylur | C83: Fellibylur ( fellistormur eða felliveður ) er sérlega kröpp lægð sem myndast í hitabeltinu og fær kraft sinn úr uppstreymi lofts í kringum stormaugað . Mikið af raka þéttist í uppstreyminu og skilar við það varmaorku sem nýtist við að knýja vindinn . Í öðrum heimshlutum eru ýmis orð notuð um fellibyl . Til dæmis nefnast fellibyljir austurlanda fjær " týfónar " . Fellibyljir valda oft mjög miklu tjóni . | D83: Af hverju myndast fellibylir ekki í tempruðum beltum ? | E83: {'text': array([' Mikið af raka þéttist í uppstreyminu og skilar við það varmaorku sem nýtist við að knýja vindinn'], dtype=object), 'answer_start': array([151])} | F83: IC | G83: IC | H83: IC
A84: nqii_4410 | B84: John Forbes Nash | C84: John Forbes Nash ( fæddur 13. júní 1928 ; d. 23. mai 2015 ) var stærðfræðingur sem fékkst við leikjafræði og diffurrúmfræði . Hann deildi nóbelsverðlaununum í hagfræði árið 1994 með tveimur öðrum leikjafræðingum , Reinhard Selten og John Harsanyi . | D84: Hvað er John Nash þekktur fyrir ? | E84: {'text': array([' leikjafræði'], dtype=object), 'answer_start': array([93])} | F84: F | G84: F | H84: F
A85: nqii_30 | B85: Hannes Hafstein | C85: Hannes Þórður Hafstein ( f. 4. desember 1861 , d. 13. desember 1922 ) var íslenskt skáld , sýslumaður og fyrsti ráðherra Íslands . | D85: Hver var Hannes Hafsteins ? | E85: {'text': array([' íslenskt skáld , sýslumaður og fyrsti ráðherra Íslands', ' íslenskt skáld , sýslumaður og fyrsti ráðherra Íslands', 'Hannes Þórður Hafstein ( f. 4. desember 1861 , d. 13. desember 1922 ) var íslenskt skáld , sýslumaður og fyrsti ráðherra Íslands'], dtype=object), 'answer_start': array([73, 73, 0])} | F85: F | G85: OK | H85: OK
A86: nqii_1784 | B86: Heimspeki | C86: Epikúrisminn var heimspeki Epikúrosar en Epikúros var undir miklum áhrifum frá Demókrítosi . Epikúros hélt fram rammri efnishyggju og varði eindahyggjuna ( atómismann ) sem Levkippos og Demókrítos höfðu fyrstir sett fram . Hann hélt því einnig fram að ánægjan væri hin æðstu gæði en Epikúros taldi að andleg ánægja væri æðri líkamlegri ánægju og að í öllu skyldi gæta hófs . | D86: Hvaða áhrif hafði epikúrismi á gríska heimspeki ? | E86: {'text': array([' Epikúros taldi að andleg ánægja væri æðri líkamlegri ánægju og að í öllu skyldi gæta hófs .'], dtype=object), 'answer_start': array([282])} | F86: IC | G86: IC | H86: OK
A87: nqii_16861 | B87: Hong Kong | C87: Hong Kong ( kínverska : 香港 ) , opinberlega Sérstjórnarhérað Alþýðulýðveldisins Kína Hong Kong , er sérstakt sjálfstjórnarhérað í Kínverska alþýðulýðveldinu , á austurbakka árósa Perluár í suðurhluta Kína . Hong Kong er einn af þéttbýlustu stöðum heims , með 7,4 milljón íbúa af margvíslegum uppruna á 1.104 ferkílómetra svæði . | D87: Hvað búa margir í Hong Kong ? | E87: {'text': array([' 7,4 milljón', ' 7,4 milljón', ' Hong Kong er einn af þéttbýlustu stöðum heims , með 7,4 milljón íbúa'], dtype=object), 'answer_start': array([257, 257, 205])} | F87: OK | G87: OK | H87: OK
A88: nqii_10608 | B88: Sorp | C88: Sorp ( einnig þekkt sem rusl , skran eða drasl ) er óæskilegt eða ónytsamlegt efni . Í lífverum kallast ónytsamleg efni eða eiturefni sem þær gefa frá sér " úrgangur " . | D88: Hvaða efni eru eiturefni ? | E88: {'text': array([' Í lífverum kallast ónytsamleg efni eða eiturefni sem þær gefa frá sér " úrgangur'], dtype=object), 'answer_start': array([84])} | F88: IC | G88: IC | H88: IC
... A150: nqii_3787 | B150: Margaret Thatcher | C150: Margrét Thatcher ( eða að fullu Margaret Hilda Thatcher , Baroness Thatcher of Kesteven ; 13. október 1925 – 8. apríl 2013 ) var forsætisráðherra Bretlands á árunum 1979 - 1990 og leiðtogi breska Íhaldsflokksins 1975 - 1990 . Hún varð fyrst kvenna til að gegna þessum tveimur stöðum og sat einnig lengst allra samfellt sem forsætisráðherra Bretlands á 20. öld . Hún var í senn einhver dáðasti og hataðasti stjórnmálamaður lands síns . Thatcher lagði ríka áherslu á að draga úr hvers kyns ríkisafskiptum , sem og á frjálsan markað og frjálst framtak . Áhrifa Thatchers gætir enn innan Breska íhaldsflokksins . | D150: Hvað var Margét Thatcher lengi forsætisráðherra Bretlands ? | E150: {'text': array([' var forsætisráðherra Bretlands á árunum 1979 - 1990'], dtype=object), 'answer_start': array([124])} | F150: OK | G150: OK | H150: F
A151: nqii_1391 | B151: Vesturfarar | C151: Vesturfarar voru Íslendingar sem héldu til Brasilíu , Kanada og Bandaríkjanna á ofanverðri 19. öld og stóðu fólksflutningarnir allt fram að fyrri heimstyrjöld eða frá 1870 til 1914 . Mestir voru þeir þó á seinni hluta 19. aldar . Ástæður fólksflutninganna voru margvíslegar , oftast voru þær fjárhagslegar , veðurfarslegar og tengdust skort á landrými ( eða vistarbandinu ) , óánægja með gang sjálfstæðisbaráttunnar og stundum einnig ævintýraþrá . Talið er að um 15 þúsund Íslendingar eða 20% þjóðarinnar hafi farið vestur og ekki snúið aftur . | D151: Hvenær hófst fólksflutningur til Kanada ? | E151: {'text': array([' 1870', ' 1870', ' 1870'], dtype=object), 'answer_start': array([166, 166, 166])} | F151: OK | G151: OK | H151: IC | I151: Svarið er vitlaust, enda ekki talað sérstaklega um Kanada í textanum. Vesturferðir til Kanada hófust 1872.
A152: nqii_4205 | B152: Fyrri heimsstyrjöldin | C152: Fyrri heimsstyrjöldin ( sem nefnt var heimsstríðið fyrir seinni heimsstyrjöldina ) var mannskætt stríð sem geysaði í Evrópu í fjögur ár . Stríðið hefur verið nefnt „ stríðið mikla “ og „ stríðið sem enda átti öll stríð “ . Sá atburður sem miðað er við að marki upphaf stríðsins var morðið á Frans Ferdinand erkihertoga og ríkisarfa Austurríkis í Sarajevó þann 28. júní 1914 . Átök hófust í ágúst 1914 og breiddust hratt út . Þegar upp var staðið lágu um tíu milljónir manna í valnum , um tuttugu milljónir höfðu særst og ótal manns misst heimili sín og lifibrauð . Stríðinu lauk með uppgjöf Þjóðverja 11. nóvember 1918 . Að stríðinu loknu funduðu fyrrum fjandmenn í Versölum í Frakklandi þar sem Versalasamningurinn var gerður . | D152: Hvaða ár hófst fyrri heimsstyrjöldin ? | E152: {'text': array([' 1914', ' 28. júní 1914'], dtype=object), 'answer_start': array([368, 359])} | F152: OK | G152: OK | H152: OK
A153: nqii_17147 | B153: Hippókratesareiðurinn | C153: " Ég sem rita nafn mitt hér undir , lofa því og legg við drengskap minn að beita kunnáttu minni með fullri alúð og samviskusemi að láta mér ávallt annt um sjúklinga mína án manngreinarálits að gera mér far um að auka kunnáttu mína í læknafræðum að kynna mér og halda vandlega öll lög og fyrirmæli er lúta að störfum lækna " | D153: Hver er Hippokratesareiðurinn ? | E153: {'text': array(['" Ég sem rita nafn mitt hér undir , lofa því og legg við drengskap minn að beita kunnáttu minni'], dtype=object), 'answer_start': array([0])} | F153: IC | G153: F | H153: F
A154: nqii_13698 | B154: Kóreupopp | C154: BoA eða Kwon Bo-Ah , er einn þekktasti tónlistarmaður stefnunnar í dag . Hún hóf feril sinn árið 2000 eftir að SM Entertainment uppgötvaði hana . Það sem gerir BoA svona einstaka er að hún er fyrsta stjarnan sem risafyrirtæki tók að sér og gerði fræga víðsvegar um heiminn . Segja mætti að BoA sé ástæðan fyrir því að kóreupopp sé þekkt út fyrir Suður Kóreu . Þessi söngkona gerði garðinn frægann með albúminu sínu " Don’t Start Now " , en þar syngur hún bæði á japönsku og kóresku . Með þessu tókst henni að komast á topp vinsældalistans í báðum löndum samtímis , og setti jafnframt sölumet í Kóreu . | D154: Hver er frægasta K-pop stjarna Suður-Kóreu ? | E154: {'text': array(['BoA eða Kwon Bo-Ah'], dtype=object), 'answer_start': array([0])} | F154: OK | G154: OK | H154: OK
A155: nqii_2331 | B155: Tjörnin | C155: Tjörnin er dæmi um sjávarlón þar sem sandur og möl hefur myndað malarrif sem lokar smám saman af lónið . Gamli miðbærinn í Reykjavík stendur á rifinu . Rifið var ekki fullmyndað fyrr en fyrir um það bil 1200 árum og þá hófst lífræn setmyndun í Tjörninni en undir þeim setlögum eru sand - og malarlög . Þegar lífræn efni tóku að safnast saman á botni Tjarnarinnar gætti lítilla seltuáhrifa og grunnvatn hefur streymt þangað frá Vatnsmýrinni og holtunum í kring . Tjarnarbakkarnir voru grónir gulstör ( carex lyngbyei ) og öðrum tegundum af hálfgrasaætt en svo komu tímabil þegar seltan verður meiri þá hörfuðu háplöntur . Um 1900 mun engum fugli hafa verið vært á Tjörninni , allir fuglar voru drepnir . Andaveiðar voru eitthvað stundaðar á Tjörninni allt fram á annan áratug síðustu aldar . Með lögreglusamþykkt frá 19. apríl 1919 var bannað að skjóta í borgarlandinu . Um sama leyti var sett siglingabann en áður höfðu margir átt báta og vegna umferðar þreifst ekkert kríuvarp í Tjarnarhólmanum fyrir 1919 . Með skotveiðibanninu og siglingabanninu fjölgaði mikið stokköndum og kríum . Tveir hólmar eru í Tjörninni . Annar þeirra er í suðurenda tjarnarinnar , en hinn , sem er í norðurhlutanum , og mest ber á frá miðborginni séð , gengur venjulega undir nafninu " Tjarnarhólminn " . Í Tjarnarhólmanum hefur löngum verið varp , en um miðja 19. öld var hólminn notaður sem miðpunktur í hringekju sem svo var kölluð . Segir svo frá henni í Lesbók Morgunblaðsins 1933 : | D155: Hvenær varð Tjörn Reykjavíkur til ? | E155: {'text': array([' fyrir um það bil 1200 árum', ' fyrir um það bil 1200 árum'], dtype=object), 'answer_start': array([185, 185])} | F155: IC | G155: IC | H155: OK
A156: nqii_2695 | B156: Sovétríkin | C156: Sovétríkin eða Советский Союз á rússnesku ( einnig kallað Ráðstjórnarríkin eða " Союз Советских Социалистических Республик ( СССР ) " á rússnesku , umritað " Sojúz Sovétskikh Socialistíčeskikh Respúblik ( SSSR ) " , í íslenskri þýðingu " Sambandsríki sósíalískra sovíetlýðvelda " ) var sambandsríki með sósíaslíska stjórnarskrá í Austur-Evrópu og Asíu sem sett var á laggirnar árið 1922 og leystist upp 1991 . | D156: Hvenær urðu Sovétríkin til ? | E156: {'text': array([' 1922'], dtype=object), 'answer_start': array([381])} | F156: OK | G156: OK | H156: OK
A157: nqii_9334 | B157: Napóleon Bónaparte | C157: Napóleon Bónaparte ( franska Napoléon Bonaparte ) eða Napóleon I ( 15. ágúst 1769 – 5. maí 1821 ) , nefndur hinn mikli , var herforingi í frönsku byltingunni og þjóðarleiðtogi Frakklands , fyrst sem aðalræðismaður franska lýðveldisins frá 1799 til 1804 og síðan sem Frakkakeisari og konungur Ítalíu til ársins 1814 . Hann var giftur tvisvar og átti soninn Napóleon II með seinni konu sinni . Napóleon lagði mestalla Evrópu undir Frakka í Napóleonsstyrjöldunum en var að endingu sigraður og sendur í útlegð til eyjarinnar Elbu árið 1814 . Hann slapp þaðan og réði aftur yfir Frakklandi um stutt skeið árið 1815 þar til hann tapaði í orrustunni við Waterloo . Hann lést árið 1821 í útlegð á bresku eyjunni Sankti Helenu . Ýmist er talið að hann hafi framið sjálfsmorð eða , eins og sumir vilja meina , að eitrað hafi verið fyrir honum . Opinber skýring var að hann hafi dáið úr magakrabbameini . | D157: Hvers vegna var Napóleon sendur í útlegð ? | E157: {'text': array([' Napóleon lagði mestalla Evrópu undir Frakka í Napóleonsstyrjöldunum en var að endingu sigraður og sendur í útlegð'], dtype=object), 'answer_start': array([391])} | F157: IC | G157: IC | H157: F
A158: nqii_17202 | B158: Júlíus Caesar | C158: Gaius Julius Caesar ( latína : CAIVS IVLIVS CAESAR ) eða Júlíus Cæsar , stundum ritað Júlíus Sesar , 12. eða 13. júlí um 100 f.Kr. – 15. mars 44 f.Kr. ) var rómverskur herforingi , sagnaritari , stjórnmálamaður og síðar einvaldur í Róm . | D158: Hvenær fæddist Caesar ? | E158: {'text': array([' 12. eða 13. júlí um 100 f.Kr.', ' 12. eða 13. júlí um 100 f.Kr.', ' 12. eða 13. júlí um 100 f.Kr'], dtype=object), 'answer_start': array([100, 100, 100])} | F158: OK | G158: OK | H158: OK
A159: nqii_5730 | B159: Rúnir | C159: Einungis hafa tæplega hundrað rúnaristur fundist á Íslandi og eru þær elstu frá 10. eða 11. öld og þær yngstu frá síðari hluta 19. aldar . Um 50 af þessum ristum eru á rúnalegsteinum flestar sennilega frá 15. og 16. öld . Þegar á líður 17. öldina er notkun á rúnum almennt hætt en þær voru í nokkrum mæli notaðar til skrauts í útskurði allt til loka 19. aldar . | D159: Hver eru fyrstu ummerki um rúnir á Íslandi ? | E159: {'text': array(['Einungis hafa tæplega hundrað rúnaristur fundist á Íslandi og eru þær elstu frá 10. eða 11. öld'], dtype=object), 'answer_start': array([0])} | F159: OK | G159: OK | H159: OK
A160: nqii_8815 | B160: Tókýó | C160: Í borginni eru óvenju fáir skýjakljúfar miðað við aðrar stórborgir en það útskýrist að mestu leyti af byggingareglum vegna jarðskjálfta . Hús eru yfirleitt ekki hærri en 12 hæðir en Tókýó Midtown er stærsti skýjakljúfur borgarinnar , 248 m hátt . Hæsta mannvirki borgarinnar er aftur Himnatréð ( Tokyo Skytree ) , 634 metra hátt , og slær þar með út Tókýó-turninn , en hann er ' einungis ' 333 m hár . | D160: Hversu mörg hús eru í Tókýó ? | E160: {'text': array([' Tokyo Skytree'], dtype=object), 'answer_start': array([295])} | F160: IC | G160: IC | H160: IC
A161: nqii_10658 | B161: Ingólfur Arnarson | C161: Ingólfur Arnarson ( stundum nefndur Björnólfsson ) er jafnan talinn fyrsti landnámsmaður Íslands . Hann kom fyrst til Íslands ásamt systur sinni Helgu Arnardóttur og fóstbróður sínum og mági , Hjörleifi Hróðmarssyni , til landkönnunar í kringum 867 . Þeir komu svo til að nema land á Íslandi í kringum 870 , þó hefð sé að miða við 874 . Ingólfur hafði verið gerður útlægur frá heimkynnum sínum í Dalsfirði í Firðafylki í Noregi og ákvað því að flytja til Íslands . | D161: Hvenær fann Ingólfur Arnarsson Ísland ? | E161: {'text': array([' í kringum 867'], dtype=object), 'answer_start': array([234])} | F161: F | G161: F | H161: OK
A162: nqii_5777 | B162: Grikkland hið forna | C162: Menn hafa ekki komið sér saman um nein ákveðin ártöl sem marki upphaf eða endi fornaldarmenningar Grikklands . Áður fyrr var miðað við upphaf Ólympíuleikanna árið 776 f.Kr. , en flestir nútímasagnfræðingar eru nú orðnir afhuga því . Flestir skilgreina tímabilið þannig að það nái aftur til Mýkenumenningarinnar , sem hófst um 1600 f.Kr. en leið undir lok um 1150 f.Kr. Aftur á móti telja margir að hin áhrifamikla mínóíska menning , sem blómstraði einkum á Krít ( og er einnig nefnd Krítarmenningin ) , en einnig á meginlandi Grikklands á undan Mýkenumenningunni , hafi verið svo frábrugðin grískri menningu síðari tíma að hana beri að flokka út af fyrir sig . Blómaskeiði mínóísku menningarinnar lauk á 14. öld f.Kr. , en menningin leið þó ekki endanlega undir lok fyrr en um 1200 f.Kr. , skömmu fyrir endalok Mýkenumenningarinnar . Eigi að síður er Mýkenumenningin gjarnan talin með Grikklandi hinu forna en ekki mínóísk menning . | D162: Hvenær leið menning Mýkenumanna undir lok ? | E162: {'text': array([' um 1150 f.Kr.'], dtype=object), 'answer_start': array([354])} | F162: OK | G162: OK | H162: OK
A163: nqii_9056 | B163: Sjálfstæðisflokkurinn | C163: Núverandi formaður flokksins er Bjarni Benediktsson og Þórdís Kolbrún Reykfjörð Gylfadóttir er varaformaður Áslaug Arna Sigurbjörnsdóttir ritari flokksins . Flokkurinn hefur nú 16 sæti á Alþingi eftir alþingiskosningarnar 2017 en hafði 21 þingsæti fyrir þær kosningar . Allir formenn flokksins hafa gegnt embætti forsætisráðherra á Íslandi . | D163: Hver er núverandi formaður Sjálfstæðisflokksins ? | E163: {'text': array([' Bjarni Benediktsson'], dtype=object), 'answer_start': array([31])} | F163: OK | G163: OK | H163: F | I163: (það er ekki hægt að spyrja um "núverandi" eitthvað - nema auðvitað í samhengi textans, en til hvers þá að nota alvöru nöfn?)
A164: nqii_7859 | B164: Eykt | C164: Eykt er heiti á tímalengd , sem er einn áttundi hluti sólarhringsins eða því sem næst þrjár klukkustundir hver . Eyktamörk eru þegar ein eykt endar og sú næsta byrjar . Eyktamörkin gengu undir ákveðnum heitum og voru helstu tímaviðmiðanir í daglegu tali . | D164: Hvað þýðir eykt ? | E164: {'text': array(['Eykt er heiti á tímalengd , sem er einn áttundi hluti sólarhringsins eða því sem næst þrjár klukkustundir hver'], dtype=object), 'answer_start': array([0])} | F164: OK | G164: OK | H164: OK
A165: nqii_17683 | B165: Finnland | C165: Samar eru frumbyggjar sem búa í Finnlandi , Svíþjóð , Noregi og Rússlandi . Áður fyrr voru Samar oft kallaðir Lappar , en nú til dags telja margir Samar það vera niðrandi heiti . Auk eigin tungumála hafa Samar sinn eigin lífsstíl , yfirbragð og menningu . Svipuð saga , hefðir , lifnaðarhætti og siðir sameina Sama sem búa í mismunandi löndum . Samtals eru Samar um 75.000 til 100.000 en af þeim búa minna en 7.000 í Finnlandi , sem þýðir að Samar eru einungis 0,13% af íbúum Finnlands . | D165: Hvað búa margir Samar í Finnlandi ? | E165: {'text': array([' minna en 7.000', ' 7.000 í Finnlandi'], dtype=object), 'answer_start': array([399, 408])} | F165: OK | G165: OK | H165: OK
A166: nqii_14131 | B166: Georgía | C166: Georgía ( georgíska საქართველო ; " Sakartvelo " ) er land í Kákasusfjöllum , við austurströnd Svartahafs . Georgía á landamæri að Rússlandi í norðri , Tyrklandi og Armeníu í suðri og Aserbaídsjan í austri . Georgía liggur í Austur-Evrópu og Vestur-Asíu en hefur flestöll stjórnmálaleg og menningarleg tengsl sín við Evrópu . | D166: Hvaða lönd eru með landamæri að Georgíu ? | E166: {'text': array([' Rússlandi í norðri , Tyrklandi og Armeníu í suðri og Aserbaídsjan í austri', ' Georgía á landamæri að Rússlandi í norðri , Tyrklandi og Armeníu í suðri og Aserbaídsjan í austri .', ' Rússlandi í norðri , Tyrklandi og Armeníu í suðri og Aserbaídsjan í austri'], dtype=object), 'answer_start': array([129, 106, 129])} | F166: OK | G166: OK | H166: OK
A167: nqii_2623 | B167: Grænland | C167: Íbúar Grænlands voru tæp 56.000 árið 2019 og langflestir Inuítar , upprunir þaðan sem í dag er Kanada . Síðustu hópflutningarnir áttu sér stað um miðja 19. öld . Í höfuðstaðnum Nuuk á Vestur-Grænlandi búa allmargir sem eru af evrópskum ættum . | D167: Hvar eru Inúítar í dag ? | E167: {'text': array(['Íbúar Grænlands voru tæp 56.000 árið 2019 og langflestir Inuítar'], dtype=object), 'answer_start': array([0])} | F167: IC | G167: IC | H167: OK
A168: nqii_2128 | B168: Bertrand Russell | C168: Bertrand Arthur William Russell ( 18. maí 1872 – 2. febrúar 1970 ) var breskur heimspekingur , rökfræðingur , stærðfræðingur og rithöfundur , sem skrifaði um mjög fjölbreytileg efni . Í heimspeki og stærðfræði er hann þekktastur fyrir að skrifa ásamt A.N. Whitehead bókina " Principia Mathematica " , sem kom út í þremur bindum á árunum 1910 til 1913 . Með verkinu hugðust þeir sýna fram á að hægt væri að leiða alla hreina stærðfræði út frá vissum rökfræðilegum frumsendum . Þeim tókst ekki ætlunarverkið en samt hefur verk þeirra reynst ákaflega áhrifaríkt . Russell er einnig mjög þekktur fyrir að uppgötva þversögnina , sem við hann er kennd : Russell-þversögnin ( " the Russell paradox " ) . | D168: Hvaða verk samdi Bertrand ? | E168: {'text': array([' " Principia Mathematica "', ' Principia Mathematica'], dtype=object), 'answer_start': array([272, 274])} | F168: OK | G168: OK | H168: IC
A169: nqii_8766 | B169: Sviss | C169: Sviss er ekki land einnar þjóðar , heldur bandalag mismunandi héraða sem ákváðu að tengjast af pólitískum ástæðum . Upphaflegu kantónurnar voru þýskumælandi en eftir því sem fleiri héruð bættust við , bættust frönsku - og ítölskumælandi íbúar við . Af sömu ástæðu eru einnig fleiri en eitt tungumál talað í landinu . Þjóðtungurnar eru fjórar : þýska ( svissnesk þýska ) um allt miðbik landsins , franska í vestri , ítalska fyrir sunnan og rómanska fyrir austan . Síðastnefnda málið er minnst útbreitt af málum þessum og er sambland latínu og germönsku frá tímum Rómverja . Langflestir tala þó þýsku eða tæp 64% . Um 20% tala frönsku . Að mestu leyti eru málamörkin skýr , sérstaklega í sveitum . En í nokkrum borgum eru tvö mál töluð , til dæmis í Fribourg ( Freiburg ) , Neuchâtel ( Neuenburg ) og Biel ( Bienne ) , þar sem bæði er töluð þýska og franska . | D169: Hvaða tungumál eru töluð í Sviss ? | E169: {'text': array([' þýska ( svissnesk þýska ) um allt miðbik landsins , franska í vestri , ítalska fyrir sunnan og rómanska fyrir austan'], dtype=object), 'answer_start': array([343])} | F169: OK | G169: OK | H169: OK
A170: nqii_11330 | B170: Guðríður Símonardóttir | C170: Guðríður Símonardóttir ( 1598 – 18. desember 1682 ) ( Tyrkja-Gudda ) var húsmóðir í Vestmannaeyjum sem var gift Eyjólfi Sólmundarsyni ( eða Sölmundarsyni ) ( d. 1636 ) , sem líklega hefur verið sjómaður þar . Árið 1627 komu svokallaðir Tyrkir og rændu í Vestmannaeyjum og víðar , meðal annars í Grindavík og á Djúpavogi . „ Tyrkirnir “ voru sjóræningjar frá Alsír og voru að líkindum allra þjóða kvikindi , en rán þetta er alltaf kallað Tyrkjaránið í Íslandssögunni . Rændu þeir bæði fólki og fé og var Guðríður ásamt Sölmundi , syni sínum , í hópi þeirra sem rænt var . | D170: Hver var Tyrkja-Gudda ? | E170: {'text': array(['Guðríður Símonardóttir'], dtype=object), 'answer_start': array([0])} | F170: F | G170: OK | H170: F
A171: nqii_17434 | B171: Bandaríkin | C171: Bandaríkin ( eða Bandaríki Norður-Ameríku , skammstafað BNA ) eru sambandslýðveldi sem er næststærsta ríki Norður-Ameríku að flatarmáli ( 9,83 milljónir km² ) og jafnframt það fjölmennasta með yfir 324 milljónir íbúa ( árið 2017 ) . Þau eru ennfremur fjórða stærsta land heims og það þriðja fjölmennasta . Þau teygja sig milli Atlantshafs og Kyrrahafs og eiga landamæri að Kanada í norðri og Mexíkó í suðri . Bandaríkin samanstanda af 50 fylkjum sem njóta nokkurs sjálfræðis í eigin efnum og hafa eigin löggjöf sem þó má ekki stangast á við stjórnarskrá Bandaríkjanna . Auk sambandsríkjanna hafa Bandaríkin lögsögu yfir ýmsum hjálendum víða um heim . | D171: Hver er fólksfjöldinn í Bandaríkjunum ? | E171: {'text': array([' yfir 324 milljónir íbúa ( árið 2017 )', ' yfir 324 milljónir íbúa', ' 324 milljónir íbúa ( árið 2017'], dtype=object), 'answer_start': array([192, 192, 197])} | F171: OK | G171: OK | H171: OK
A172: nqii_13935 | B172: Höfrungahlaup | C172: Helgi Hálfdánarson hélt því fram að það að " brjóta hval " væri forn leikur sem væri svipaður þeim sem nú er nefndur höfrungahlaup . Í bréfi til Gísla Jónssonar , þar sem hann reynir að útskýra línur í " Hulduljóð " i eftir Jónas Hallgrímsson , segir hann : | D172: Eftir hvern er ljóðið Hulduljóð ? | E172: {'text': array([' Jónas Hallgrímsson'], dtype=object), 'answer_start': array([223])} | F172: OK | G172: OK | H172: OK
A173: nqii_12013 | B173: Varsjá | C173: Á pólsku þýðir orðið " Warszawa " ( einnig stafað " Warszewa " eða " Warszowa " ) „ í eigu Warsz “ . " Warsz " er stytting á slavnesku karlmannanafni Warcisław ( nafn borgarinnar Wrocław á líka rætur að rekja til þessa mannanafns ) . Samkvæmt þjóðsögu var Warsz fiskimaður giftur konu sem hét Sawa . Sawa var hafmeyja sem bjó í ánni Visla nálægt borginni , sem Warsz varð ástfanginn í . Í rauninni var Warsz aðalsmaður sem var uppi á 12. eða 13. öld sem átti þorp sem á svæðinu þar sem hverfið Mariensztat liggur í dag . Opinbera heiti borgarinnar á pólsku er " miasto stołeczne Warszawa " ( höfuðborgin Varsjá ) . | D173: Hvað þýðir Warszawa á Pólsku ? | E173: {'text': array([' „ í eigu Warsz “', ' „ í eigu Warsz “ . " Warsz " er stytting á slavnesku karlmannanafni Warcisław'], dtype=object), 'answer_start': array([81, 81])} | F173: F | G173: OK | H173: OK
A174: nqii_16887 | B174: Nýja-Sjáland | C174: Fyrstu Evrópumennirnir sem komu til Nýja-Sjálands svo vitað sé voru hollenski landkönnuðurinn Abel Tasman og áhöfn hans árið 1642 . Til átaka kom milli þeirra og innfæddra og fjórir áhafnarmeðlimir og einn Maóri voru drepnir . Engir Evrópumenn komu til landsins eftir það fyrr en árið 1769 þegar James Cook kortlagði nær alla strandlengjuna . Í kjölfar Cooks komu fjöldi evrópskra og norðuramerískra hvalveiði - , selveiði - og kaupskipa til landsins . Þeir versluðu við innfædda og seldu þeim meðal annars mat , járnhluti og byssur . Kartaflan og byssan höfðu mikil áhrif á samfélag Maóra . Kartaflan gaf af sér stöðugri og meiri matarbirgðir en áður höfðu þekkst og gerði þannig lengri styrjaldir mögulegar . Byssustríðin milli ættbálka Maóra stóðu frá 1801 til 1840 og urðu til þess að milli 30 og 40.000 Maórar týndu lífinu . Ásamt sjúkdómum sem Evrópumenn báru með sér urðu þessi átök til þess að fjöldi Maóra varð aðeins 40% af því sem hann hafði verið fyrir komu Evrópumanna . Snemma á 19. öld hófu trúboðar starfsemi á eyjunum og sneru meirihluta Maóra smám saman til kristni . Árið 1788 var Arthur Phillip skipaður landstjóri yfir nýlendunni Nýja Suður-Wales sem samkvæmt skipunarbréfi hans náði líka yfir Nýja-Sjáland . Árið 1832 skipaði breska ríkisstjórnin James Busby ráðherra á eyjunum í kjölfar bænarskjals frá Maórum á Norðurey . Þegar franski ævintýramaðurinn Charles de Thierry tilkynnti árið 1835 að hann hygðist stofna ríki á Nýja-Sjálandi sendu Sameinaðir ættbálkar Nýja-Sjálands Vilhjálmi 4 . Sjálfstæðisyfirlýsingu Nýja-Sjálands þar sem þeir báðu um vernd . Nýja-Sjálandsfélagið hóf um sama leyti að kaupa land af ættbálkahöfðingjunum til að stofna nýlendu . Þetta varð til þess að Breska nýlenduskrifstofan sendi William Hobson til að gera tilkall til eyjanna fyrir hönd Bretlands og semja við ættbálkahöfðingjana . Waitangi-samningurinn var fyrst undirritaður í Eyjaflóa 6. febrúar 1840 . Þann 21. maí sama ár lýsti Hobson því yfir að eyjarnar væru breskt yfirráðasvæði þótt enn ættu margir eftir að undirrita samninginn . Eftir undirritun samningsins jókst landnám fólks frá Bretlandi . | D174: Hvaða löndum kom James Cook á kort ? | E174: {'text': array([' Nýja-Sjálands'], dtype=object), 'answer_start': array([35])} | F174: IC | G174: F | H174: F
A175: nqii_12551 | B175: Stjórnarskrá lýðveldisins Íslands | C175: 1. kafli stjórnarskrárinnar er eingöngu 2 greinar og tilgreinir fyrri greinin það að Ísland eigi að vera lýðveldi og að ríkisstjórnin skuli vera þingbundin , en það merkir að ríkisstjórnin er bundin af ákvörðunum Alþingis . Í 2. grein er svo kveðið á um þrískiptingu ríkisvaldsins og hvernig henni skuli háttað . Löggjafarvaldið er í höndum Alþingis og forseta Íslands , framkvæmdavaldið er hjá forsetanum , en hann felur það ráðherrum og öðrum stjórnvöldum sem skilgreind eru í lögum . Dómsvaldið er hjá dómendum . | D175: Hvenær var fyrsta greinin samin í stjórnarskránni ? | E175: {'text': array([' að Ísland eigi að vera lýðveldi og að ríkisstjórnin skuli vera þingbundin'], dtype=object), 'answer_start': array([81])} | F175: IC | G175: IC | H175: IC
... A185: nqii_3364 | B185: Þrjátíu ára stríðið | C185: Þrjátíu ára stríðið var röð styrjalda sem átti sér stað í Þýskalandi á árunum 1618 til 1648 . Öll helstu stórveldi Evrópu drógust inn í átökin . Lengi vel var stríðsins minnst sem skæðustu styrjaldar sem Evrópa hafði háð fram til Napóleonsstyrjaldanna . Herfarir hluteigandi og plágur sem þeim fylgdu lögðu mörg héruð Þýskalands því sem næst í auðn . | D185: Hverjir tóku þátt í Þrjátíu ára stríðinu ? | E185: {'text': array([' Öll helstu stórveldi Evrópu drógust inn í átökin'], dtype=object), 'answer_start': array([93])} | F185: OK | G185: OK | H185: OK
A186: nqii_4609 | B186: Bolungarvík | C186: Bolungarvík er kaupstaður á Vestfjörðum og sjálfstætt sveitarfélag , við samnefnda vík , yst í Ísafjarðardjúpi . Hún er ein elsta verstöð landsins og er stutt í góð fiskimið . Áður en bærinn fékk kaupstaðarréttindi hét sveitarfélagið Hólshreppur . Þann 1. janúar 2016 var íbúarfjöldi Bolungarvíkur 904 manns . Bolungarvík er næstfjölmennasti bærinn á Vestfjörðum og þriðja fjölmennasta sveitarfélagið á eftir Vesturbyggð ( 1013 íbúar ) og Ísafjarðarbæ ( 3623 íbúar ) . | D186: Hvað búa margir í Bolungarvík ? | E186: {'text': array([' 904', ' 904 manns', ' 904'], dtype=object), 'answer_start': array([297, 297, 297])} | F186: OK | G186: OK | H186: OK | I186: Rétt - í samhengi inntakstextans
A187: nqii_742 | B187: Sálfræði | C187: Það mikilvægasta var að aðferðir og viðhorf Wilhelms Wundt og William James voru laus við yfirskilvitlegar trúarlegar útskýringar á hugsun manna eða hegðun , sem losaði sálfræðina undan viðjum heimspeki og guðfræði , og lagði grunninn að nútíma sálfræði sem vísindagrein . | D187: Hver kom fyrstur með hugtakið sálfræði ? | E187: {'text': array([' Wilhelms Wundt'], dtype=object), 'answer_start': array([43])} | F187: IC | G187: IC | H187: IC
A188: nqii_5451 | B188: Kílógramm | C188: Kílógrammið var upphaflega skilgreint sem massi 1 lítra af vatni við 4° Celsius og 1 atm ( staðalaðstæður þrýstings ) . Þessi skilgreining olli nokkrum vandkvæðum þar sem þéttleiki vatns er háður þrýstingi og þrýstingur er háður massa ( og þannig er skilgreiningin á mælieiningunni orðin háð sjálfri sér ) . | D188: Hver er skilgreiningin á kílói ? | E188: {'text': array(['Kílógrammið var upphaflega skilgreint sem massi 1 lítra af vatni við 4° Celsius og 1 atm'], dtype=object), 'answer_start': array([0])} | F188: F | G188: F | H188: OK
A189: nqii_3514 | B189: Hestur | C189: Folöld fæðast venjulega á vorin eftir 336 daga langa meðgöngu og kallast það að merin " kasti " . Folöldin kallast " merfolald " og " hestfolald " eftir kynjum . Fleirburar eru sjaldgæfir , en þó koma tvíburar fyrir . Merar eru þeim eiginleikum gæddar að geta gengið lengur með folaldið ef hart er í ári og gengið þá allt að 365 daga meðgöngu . Þetta er algengt á kaldari svæðum , svo sem á Íslandi , vegna þess hve vorhret eru algeng . | D189: Hvað ganga hryssur lengi með folöld sín ? | E189: {'text': array(['Folöld fæðast venjulega á vorin eftir 336 daga langa meðgöngu'], dtype=object), 'answer_start': array([0])} | F189: OK | G189: OK | H189: OK
A190: nqii_14849 | B190: Völuspá | C190: Völuspá er kvæði tengt norrænni goðafræði og í dag ein helsta heimild um hana . Í ritinu er sagt frá sögu heimsins , allt frá sköpun til ragnaraka . Boðskapurinn birtist lesanda í gegn um samtal Völvu og Óðins þar sem Völvan segir frá ýmsum fróðleik sem varðar sköpun heims og mannfólks . Völvan rekur atburðarás veraldarinnar frá því að Sól og Máni , Æsir og Vanir , mannfólk og jötnar voru sköpuð , og hvernig þessar verur drífa heiminn til ragnarraka með mistökum og spillingu sín á milli . Eftir ragnarök segir Völvan þó að líf muni rísa á ný , hreint og óspillt , og hvernig menn og verur muni græða heiminn á ný . Völuspá samanstendur af 58 - 67 vísum sem ortar eru undir fornyrðislagi , en fjöldi kvæða fer eftir útgefanda . Völuspá er hluti Eddukvæða og varðveitt í Konungsbók Eddukvæða frá árinu 1270 . Þrátt fyrir að Völuspáin sé almennt tengd goðafræðinni má sjá fjölda tilvitnana í kristna trú , s.s. um fæðingu Jesú Krists . Því má leiða líkum að því að höfundur kunni að hafa velt fyrir sér bæði norrænu goðafræðinni og kristnu trúnni . | D190: Hvar er völuspá geymd ? | E190: {'text': array([' Völuspá er hluti Eddukvæða og varðveitt í Konungsbók Eddukvæða frá árinu 1270', ' Konungsbók Eddukvæða'], dtype=object), 'answer_start': array([731, 773])} | F190: F | G190: OK | H190: OK
A191: nqii_16817 | B191: Kínverska | C191: Aðrar algengar mállýskur eru kantónska ( 广东话 ; " Guǎngdōnghuà " ) sem er t.d. töluð í Kanton-héraðinu og Hong Kong , Sichuan-mállýska ( 四川话 " ; Sìchuānhuà " ) sem er töluð í Sichuan-héraði og Shanghai-mállýskan ( 上海话 ; " Shànghǎihuà " ) sem er aðallega bundin við borgina Sjanghæ . | D191: Hvaða kínverska mállýska er töluð í Hong Kong ? | E191: {'text': array([' kantónska', ' kantónska ( 广东话 ; " Guǎngdōnghuà " ) sem er t.d. töluð í Kanton-héraðinu og Hong Kong'], dtype=object), 'answer_start': array([28, 28])} | F191: OK | G191: OK | H191: OK
A192: nqii_11068 | B192: Sófistar | C192: Sófistar ( forngríska : σοφιστής , " sofistēs " ) eða fræðarar voru viskukennarar og róttæklingar í Grikklandi til forna . Hugtakið er dregið af gríska lýsingarorðinu σοφός , " sofos " , sem merkir „ vitur “ . Sófistar ferðuðust borga á milli og héldu námskeið og þénuðu sumir vel á kennslunni . Þeir voru sannfærðir um að margt sem talið var heilagt að gömlum sið og talið liggja í eðli hluta væri í raun merki um mannlega hagsmuni og árangur af mannlegum ákvörðunum . Þeir gagnrýndu kynþáttafordóma , þrælahald og kvennakúgun . Hafa ber í huga að sófistarnir voru sundurleitur hópur sem hafði ólíkar skoðanir um margt . | D192: Hverjir voru Sófistarnir ? | E192: {'text': array(['Sófistar ( forngríska : σοφιστής , " sofistēs " ) eða fræðarar voru viskukennarar og róttæklingar í Grikklandi til forna'], dtype=object), 'answer_start': array([0])} | F192: OK | G192: OK | H192: OK
A193: nqii_1195 | B193: Reykjavík | C193: < onlyinclude > Reykjavík er höfuðborg Íslands , fjölmennasta sveitarfélag landsins og eina borgin . Þannig er Reykjavík efnahagsleg , menningarleg og stjórnmálaleg þungamiðja landsins . Tæplega 131.000 manns búa í Reykjavík ( 2019 ) , þar af eru um 11% innflytjendur . Íbúar höfuðborgarsvæðisins eru yfir 220 þúsund í sjö sveitarfélögum . Opinbert heiti sveitarfélagsins Reykjavíkur er Reykjavíkurborg . | D193: Hvað búa margir í Reykjavík ? | E193: {'text': array([' Tæplega 131.000 manns', ' yfir 220 þúsund', ' Tæplega 131.000 manns búa í Reykjavík ( 2019 )', ' Tæplega 131.000 manns', ' 131.000 manns', ' Tæplega 131.000 manns'], dtype=object), 'answer_start': array([186, 300, 186, 186, 194, 186])} | F193: OK | G193: OK | H193: OK
A194: nqii_9764 | B194: Íslensku jólasveinarnir | C194: Í fyrstu útgáfu af Þjóðsögum Jóns Árnasonar koma nöfn jólasveinana fyrst fyrir á prenti . Jón hafði kringum 1860 fengið þrjár nafnarunur með heitum á jólasveinum . Ekki er alveg ljóst í hvaða röð hann fær þær , en hér eru þær nefndar eftir aldri heimildarmanna hans . Hinn elsti þeirra er síra Páll Jónsson , fæddur 1812 og alinn upp fram yfir tvítugt vestur í Dölum , en hafði verið prestur norður í Eyjafirði í næstum 20 ár , á Myrká og Völlum í Svarfaðardal , þegar hann sendi Jóni þessi 13 nöfn : | D194: Hversu margir eru íslensku jólasveinarnir ? | E194: {'text': array([' 13'], dtype=object), 'answer_start': array([490])} | F194: F | G194: OK | H194: F
A195: nqii_12767 | B195: Kárahnjúkavirkjun | C195: Kárahnjúkavirkjun öðru nafni Fljótsdalsstöð er 690 MW vatnsaflsvirkjun á hálendi Íslands norðan Vatnajökuls . | D195: Hvar er Kárahnjúkavirkjun ? | E195: {'text': array([' á hálendi Íslands norðan Vatnajökuls', ' á hálendi Íslands norðan Vatnajökuls', ' norðan Vatnajökuls'], dtype=object), 'answer_start': array([70, 70, 88])} | F195: OK | G195: OK | H195: OK
A196: nqii_17105 | B196: Búrfell upp af Hafnarfirði | C196: Búrfell upp af Hafnarfirði er eldstöð af þeirri gerð sem kallast eldborg . Eldborgir einkennast af því að gos hefur átt sér stað á stuttri sprungu eða pípulaga gosrás og myndar því stakan aðalgíg og stundum smærri gíga þar hjá . Engir hliðargígar eru hjá Búrfelli , það stendur eitt og stakt , 180 m hátt yfir sjó , hlaðið úr gjalli og hraunkleprum . Hraunstraumarnir sem runnu frá gígnum nefnast einu nafni Búrfellshraun en hafa fjölmörg sérnöfn eftir einstökum hlutum hraunsins , svo sem Smyrlabúðarhraun , Gráhelluhraun , Lækjarbotnahraun , Urriðakotshraun , Hafnarfjarðarhraun , Garðahraun og Gálgahraun . | D196: Hversu hátt er Búrfell í Grímsnesi ? | E196: {'text': array([' 180 m hátt yfir sjó', ' 180 m hátt yfir sjó'], dtype=object), 'answer_start': array([293, 293])} | F196: OK | G196: OK | H196: OK
A197: nqii_3570 | B197: Kim Jong-un | C197: Kim Jong-un ( f. 8. janúar 1984 ) er æðsti leiðtogi og einræðisherra Norður-Kóreu . Hann er sonur forvera síns , Kims Jong-il , og sonarsonur stofnanda Norður-Kóreu , Kims Il-sung . Kim Jong-un tók við sem leiðtogi Norður-Kóreu eftir dauða föður síns árið 2011 . Kim Jong-un er fyrsti leiðtogi Norður-Kóreu sem er fæddur eftir stofnun ríkisins árið 1945 . | D197: Hver er höfuðborg Bólivíu ? | E197: {'text': array([' Kim Jong-un tók við sem leiðtogi Norður-Kóreu'], dtype=object), 'answer_start': array([181])} | F197: IC | G197: IC | H197: IC
A198: nqii_5971 | B198: Beijing | C198: Beijing er næstfjölmennasta borg landsins , næst á eftir Sjanghæ . Um 19 milljónir búa þar og allt að 24 milljónir á stórborgarsvæðinu ( 2017 ) . Beijing er miðpunktur mennta og menningar auk þess sem stjórnvöld stýra landinu þaðan . Sjanghæ og Hong Kong eru hins vegar meira áberandi hvað varðar efnahagsleg umsvif . Borgin er kunn fyrir ríkulegar hallir , hof og gríðarstóra steinveggi og hlið . Listasöfn borgarinnar og háskólar hennar gera hana að menningarmiðstöð landsins . | D198: Hvað búa margir í Peking ? | E198: {'text': array([' Um 19 milljónir búa þar og allt að 24 milljónir á stórborgarsvæðinu ( 2017 )', ' allt að 24 milljónir'], dtype=object), 'answer_start': array([66, 93])} | F198: OK | G198: OK | H198: OK
... A214: nqii_1442 | B214: Siðaskiptin á Íslandi | C214: Siðaskiptin á Íslandi urðu um miðja 16. öld og eru gjarnan miðuð við aftöku Jóns Arasonar biskups á Hólum haustið 1550 , en hann var tekinn af lífi ásamt sonum sínum í Skálholti . Siðbreytingin hófst þó töluvert fyrir líflát Jóns , en aftakan markaði þáttaskil vegna þess að biskupinn hafði verið helsti andstæðingur hennar á Íslandi og þegar hann var úr sögunni varð miklu auðveldara að koma breytingum í kring . | D214: Hvenær áttu siðaskiptin sér stað ? | E214: {'text': array([' um miðja 16. öld og eru gjarnan miðuð við aftöku Jóns Arasonar biskups á Hólum haustið 1550', ' haustið 1550'], dtype=object), 'answer_start': array([ 26, 105])} | F214: OK | G214: OK | H214: OK

Sheet icelandic_qa_random_sample
A1: example_id | B1: question | C1: answer | D1: answer_start | E1: context | F1: rater_1 | G1: rater_2 | H1: rater_3 | I1: skýringar
A2: 1340 | B2: Hvaða kallaðist aðferð sem var notuð á Íslandi til að aðskilja ær og lömb á vorin? | C2: Fráfærur. | E2: Fráfærur kallaðist það þegar ær og lömb voru aðskilin á vorin til þess að unnt væri að nytja mjólkina. Þær voru tíðkaðar á hverjum bæ á Íslandi um margar aldir. Lömbin voru kefld þannig að þau náðu ekki að sjúga mæður sínar en þó meira um að stíað væri, lömbin lokuð inni þangað til fært var frá. Fráfærnatími var um Jónsmessu til forna en mánuðurinn á undan var svonefnd stekktíð, en þá voru lömbin enn með mæðrum sínum en sett í lambakró á stekknum á kvöldin og höfð þar um nóttina en ærnar gengu lausar á meðan og voru svo mjólkaðar að morgni, áður en lömbunum var hleypt út. Þetta var líka kallað að stía lömbin og stóð yfirleitt í um tvær vikur. Allan geldfénað var skylda að reka á afrétt, eingöngu mátti málnytupeningur (ær sem eru mjólkaðar) vera heima eða í seljum á sumrin. Í Jónsbók var ákvæði um að geldur peningur skyldi vera farinn úr heimahögum þegar tveir mánuðir væru liðnir af sumri og ekki mátti reka fé aftur heim fyrir tvímánuð (síðustu viku í ágúst) en í réttarbót Eiríks konungs Magnússonar frá 1294 var því breytt þannig að hreppsstjórnarmenn ákváðu hvenær fé yrði rekið á fjall og heim eftir því sem hentaði. Þegar lömbin voru um það bil sex vikna voru þau svo rekin á fjall eða í haga fjarri ánum og látin sjá um sig sjálf en ærnar hafðar heima og mjólkaðar kvölds og morgna. Smalinn sat yfir þeim, að minnsta kosti á daginn. Ær sem fært hafði verið frá og voru mjólkaðar kölluðust kvíaaær. Stundum var setið yfir lömbunum fyrstu vikuna og voru þau þá oft höfð í hafti svo auðveldara væri að halda þeim saman. Sauðamjólkin var mikið notuð til skyrgerðar, ein sér eða blönduð kúamjólk, en einnig var gert úr henni smjör og ostar. Fráfærur tíðkuðust fram á 20. öldina en lögðust víðast hvar af á árunum 1915-1940, meðal annars vegna mikillar verðhækkunar á lambakjöti á stríðsárunum fyrri, svo að það borgaði sig betur að láta lömbin njóta mjólkurinnar en mjólka ærnar. Síðast var fært frá svo vitað sé á Kirkjubóli í Bjarnardal í Önundarfirði sumarið 1951 eða 1952. Síðasti fráfærusmalinn á Íslandi var Kristján Bersi Ólafsson, síðar blaðamaður, ritstjóri, kennari og skólameistari í Flensborg. Fráfærur á Kirkjubóli má sjá í Vestfjarðamynd Guðlaugs Rósinkrans, sem Kjartan Ó. Bjarnason tók sennilega um 1950. Kvikmynd Ósvaldar Knudsens, Fráfærur, er tekin á Kirkjubóli. Myndin var frumsýnd 1958, en tekin upp fyrr, líklega 1955. Þær fráfærur voru leiknar fyrir kvikmyndagerðarmanninn. Nú er líka talað um fráfærur þegar átt er við aðskilnað afkvæmis og móður, t.d. gríss frá gyltu. Tilvísanir Íslensk sauðfjárrækt | F2: OK | G2: OK | H2: OK
